package com.google.android.gms.measurement.internal;

import android.text.TextUtils;
import androidx.collection.ArrayMap;
import com.google.android.gms.common.internal.Preconditions;
import com.google.android.gms.internal.measurement.zzfv;
import com.google.android.gms.internal.measurement.zzfw;
import com.google.android.gms.internal.measurement.zzfx;
import com.google.android.gms.internal.measurement.zzfy;
import com.google.android.gms.internal.measurement.zzfz;
import com.google.android.gms.internal.measurement.zzge;
import com.google.android.gms.internal.measurement.zzgg;
import com.google.android.gms.internal.measurement.zzgl;
import java.math.BigDecimal;
import java.util.ArrayList;
import java.util.Arrays;
import java.util.HashSet;
import java.util.Iterator;
import java.util.List;
import java.util.Locale;
import java.util.Map;
import java.util.Set;
import java.util.regex.Matcher;
import java.util.regex.Pattern;
import java.util.regex.PatternSyntaxException;

final class zzj
  extends zzez
{
  zzj(zzfa paramZzfa)
  {
    super(paramZzfa);
  }
  
  private final Boolean zza(double paramDouble, zzfx paramZzfx)
  {
    try
    {
      paramZzfx = zza(new BigDecimal(paramDouble), paramZzfx, Math.ulp(paramDouble));
      return paramZzfx;
    }
    catch (NumberFormatException paramZzfx)
    {
      for (;;) {}
    }
    return null;
  }
  
  private final Boolean zza(long paramLong, zzfx paramZzfx)
  {
    try
    {
      paramZzfx = zza(new BigDecimal(paramLong), paramZzfx, 0.0D);
      return paramZzfx;
    }
    catch (NumberFormatException paramZzfx)
    {
      for (;;) {}
    }
    return null;
  }
  
  private final Boolean zza(zzfv paramZzfv, String paramString, zzgg[] paramArrayOfZzgg, long paramLong)
  {
    Object localObject1 = zzavi;
    int j = 0;
    Boolean localBoolean = Boolean.valueOf(false);
    if (localObject1 != null)
    {
      localObject1 = zza(paramLong, zzavi);
      if (localObject1 == null) {
        return null;
      }
      if (!((Boolean)localObject1).booleanValue()) {
        return localBoolean;
      }
    }
    Object localObject2 = new HashSet();
    localObject1 = zzavg;
    int k = localObject1.length;
    int i = 0;
    Object localObject3;
    while (i < k)
    {
      localObject3 = localObject1[i];
      if (TextUtils.isEmpty(zzavn))
      {
        zzgo().zzjg().zzg("null or empty param name in filter. event", zzgl().zzbs(paramString));
        return null;
      }
      ((Set)localObject2).add(zzavn);
      i += 1;
    }
    localObject1 = new ArrayMap();
    k = paramArrayOfZzgg.length;
    i = 0;
    while (i < k)
    {
      localObject3 = paramArrayOfZzgg[i];
      if (((Set)localObject2).contains(name)) {
        if (zzawx != null)
        {
          ((Map)localObject1).put(name, zzawx);
        }
        else if (zzauh != null)
        {
          ((Map)localObject1).put(name, zzauh);
        }
        else if (zzamp != null)
        {
          ((Map)localObject1).put(name, zzamp);
        }
        else
        {
          zzgo().zzjg().zze("Unknown value for param. event, param", zzgl().zzbs(paramString), zzgl().zzbt(name));
          return null;
        }
      }
      i += 1;
    }
    paramArrayOfZzgg = zzavg;
    k = paramArrayOfZzgg.length;
    i = j;
    while (i < k)
    {
      paramZzfv = paramArrayOfZzgg[i];
      boolean bool = Boolean.TRUE.equals(zzavm);
      localObject2 = zzavn;
      if (TextUtils.isEmpty((CharSequence)localObject2))
      {
        zzgo().zzjg().zzg("Event has empty param name. event", zzgl().zzbs(paramString));
        return null;
      }
      localObject3 = ((Map)localObject1).get(localObject2);
      if ((localObject3 instanceof Long))
      {
        if (zzavl == null)
        {
          zzgo().zzjg().zze("No number filter for long param. event, param", zzgl().zzbs(paramString), zzgl().zzbt((String)localObject2));
          return null;
        }
        paramZzfv = zza(((Long)localObject3).longValue(), zzavl);
        if (paramZzfv == null) {
          return null;
        }
        if ((true ^ paramZzfv.booleanValue() ^ bool)) {
          return localBoolean;
        }
      }
      else if ((localObject3 instanceof Double))
      {
        if (zzavl == null)
        {
          zzgo().zzjg().zze("No number filter for double param. event, param", zzgl().zzbs(paramString), zzgl().zzbt((String)localObject2));
          return null;
        }
        paramZzfv = zza(((Double)localObject3).doubleValue(), zzavl);
        if (paramZzfv == null) {
          return null;
        }
        if ((true ^ paramZzfv.booleanValue() ^ bool)) {
          return localBoolean;
        }
      }
      else
      {
        if (!(localObject3 instanceof String)) {
          break label725;
        }
        if (zzavk != null)
        {
          paramZzfv = zza((String)localObject3, zzavk);
        }
        else
        {
          if (zzavl == null) {
            break label694;
          }
          localObject3 = (String)localObject3;
          if (!zzfg.zzcp((String)localObject3)) {
            break label663;
          }
          paramZzfv = zza((String)localObject3, zzavl);
        }
        if (paramZzfv == null) {
          return null;
        }
        if ((true ^ paramZzfv.booleanValue() ^ bool)) {
          return localBoolean;
        }
      }
      i += 1;
      continue;
      label663:
      zzgo().zzjg().zze("Invalid param value for number filter. event, param", zzgl().zzbs(paramString), zzgl().zzbt((String)localObject2));
      return null;
      label694:
      zzgo().zzjg().zze("No filter for String param. event, param", zzgl().zzbs(paramString), zzgl().zzbt((String)localObject2));
      return null;
      label725:
      if (localObject3 == null)
      {
        zzgo().zzjl().zze("Missing param for filter. event, param", zzgl().zzbs(paramString), zzgl().zzbt((String)localObject2));
        return localBoolean;
      }
      zzgo().zzjg().zze("Unknown param type. event, param", zzgl().zzbs(paramString), zzgl().zzbt((String)localObject2));
      return null;
    }
    return Boolean.valueOf(true);
  }
  
  private final Boolean zza(zzfy paramZzfy, zzgl paramZzgl)
  {
    paramZzfy = zzavv;
    if (paramZzfy == null)
    {
      zzgo().zzjg().zzg("Missing property filter. property", zzgl().zzbu(name));
      return null;
    }
    boolean bool = Boolean.TRUE.equals(zzavm);
    if (zzawx != null)
    {
      if (zzavl == null)
      {
        zzgo().zzjg().zzg("No number filter for long property. property", zzgl().zzbu(name));
        return null;
      }
      return zza(zza(zzawx.longValue(), zzavl), bool);
    }
    if (zzauh != null)
    {
      if (zzavl == null)
      {
        zzgo().zzjg().zzg("No number filter for double property. property", zzgl().zzbu(name));
        return null;
      }
      return zza(zza(zzauh.doubleValue(), zzavl), bool);
    }
    if (zzamp != null)
    {
      if (zzavk == null)
      {
        if (zzavl == null)
        {
          zzgo().zzjg().zzg("No string or number filter defined. property", zzgl().zzbu(name));
          return null;
        }
        if (zzfg.zzcp(zzamp)) {
          return zza(zza(zzamp, zzavl), bool);
        }
        zzgo().zzjg().zze("Invalid user property value for Numeric number filter. property, value", zzgl().zzbu(name), zzamp);
        return null;
      }
      return zza(zza(zzamp, zzavk), bool);
    }
    zzgo().zzjg().zzg("User property has no value, property", zzgl().zzbu(name));
    return null;
  }
  
  private static Boolean zza(Boolean paramBoolean, boolean paramBoolean1)
  {
    if (paramBoolean == null) {
      return null;
    }
    return Boolean.valueOf(paramBoolean.booleanValue() ^ paramBoolean1);
  }
  
  private final Boolean zza(String paramString1, int paramInt, boolean paramBoolean, String paramString2, List<String> paramList, String paramString3)
  {
    if (paramString1 == null) {
      return null;
    }
    if (paramInt == 6)
    {
      if ((paramList == null) || (paramList.size() == 0)) {
        return null;
      }
    }
    else if (paramString2 == null) {
      return null;
    }
    String str = paramString1;
    if (!paramBoolean) {
      if (paramInt == 1) {
        str = paramString1;
      } else {
        str = paramString1.toUpperCase(Locale.ENGLISH);
      }
    }
    switch (paramInt)
    {
    default: 
      return null;
    case 6: 
      return Boolean.valueOf(paramList.contains(str));
    case 5: 
      return Boolean.valueOf(str.equals(paramString2));
    case 4: 
      return Boolean.valueOf(str.contains(paramString2));
    case 3: 
      return Boolean.valueOf(str.endsWith(paramString2));
    case 2: 
      return Boolean.valueOf(str.startsWith(paramString2));
    }
    if (paramBoolean) {
      paramInt = 0;
    } else {
      paramInt = 66;
    }
    try
    {
      paramBoolean = Pattern.compile(paramString3, paramInt).matcher(str).matches();
      return Boolean.valueOf(paramBoolean);
    }
    catch (PatternSyntaxException paramString1)
    {
      for (;;) {}
    }
    zzgo().zzjg().zzg("Invalid regular expression in REGEXP audience filter. expression", paramString3);
    return null;
  }
  
  private final Boolean zza(String paramString, zzfx paramZzfx)
  {
    if (!zzfg.zzcp(paramString)) {
      return null;
    }
    try
    {
      paramString = zza(new BigDecimal(paramString), paramZzfx, 0.0D);
      return paramString;
    }
    catch (NumberFormatException paramString) {}
    return null;
  }
  
  private final Boolean zza(String paramString, zzfz paramZzfz)
  {
    Preconditions.checkNotNull(paramZzfz);
    if (paramString == null) {
      return null;
    }
    if (zzavw != null)
    {
      if (zzavw.intValue() == 0) {
        return null;
      }
      if (zzavw.intValue() == 6)
      {
        if ((zzavz == null) || (zzavz.length == 0)) {
          return null;
        }
      }
      else if (zzavx == null) {
        return null;
      }
      int j = zzavw.intValue();
      Object localObject1 = zzavy;
      int i = 0;
      boolean bool;
      if ((localObject1 != null) && (zzavy.booleanValue())) {
        bool = true;
      } else {
        bool = false;
      }
      if ((!bool) && (j != 1) && (j != 6)) {
        localObject1 = zzavx.toUpperCase(Locale.ENGLISH);
      } else {
        localObject1 = zzavx;
      }
      Object localObject2;
      if (zzavz == null)
      {
        paramZzfz = null;
      }
      else
      {
        localObject2 = zzavz;
        if (bool)
        {
          paramZzfz = Arrays.asList((Object[])localObject2);
        }
        else
        {
          paramZzfz = new ArrayList();
          int k = localObject2.length;
          while (i < k)
          {
            paramZzfz.add(localObject2[i].toUpperCase(Locale.ENGLISH));
            i += 1;
          }
        }
      }
      if (j == 1) {
        localObject2 = localObject1;
      } else {
        localObject2 = null;
      }
      return zza(paramString, j, bool, (String)localObject1, paramZzfz, (String)localObject2);
    }
    return null;
  }
  
  /* Error */
  private static Boolean zza(BigDecimal paramBigDecimal, zzfx paramZzfx, double paramDouble)
  {
    // Byte code:
    //   0: aload_1
    //   1: invokestatic 297	com/google/android/gms/common/internal/Preconditions:checkNotNull	(Ljava/lang/Object;)Ljava/lang/Object;
    //   4: pop
    //   5: aload_1
    //   6: getfield 335	com/google/android/gms/internal/measurement/zzfx:zzavo	Ljava/lang/Integer;
    //   9: ifnull +405 -> 414
    //   12: aload_1
    //   13: getfield 335	com/google/android/gms/internal/measurement/zzfx:zzavo	Ljava/lang/Integer;
    //   16: invokevirtual 308	java/lang/Integer:intValue	()I
    //   19: ifne +5 -> 24
    //   22: aconst_null
    //   23: areturn
    //   24: aload_1
    //   25: getfield 335	com/google/android/gms/internal/measurement/zzfx:zzavo	Ljava/lang/Integer;
    //   28: invokevirtual 308	java/lang/Integer:intValue	()I
    //   31: iconst_4
    //   32: if_icmpne +19 -> 51
    //   35: aload_1
    //   36: getfield 338	com/google/android/gms/internal/measurement/zzfx:zzavr	Ljava/lang/String;
    //   39: ifnull +10 -> 49
    //   42: aload_1
    //   43: getfield 341	com/google/android/gms/internal/measurement/zzfx:zzavs	Ljava/lang/String;
    //   46: ifnonnull +14 -> 60
    //   49: aconst_null
    //   50: areturn
    //   51: aload_1
    //   52: getfield 344	com/google/android/gms/internal/measurement/zzfx:zzavq	Ljava/lang/String;
    //   55: ifnonnull +5 -> 60
    //   58: aconst_null
    //   59: areturn
    //   60: aload_1
    //   61: getfield 335	com/google/android/gms/internal/measurement/zzfx:zzavo	Ljava/lang/Integer;
    //   64: invokevirtual 308	java/lang/Integer:intValue	()I
    //   67: istore 4
    //   69: aload_1
    //   70: getfield 335	com/google/android/gms/internal/measurement/zzfx:zzavo	Ljava/lang/Integer;
    //   73: invokevirtual 308	java/lang/Integer:intValue	()I
    //   76: iconst_4
    //   77: if_icmpne +62 -> 139
    //   80: aload_1
    //   81: getfield 338	com/google/android/gms/internal/measurement/zzfx:zzavr	Ljava/lang/String;
    //   84: invokestatic 196	com/google/android/gms/measurement/internal/zzfg:zzcp	(Ljava/lang/String;)Z
    //   87: ifeq +50 -> 137
    //   90: aload_1
    //   91: getfield 341	com/google/android/gms/internal/measurement/zzfx:zzavs	Ljava/lang/String;
    //   94: invokestatic 196	com/google/android/gms/measurement/internal/zzfg:zzcp	(Ljava/lang/String;)Z
    //   97: ifne +5 -> 102
    //   100: aconst_null
    //   101: areturn
    //   102: new 15	java/math/BigDecimal
    //   105: dup
    //   106: aload_1
    //   107: getfield 338	com/google/android/gms/internal/measurement/zzfx:zzavr	Ljava/lang/String;
    //   110: invokespecial 292	java/math/BigDecimal:<init>	(Ljava/lang/String;)V
    //   113: astore 10
    //   115: new 15	java/math/BigDecimal
    //   118: dup
    //   119: aload_1
    //   120: getfield 341	com/google/android/gms/internal/measurement/zzfx:zzavs	Ljava/lang/String;
    //   123: invokespecial 292	java/math/BigDecimal:<init>	(Ljava/lang/String;)V
    //   126: astore 11
    //   128: aload 10
    //   130: astore_1
    //   131: aconst_null
    //   132: astore 10
    //   134: goto +35 -> 169
    //   137: aconst_null
    //   138: areturn
    //   139: aload_1
    //   140: getfield 344	com/google/android/gms/internal/measurement/zzfx:zzavq	Ljava/lang/String;
    //   143: invokestatic 196	com/google/android/gms/measurement/internal/zzfg:zzcp	(Ljava/lang/String;)Z
    //   146: ifne +5 -> 151
    //   149: aconst_null
    //   150: areturn
    //   151: new 15	java/math/BigDecimal
    //   154: dup
    //   155: aload_1
    //   156: getfield 344	com/google/android/gms/internal/measurement/zzfx:zzavq	Ljava/lang/String;
    //   159: invokespecial 292	java/math/BigDecimal:<init>	(Ljava/lang/String;)V
    //   162: astore 10
    //   164: aconst_null
    //   165: astore_1
    //   166: aload_1
    //   167: astore 11
    //   169: iload 4
    //   171: iconst_4
    //   172: if_icmpne +9 -> 181
    //   175: aload_1
    //   176: ifnonnull +10 -> 186
    //   179: aconst_null
    //   180: areturn
    //   181: aload 10
    //   183: ifnull +231 -> 414
    //   186: iconst_0
    //   187: istore 7
    //   189: iconst_0
    //   190: istore 5
    //   192: iconst_0
    //   193: istore 8
    //   195: iconst_0
    //   196: istore 9
    //   198: iconst_0
    //   199: istore 6
    //   201: iload 4
    //   203: iconst_1
    //   204: if_icmpeq +187 -> 391
    //   207: iload 4
    //   209: iconst_2
    //   210: if_icmpeq +158 -> 368
    //   213: iload 4
    //   215: iconst_3
    //   216: if_icmpeq +47 -> 263
    //   219: iload 4
    //   221: iconst_4
    //   222: if_icmpeq +5 -> 227
    //   225: aconst_null
    //   226: areturn
    //   227: iload 6
    //   229: istore 5
    //   231: aload_0
    //   232: aload_1
    //   233: invokevirtual 348	java/math/BigDecimal:compareTo	(Ljava/math/BigDecimal;)I
    //   236: iconst_m1
    //   237: if_icmpeq +20 -> 257
    //   240: iload 6
    //   242: istore 5
    //   244: aload_0
    //   245: aload 11
    //   247: invokevirtual 348	java/math/BigDecimal:compareTo	(Ljava/math/BigDecimal;)I
    //   250: iconst_1
    //   251: if_icmpeq +6 -> 257
    //   254: iconst_1
    //   255: istore 5
    //   257: iload 5
    //   259: invokestatic 44	java/lang/Boolean:valueOf	(Z)Ljava/lang/Boolean;
    //   262: areturn
    //   263: dload_2
    //   264: dconst_0
    //   265: dcmpl
    //   266: ifeq +84 -> 350
    //   269: iload 7
    //   271: istore 5
    //   273: aload_0
    //   274: aload 10
    //   276: new 15	java/math/BigDecimal
    //   279: dup
    //   280: dload_2
    //   281: invokespecial 18	java/math/BigDecimal:<init>	(D)V
    //   284: new 15	java/math/BigDecimal
    //   287: dup
    //   288: iconst_2
    //   289: invokespecial 351	java/math/BigDecimal:<init>	(I)V
    //   292: invokevirtual 355	java/math/BigDecimal:multiply	(Ljava/math/BigDecimal;)Ljava/math/BigDecimal;
    //   295: invokevirtual 358	java/math/BigDecimal:subtract	(Ljava/math/BigDecimal;)Ljava/math/BigDecimal;
    //   298: invokevirtual 348	java/math/BigDecimal:compareTo	(Ljava/math/BigDecimal;)I
    //   301: iconst_1
    //   302: if_icmpne +42 -> 344
    //   305: iload 7
    //   307: istore 5
    //   309: aload_0
    //   310: aload 10
    //   312: new 15	java/math/BigDecimal
    //   315: dup
    //   316: dload_2
    //   317: invokespecial 18	java/math/BigDecimal:<init>	(D)V
    //   320: new 15	java/math/BigDecimal
    //   323: dup
    //   324: iconst_2
    //   325: invokespecial 351	java/math/BigDecimal:<init>	(I)V
    //   328: invokevirtual 355	java/math/BigDecimal:multiply	(Ljava/math/BigDecimal;)Ljava/math/BigDecimal;
    //   331: invokevirtual 360	java/math/BigDecimal:add	(Ljava/math/BigDecimal;)Ljava/math/BigDecimal;
    //   334: invokevirtual 348	java/math/BigDecimal:compareTo	(Ljava/math/BigDecimal;)I
    //   337: iconst_m1
    //   338: if_icmpne +6 -> 344
    //   341: iconst_1
    //   342: istore 5
    //   344: iload 5
    //   346: invokestatic 44	java/lang/Boolean:valueOf	(Z)Ljava/lang/Boolean;
    //   349: areturn
    //   350: aload_0
    //   351: aload 10
    //   353: invokevirtual 348	java/math/BigDecimal:compareTo	(Ljava/math/BigDecimal;)I
    //   356: ifne +6 -> 362
    //   359: iconst_1
    //   360: istore 5
    //   362: iload 5
    //   364: invokestatic 44	java/lang/Boolean:valueOf	(Z)Ljava/lang/Boolean;
    //   367: areturn
    //   368: iload 8
    //   370: istore 5
    //   372: aload_0
    //   373: aload 10
    //   375: invokevirtual 348	java/math/BigDecimal:compareTo	(Ljava/math/BigDecimal;)I
    //   378: iconst_1
    //   379: if_icmpne +6 -> 385
    //   382: iconst_1
    //   383: istore 5
    //   385: iload 5
    //   387: invokestatic 44	java/lang/Boolean:valueOf	(Z)Ljava/lang/Boolean;
    //   390: areturn
    //   391: iload 9
    //   393: istore 5
    //   395: aload_0
    //   396: aload 10
    //   398: invokevirtual 348	java/math/BigDecimal:compareTo	(Ljava/math/BigDecimal;)I
    //   401: iconst_m1
    //   402: if_icmpne +6 -> 408
    //   405: iconst_1
    //   406: istore 5
    //   408: iload 5
    //   410: invokestatic 44	java/lang/Boolean:valueOf	(Z)Ljava/lang/Boolean;
    //   413: areturn
    //   414: aconst_null
    //   415: areturn
    //   416: astore_0
    //   417: aconst_null
    //   418: areturn
    //   419: astore_0
    //   420: aconst_null
    //   421: areturn
    // Local variable table:
    //   start	length	slot	name	signature
    //   0	422	0	paramBigDecimal	BigDecimal
    //   0	422	1	paramZzfx	zzfx
    //   0	422	2	paramDouble	double
    //   67	156	4	i	int
    //   190	219	5	bool1	boolean
    //   199	42	6	bool2	boolean
    //   187	119	7	bool3	boolean
    //   193	176	8	bool4	boolean
    //   196	196	9	bool5	boolean
    //   113	284	10	localBigDecimal	BigDecimal
    //   126	120	11	localObject	Object
    // Exception table:
    //   from	to	target	type
    //   102	128	416	java/lang/NumberFormatException
    //   151	164	419	java/lang/NumberFormatException
  }
  
  private static void zza(Map<Integer, Long> paramMap, int paramInt, long paramLong)
  {
    Long localLong = (Long)paramMap.get(Integer.valueOf(paramInt));
    paramLong /= 1000L;
    if ((localLong == null) || (paramLong > localLong.longValue())) {
      paramMap.put(Integer.valueOf(paramInt), Long.valueOf(paramLong));
    }
  }
  
  private static void zzb(Map<Integer, List<Long>> paramMap, int paramInt, long paramLong)
  {
    List localList = (List)paramMap.get(Integer.valueOf(paramInt));
    Object localObject = localList;
    if (localList == null)
    {
      localObject = new ArrayList();
      paramMap.put(Integer.valueOf(paramInt), localObject);
    }
    ((List)localObject).add(Long.valueOf(paramLong / 1000L));
  }
  
  private static zzge[] zzd(Map<Integer, Long> paramMap)
  {
    if (paramMap == null) {
      return null;
    }
    int i = 0;
    zzge[] arrayOfZzge = new zzge[paramMap.size()];
    Iterator localIterator = paramMap.keySet().iterator();
    while (localIterator.hasNext())
    {
      Integer localInteger = (Integer)localIterator.next();
      zzge localZzge = new zzge();
      zzawq = localInteger;
      zzawr = ((Long)paramMap.get(localInteger));
      arrayOfZzge[i] = localZzge;
      i += 1;
    }
    return arrayOfZzge;
  }
  
  /* Error */
  final com.google.android.gms.internal.measurement.zzgd[] zza(String arg1, com.google.android.gms.internal.measurement.zzgf[] arg2, zzgl[] arg3)
  {
    // Byte code:
    //   0: aload_1
    //   1: astore 18
    //   3: aload_2
    //   4: astore 36
    //   6: aload_1
    //   7: invokestatic 410	com/google/android/gms/common/internal/Preconditions:checkNotEmpty	(Ljava/lang/String;)Ljava/lang/String;
    //   10: pop
    //   11: new 52	java/util/HashSet
    //   14: dup
    //   15: invokespecial 55	java/util/HashSet:<init>	()V
    //   18: astore 24
    //   20: new 109	androidx/collection/ArrayMap
    //   23: dup
    //   24: invokespecial 110	androidx/collection/ArrayMap:<init>	()V
    //   27: astore 25
    //   29: new 109	androidx/collection/ArrayMap
    //   32: dup
    //   33: invokespecial 110	androidx/collection/ArrayMap:<init>	()V
    //   36: astore 17
    //   38: new 109	androidx/collection/ArrayMap
    //   41: dup
    //   42: invokespecial 110	androidx/collection/ArrayMap:<init>	()V
    //   45: astore 16
    //   47: new 109	androidx/collection/ArrayMap
    //   50: dup
    //   51: invokespecial 110	androidx/collection/ArrayMap:<init>	()V
    //   54: astore 15
    //   56: new 109	androidx/collection/ArrayMap
    //   59: dup
    //   60: invokespecial 110	androidx/collection/ArrayMap:<init>	()V
    //   63: astore 23
    //   65: aload_0
    //   66: invokevirtual 414	com/google/android/gms/measurement/internal/zzco:zzgq	()Lcom/google/android/gms/measurement/internal/zzn;
    //   69: aload 18
    //   71: getstatic 420	com/google/android/gms/measurement/internal/zzaf:zzakw	Lcom/google/android/gms/measurement/internal/zzaf$zza;
    //   74: invokevirtual 425	com/google/android/gms/measurement/internal/zzn:zzd	(Ljava/lang/String;Lcom/google/android/gms/measurement/internal/zzaf$zza;)Z
    //   77: istore 10
    //   79: aload_0
    //   80: invokevirtual 431	com/google/android/gms/measurement/internal/zzey:zzjq	()Lcom/google/android/gms/measurement/internal/zzq;
    //   83: aload 18
    //   85: invokevirtual 437	com/google/android/gms/measurement/internal/zzq:zzbo	(Ljava/lang/String;)Ljava/util/Map;
    //   88: astore 27
    //   90: iconst_1
    //   91: invokestatic 44	java/lang/Boolean:valueOf	(Z)Ljava/lang/Boolean;
    //   94: astore 18
    //   96: aload 18
    //   98: astore 21
    //   100: aload 15
    //   102: astore 22
    //   104: aload 16
    //   106: astore 20
    //   108: aload 17
    //   110: astore 19
    //   112: aload 27
    //   114: ifnull +524 -> 638
    //   117: aload 27
    //   119: invokeinterface 381 1 0
    //   124: invokeinterface 385 1 0
    //   129: astore 26
    //   131: aload 18
    //   133: astore 21
    //   135: aload 15
    //   137: astore 22
    //   139: aload 16
    //   141: astore 20
    //   143: aload 17
    //   145: astore 19
    //   147: aload 26
    //   149: invokeinterface 390 1 0
    //   154: ifeq +484 -> 638
    //   157: aload 26
    //   159: invokeinterface 394 1 0
    //   164: checkcast 305	java/lang/Integer
    //   167: invokevirtual 308	java/lang/Integer:intValue	()I
    //   170: istore 6
    //   172: aload 27
    //   174: iload 6
    //   176: invokestatic 364	java/lang/Integer:valueOf	(I)Ljava/lang/Integer;
    //   179: invokeinterface 160 2 0
    //   184: checkcast 439	com/google/android/gms/internal/measurement/zzgj
    //   187: astore 28
    //   189: aload 17
    //   191: iload 6
    //   193: invokestatic 364	java/lang/Integer:valueOf	(I)Ljava/lang/Integer;
    //   196: invokeinterface 160 2 0
    //   201: checkcast 441	java/util/BitSet
    //   204: astore 21
    //   206: aload 16
    //   208: iload 6
    //   210: invokestatic 364	java/lang/Integer:valueOf	(I)Ljava/lang/Integer;
    //   213: invokeinterface 160 2 0
    //   218: checkcast 441	java/util/BitSet
    //   221: astore 20
    //   223: iload 10
    //   225: ifeq +114 -> 339
    //   228: new 109	androidx/collection/ArrayMap
    //   231: dup
    //   232: invokespecial 110	androidx/collection/ArrayMap:<init>	()V
    //   235: astore 22
    //   237: aload 28
    //   239: ifnull +78 -> 317
    //   242: aload 28
    //   244: getfield 445	com/google/android/gms/internal/measurement/zzgj:zzayg	[Lcom/google/android/gms/internal/measurement/zzge;
    //   247: ifnonnull +6 -> 253
    //   250: goto +67 -> 317
    //   253: aload 28
    //   255: getfield 445	com/google/android/gms/internal/measurement/zzgj:zzayg	[Lcom/google/android/gms/internal/measurement/zzge;
    //   258: astore 19
    //   260: aload 19
    //   262: arraylength
    //   263: istore 4
    //   265: iconst_0
    //   266: istore 5
    //   268: iload 5
    //   270: iload 4
    //   272: if_icmpge +45 -> 317
    //   275: aload 19
    //   277: iload 5
    //   279: aaload
    //   280: astore 29
    //   282: aload 29
    //   284: getfield 398	com/google/android/gms/internal/measurement/zzge:zzawq	Ljava/lang/Integer;
    //   287: ifnull +21 -> 308
    //   290: aload 22
    //   292: aload 29
    //   294: getfield 398	com/google/android/gms/internal/measurement/zzge:zzawq	Ljava/lang/Integer;
    //   297: aload 29
    //   299: getfield 401	com/google/android/gms/internal/measurement/zzge:zzawr	Ljava/lang/Long;
    //   302: invokeinterface 128 3 0
    //   307: pop
    //   308: iload 5
    //   310: iconst_1
    //   311: iadd
    //   312: istore 5
    //   314: goto -46 -> 268
    //   317: aload 15
    //   319: iload 6
    //   321: invokestatic 364	java/lang/Integer:valueOf	(I)Ljava/lang/Integer;
    //   324: aload 22
    //   326: invokeinterface 128 3 0
    //   331: pop
    //   332: aload 22
    //   334: astore 19
    //   336: goto +6 -> 342
    //   339: aconst_null
    //   340: astore 19
    //   342: aload 21
    //   344: ifnonnull +54 -> 398
    //   347: new 441	java/util/BitSet
    //   350: dup
    //   351: invokespecial 446	java/util/BitSet:<init>	()V
    //   354: astore 21
    //   356: aload 17
    //   358: iload 6
    //   360: invokestatic 364	java/lang/Integer:valueOf	(I)Ljava/lang/Integer;
    //   363: aload 21
    //   365: invokeinterface 128 3 0
    //   370: pop
    //   371: new 441	java/util/BitSet
    //   374: dup
    //   375: invokespecial 446	java/util/BitSet:<init>	()V
    //   378: astore 20
    //   380: aload 16
    //   382: iload 6
    //   384: invokestatic 364	java/lang/Integer:valueOf	(I)Ljava/lang/Integer;
    //   387: aload 20
    //   389: invokeinterface 128 3 0
    //   394: pop
    //   395: goto +3 -> 398
    //   398: iconst_0
    //   399: istore 4
    //   401: iload 4
    //   403: aload 28
    //   405: getfield 450	com/google/android/gms/internal/measurement/zzgj:zzaye	[J
    //   408: arraylength
    //   409: bipush 6
    //   411: ishl
    //   412: if_icmpge +107 -> 519
    //   415: aload 28
    //   417: getfield 450	com/google/android/gms/internal/measurement/zzgj:zzaye	[J
    //   420: iload 4
    //   422: invokestatic 453	com/google/android/gms/measurement/internal/zzfg:zza	([JI)Z
    //   425: ifeq +59 -> 484
    //   428: aload_0
    //   429: invokevirtual 77	com/google/android/gms/measurement/internal/zzco:zzgo	()Lcom/google/android/gms/measurement/internal/zzap;
    //   432: invokevirtual 206	com/google/android/gms/measurement/internal/zzap:zzjl	()Lcom/google/android/gms/measurement/internal/zzar;
    //   435: ldc_w 455
    //   438: iload 6
    //   440: invokestatic 364	java/lang/Integer:valueOf	(I)Ljava/lang/Integer;
    //   443: iload 4
    //   445: invokestatic 364	java/lang/Integer:valueOf	(I)Ljava/lang/Integer;
    //   448: invokevirtual 144	com/google/android/gms/measurement/internal/zzar:zze	(Ljava/lang/String;Ljava/lang/Object;Ljava/lang/Object;)V
    //   451: aload 20
    //   453: iload 4
    //   455: invokevirtual 458	java/util/BitSet:set	(I)V
    //   458: aload 28
    //   460: getfield 461	com/google/android/gms/internal/measurement/zzgj:zzayf	[J
    //   463: iload 4
    //   465: invokestatic 453	com/google/android/gms/measurement/internal/zzfg:zza	([JI)Z
    //   468: ifeq +16 -> 484
    //   471: aload 21
    //   473: iload 4
    //   475: invokevirtual 458	java/util/BitSet:set	(I)V
    //   478: iconst_1
    //   479: istore 5
    //   481: goto +6 -> 487
    //   484: iconst_0
    //   485: istore 5
    //   487: aload 19
    //   489: ifnull +21 -> 510
    //   492: iload 5
    //   494: ifne +16 -> 510
    //   497: aload 19
    //   499: iload 4
    //   501: invokestatic 364	java/lang/Integer:valueOf	(I)Ljava/lang/Integer;
    //   504: invokeinterface 464 2 0
    //   509: pop
    //   510: iload 4
    //   512: iconst_1
    //   513: iadd
    //   514: istore 4
    //   516: goto -115 -> 401
    //   519: new 466	com/google/android/gms/internal/measurement/zzgd
    //   522: dup
    //   523: invokespecial 467	com/google/android/gms/internal/measurement/zzgd:<init>	()V
    //   526: astore 22
    //   528: aload 25
    //   530: iload 6
    //   532: invokestatic 364	java/lang/Integer:valueOf	(I)Ljava/lang/Integer;
    //   535: aload 22
    //   537: invokeinterface 128 3 0
    //   542: pop
    //   543: aload 22
    //   545: iconst_0
    //   546: invokestatic 44	java/lang/Boolean:valueOf	(Z)Ljava/lang/Boolean;
    //   549: putfield 470	com/google/android/gms/internal/measurement/zzgd:zzawo	Ljava/lang/Boolean;
    //   552: aload 22
    //   554: aload 28
    //   556: putfield 474	com/google/android/gms/internal/measurement/zzgd:zzawn	Lcom/google/android/gms/internal/measurement/zzgj;
    //   559: aload 22
    //   561: new 439	com/google/android/gms/internal/measurement/zzgj
    //   564: dup
    //   565: invokespecial 475	com/google/android/gms/internal/measurement/zzgj:<init>	()V
    //   568: putfield 478	com/google/android/gms/internal/measurement/zzgd:zzawm	Lcom/google/android/gms/internal/measurement/zzgj;
    //   571: aload 22
    //   573: getfield 478	com/google/android/gms/internal/measurement/zzgd:zzawm	Lcom/google/android/gms/internal/measurement/zzgj;
    //   576: aload 21
    //   578: invokestatic 481	com/google/android/gms/measurement/internal/zzfg:zza	(Ljava/util/BitSet;)[J
    //   581: putfield 461	com/google/android/gms/internal/measurement/zzgj:zzayf	[J
    //   584: aload 22
    //   586: getfield 478	com/google/android/gms/internal/measurement/zzgd:zzawm	Lcom/google/android/gms/internal/measurement/zzgj;
    //   589: aload 20
    //   591: invokestatic 481	com/google/android/gms/measurement/internal/zzfg:zza	(Ljava/util/BitSet;)[J
    //   594: putfield 450	com/google/android/gms/internal/measurement/zzgj:zzaye	[J
    //   597: iload 10
    //   599: ifeq +36 -> 635
    //   602: aload 22
    //   604: getfield 478	com/google/android/gms/internal/measurement/zzgd:zzawm	Lcom/google/android/gms/internal/measurement/zzgj;
    //   607: aload 19
    //   609: invokestatic 483	com/google/android/gms/measurement/internal/zzj:zzd	(Ljava/util/Map;)[Lcom/google/android/gms/internal/measurement/zzge;
    //   612: putfield 445	com/google/android/gms/internal/measurement/zzgj:zzayg	[Lcom/google/android/gms/internal/measurement/zzge;
    //   615: aload 23
    //   617: iload 6
    //   619: invokestatic 364	java/lang/Integer:valueOf	(I)Ljava/lang/Integer;
    //   622: new 109	androidx/collection/ArrayMap
    //   625: dup
    //   626: invokespecial 110	androidx/collection/ArrayMap:<init>	()V
    //   629: invokeinterface 128 3 0
    //   634: pop
    //   635: goto -504 -> 131
    //   638: aload 22
    //   640: astore 15
    //   642: aload 20
    //   644: astore 16
    //   646: aload 19
    //   648: astore 17
    //   650: ldc_w 485
    //   653: astore 18
    //   655: ldc_w 487
    //   658: astore 22
    //   660: aload 22
    //   662: astore 34
    //   664: aload 23
    //   666: astore 33
    //   668: aload 18
    //   670: astore 32
    //   672: aload 24
    //   674: astore 35
    //   676: aload 25
    //   678: astore 31
    //   680: aload 15
    //   682: astore 30
    //   684: aload 21
    //   686: astore 29
    //   688: aload 16
    //   690: astore 28
    //   692: aload 17
    //   694: astore 27
    //   696: aload 36
    //   698: ifnull +2267 -> 2965
    //   701: new 109	androidx/collection/ArrayMap
    //   704: dup
    //   705: invokespecial 110	androidx/collection/ArrayMap:<init>	()V
    //   708: astore 28
    //   710: aload 36
    //   712: arraylength
    //   713: istore 5
    //   715: lconst_0
    //   716: lstore 11
    //   718: aconst_null
    //   719: astore 27
    //   721: aconst_null
    //   722: astore 26
    //   724: iconst_0
    //   725: istore 6
    //   727: aload 25
    //   729: astore 20
    //   731: aload 24
    //   733: astore 19
    //   735: aload 28
    //   737: astore 25
    //   739: aload 27
    //   741: astore 24
    //   743: aload_1
    //   744: astore 36
    //   746: aload 22
    //   748: astore 34
    //   750: aload 23
    //   752: astore 33
    //   754: aload 18
    //   756: astore 32
    //   758: aload 19
    //   760: astore 35
    //   762: aload 20
    //   764: astore 31
    //   766: aload 15
    //   768: astore 30
    //   770: aload 21
    //   772: astore 29
    //   774: aload 16
    //   776: astore 28
    //   778: aload 17
    //   780: astore 27
    //   782: iload 6
    //   784: iload 5
    //   786: if_icmpge +2179 -> 2965
    //   789: aload_2
    //   790: iload 6
    //   792: aaload
    //   793: astore 31
    //   795: aload 31
    //   797: getfield 490	com/google/android/gms/internal/measurement/zzgf:name	Ljava/lang/String;
    //   800: astore 27
    //   802: aload 31
    //   804: getfield 494	com/google/android/gms/internal/measurement/zzgf:zzawt	[Lcom/google/android/gms/internal/measurement/zzgg;
    //   807: astore 28
    //   809: aload_0
    //   810: invokevirtual 414	com/google/android/gms/measurement/internal/zzco:zzgq	()Lcom/google/android/gms/measurement/internal/zzn;
    //   813: aload 36
    //   815: getstatic 497	com/google/android/gms/measurement/internal/zzaf:zzakq	Lcom/google/android/gms/measurement/internal/zzaf$zza;
    //   818: invokevirtual 425	com/google/android/gms/measurement/internal/zzn:zzd	(Ljava/lang/String;Lcom/google/android/gms/measurement/internal/zzaf$zza;)Z
    //   821: ifeq +723 -> 1544
    //   824: aload_0
    //   825: invokevirtual 501	com/google/android/gms/measurement/internal/zzey:zzjo	()Lcom/google/android/gms/measurement/internal/zzfg;
    //   828: pop
    //   829: aload 31
    //   831: ldc_w 503
    //   834: invokestatic 506	com/google/android/gms/measurement/internal/zzfg:zzb	(Lcom/google/android/gms/internal/measurement/zzgf;Ljava/lang/String;)Ljava/lang/Object;
    //   837: checkcast 162	java/lang/Long
    //   840: astore 32
    //   842: aload 32
    //   844: ifnull +9 -> 853
    //   847: iconst_1
    //   848: istore 4
    //   850: goto +6 -> 856
    //   853: iconst_0
    //   854: istore 4
    //   856: iload 4
    //   858: ifeq +20 -> 878
    //   861: aload 27
    //   863: ldc_w 508
    //   866: invokevirtual 262	java/lang/String:equals	(Ljava/lang/Object;)Z
    //   869: ifeq +9 -> 878
    //   872: iconst_1
    //   873: istore 7
    //   875: goto +6 -> 881
    //   878: iconst_0
    //   879: istore 7
    //   881: iload 7
    //   883: ifeq +554 -> 1437
    //   886: aload_0
    //   887: invokevirtual 501	com/google/android/gms/measurement/internal/zzey:zzjo	()Lcom/google/android/gms/measurement/internal/zzfg;
    //   890: pop
    //   891: aload 31
    //   893: ldc_w 510
    //   896: invokestatic 506	com/google/android/gms/measurement/internal/zzfg:zzb	(Lcom/google/android/gms/internal/measurement/zzgf;Ljava/lang/String;)Ljava/lang/Object;
    //   899: checkcast 183	java/lang/String
    //   902: astore 30
    //   904: aload 30
    //   906: invokestatic 71	android/text/TextUtils:isEmpty	(Ljava/lang/CharSequence;)Z
    //   909: ifeq +21 -> 930
    //   912: aload_0
    //   913: invokevirtual 77	com/google/android/gms/measurement/internal/zzco:zzgo	()Lcom/google/android/gms/measurement/internal/zzap;
    //   916: invokevirtual 513	com/google/android/gms/measurement/internal/zzap:zzjd	()Lcom/google/android/gms/measurement/internal/zzar;
    //   919: ldc_w 515
    //   922: aload 32
    //   924: invokevirtual 101	com/google/android/gms/measurement/internal/zzar:zzg	(Ljava/lang/String;Ljava/lang/Object;)V
    //   927: goto +455 -> 1382
    //   930: aload 24
    //   932: ifnull +40 -> 972
    //   935: aload 26
    //   937: ifnull +35 -> 972
    //   940: aload 24
    //   942: astore 27
    //   944: aload 26
    //   946: astore 29
    //   948: lload 11
    //   950: lstore 13
    //   952: aload 32
    //   954: invokevirtual 171	java/lang/Long:longValue	()J
    //   957: aload 26
    //   959: invokevirtual 171	java/lang/Long:longValue	()J
    //   962: lcmp
    //   963: ifeq +6 -> 969
    //   966: goto +6 -> 972
    //   969: goto +76 -> 1045
    //   972: aload_0
    //   973: invokevirtual 431	com/google/android/gms/measurement/internal/zzey:zzjq	()Lcom/google/android/gms/measurement/internal/zzq;
    //   976: aload 36
    //   978: aload 32
    //   980: invokevirtual 518	com/google/android/gms/measurement/internal/zzq:zza	(Ljava/lang/String;Ljava/lang/Long;)Landroid/util/Pair;
    //   983: astore 29
    //   985: aload 29
    //   987: ifnull +378 -> 1365
    //   990: aload 29
    //   992: getfield 524	android/util/Pair:first	Ljava/lang/Object;
    //   995: ifnonnull +6 -> 1001
    //   998: goto +367 -> 1365
    //   1001: aload 29
    //   1003: getfield 524	android/util/Pair:first	Ljava/lang/Object;
    //   1006: checkcast 489	com/google/android/gms/internal/measurement/zzgf
    //   1009: astore 27
    //   1011: aload 29
    //   1013: getfield 527	android/util/Pair:second	Ljava/lang/Object;
    //   1016: checkcast 162	java/lang/Long
    //   1019: invokevirtual 171	java/lang/Long:longValue	()J
    //   1022: lstore 13
    //   1024: aload_0
    //   1025: invokevirtual 501	com/google/android/gms/measurement/internal/zzey:zzjo	()Lcom/google/android/gms/measurement/internal/zzfg;
    //   1028: pop
    //   1029: aload 27
    //   1031: ldc_w 503
    //   1034: invokestatic 506	com/google/android/gms/measurement/internal/zzfg:zzb	(Lcom/google/android/gms/internal/measurement/zzgf;Ljava/lang/String;)Ljava/lang/Object;
    //   1037: checkcast 162	java/lang/Long
    //   1040: astore 29
    //   1042: goto -73 -> 969
    //   1045: lload 13
    //   1047: lconst_1
    //   1048: lsub
    //   1049: lstore 11
    //   1051: lload 11
    //   1053: lconst_0
    //   1054: lcmp
    //   1055: ifgt +91 -> 1146
    //   1058: aload_0
    //   1059: invokevirtual 431	com/google/android/gms/measurement/internal/zzey:zzjq	()Lcom/google/android/gms/measurement/internal/zzq;
    //   1062: astore 26
    //   1064: aload 26
    //   1066: invokevirtual 530	com/google/android/gms/measurement/internal/zzco:zzaf	()V
    //   1069: aload 26
    //   1071: invokevirtual 77	com/google/android/gms/measurement/internal/zzco:zzgo	()Lcom/google/android/gms/measurement/internal/zzap;
    //   1074: invokevirtual 206	com/google/android/gms/measurement/internal/zzap:zzjl	()Lcom/google/android/gms/measurement/internal/zzar;
    //   1077: ldc_w 532
    //   1080: aload 36
    //   1082: invokevirtual 101	com/google/android/gms/measurement/internal/zzar:zzg	(Ljava/lang/String;Ljava/lang/Object;)V
    //   1085: aload 26
    //   1087: invokevirtual 536	com/google/android/gms/measurement/internal/zzq:getWritableDatabase	()Landroid/database/sqlite/SQLiteDatabase;
    //   1090: astore 24
    //   1092: aload 24
    //   1094: ldc_w 538
    //   1097: iconst_1
    //   1098: anewarray 183	java/lang/String
    //   1101: dup
    //   1102: iconst_0
    //   1103: aload 36
    //   1105: aastore
    //   1106: invokevirtual 544	android/database/sqlite/SQLiteDatabase:execSQL	(Ljava/lang/String;[Ljava/lang/Object;)V
    //   1109: goto +30 -> 1139
    //   1112: astore 24
    //   1114: goto +9 -> 1123
    //   1117: astore_1
    //   1118: goto +5 -> 1123
    //   1121: astore 24
    //   1123: aload 26
    //   1125: invokevirtual 77	com/google/android/gms/measurement/internal/zzco:zzgo	()Lcom/google/android/gms/measurement/internal/zzap;
    //   1128: invokevirtual 513	com/google/android/gms/measurement/internal/zzap:zzjd	()Lcom/google/android/gms/measurement/internal/zzar;
    //   1131: ldc_w 546
    //   1134: aload 24
    //   1136: invokevirtual 101	com/google/android/gms/measurement/internal/zzar:zzg	(Ljava/lang/String;Ljava/lang/Object;)V
    //   1139: aload 27
    //   1141: astore 24
    //   1143: goto +22 -> 1165
    //   1146: aload_0
    //   1147: invokevirtual 431	com/google/android/gms/measurement/internal/zzey:zzjq	()Lcom/google/android/gms/measurement/internal/zzq;
    //   1150: aload_1
    //   1151: aload 32
    //   1153: lload 11
    //   1155: aload 27
    //   1157: invokevirtual 549	com/google/android/gms/measurement/internal/zzq:zza	(Ljava/lang/String;Ljava/lang/Long;JLcom/google/android/gms/internal/measurement/zzgf;)Z
    //   1160: pop
    //   1161: aload 27
    //   1163: astore 24
    //   1165: aload 24
    //   1167: getfield 494	com/google/android/gms/internal/measurement/zzgf:zzawt	[Lcom/google/android/gms/internal/measurement/zzgg;
    //   1170: arraylength
    //   1171: aload 28
    //   1173: arraylength
    //   1174: iadd
    //   1175: anewarray 112	com/google/android/gms/internal/measurement/zzgg
    //   1178: astore 26
    //   1180: aload 24
    //   1182: getfield 494	com/google/android/gms/internal/measurement/zzgf:zzawt	[Lcom/google/android/gms/internal/measurement/zzgg;
    //   1185: astore 27
    //   1187: aload 27
    //   1189: arraylength
    //   1190: istore 9
    //   1192: iconst_0
    //   1193: istore 7
    //   1195: iconst_0
    //   1196: istore 4
    //   1198: iload 7
    //   1200: iload 9
    //   1202: if_icmpge +58 -> 1260
    //   1205: aload 27
    //   1207: iload 7
    //   1209: aaload
    //   1210: astore 32
    //   1212: aload_0
    //   1213: invokevirtual 501	com/google/android/gms/measurement/internal/zzey:zzjo	()Lcom/google/android/gms/measurement/internal/zzfg;
    //   1216: pop
    //   1217: iload 4
    //   1219: istore 8
    //   1221: aload 31
    //   1223: aload 32
    //   1225: getfield 115	com/google/android/gms/internal/measurement/zzgg:name	Ljava/lang/String;
    //   1228: invokestatic 552	com/google/android/gms/measurement/internal/zzfg:zza	(Lcom/google/android/gms/internal/measurement/zzgf;Ljava/lang/String;)Lcom/google/android/gms/internal/measurement/zzgg;
    //   1231: ifnonnull +16 -> 1247
    //   1234: aload 26
    //   1236: iload 4
    //   1238: aload 32
    //   1240: aastore
    //   1241: iload 4
    //   1243: iconst_1
    //   1244: iadd
    //   1245: istore 8
    //   1247: iload 7
    //   1249: iconst_1
    //   1250: iadd
    //   1251: istore 7
    //   1253: iload 8
    //   1255: istore 4
    //   1257: goto -59 -> 1198
    //   1260: iload 4
    //   1262: ifle +73 -> 1335
    //   1265: aload 28
    //   1267: arraylength
    //   1268: istore 8
    //   1270: iconst_0
    //   1271: istore 7
    //   1273: iload 7
    //   1275: iload 8
    //   1277: if_icmpge +28 -> 1305
    //   1280: aload 26
    //   1282: iload 4
    //   1284: aload 28
    //   1286: iload 7
    //   1288: aaload
    //   1289: aastore
    //   1290: iload 7
    //   1292: iconst_1
    //   1293: iadd
    //   1294: istore 7
    //   1296: iload 4
    //   1298: iconst_1
    //   1299: iadd
    //   1300: istore 4
    //   1302: goto -29 -> 1273
    //   1305: iload 4
    //   1307: aload 26
    //   1309: arraylength
    //   1310: if_icmpne +6 -> 1316
    //   1313: goto +15 -> 1328
    //   1316: aload 26
    //   1318: iload 4
    //   1320: invokestatic 556	java/util/Arrays:copyOf	([Ljava/lang/Object;I)[Ljava/lang/Object;
    //   1323: checkcast 557	[Lcom/google/android/gms/internal/measurement/zzgg;
    //   1326: astore 26
    //   1328: aload 26
    //   1330: astore 27
    //   1332: goto +22 -> 1354
    //   1335: aload_0
    //   1336: invokevirtual 77	com/google/android/gms/measurement/internal/zzco:zzgo	()Lcom/google/android/gms/measurement/internal/zzap;
    //   1339: invokevirtual 83	com/google/android/gms/measurement/internal/zzap:zzjg	()Lcom/google/android/gms/measurement/internal/zzar;
    //   1342: ldc_w 559
    //   1345: aload 30
    //   1347: invokevirtual 101	com/google/android/gms/measurement/internal/zzar:zzg	(Ljava/lang/String;Ljava/lang/Object;)V
    //   1350: aload 28
    //   1352: astore 27
    //   1354: aload 30
    //   1356: astore 28
    //   1358: aload 29
    //   1360: astore 26
    //   1362: goto +194 -> 1556
    //   1365: aload_0
    //   1366: invokevirtual 77	com/google/android/gms/measurement/internal/zzco:zzgo	()Lcom/google/android/gms/measurement/internal/zzap;
    //   1369: invokevirtual 513	com/google/android/gms/measurement/internal/zzap:zzjd	()Lcom/google/android/gms/measurement/internal/zzar;
    //   1372: ldc_w 561
    //   1375: aload 30
    //   1377: aload 32
    //   1379: invokevirtual 144	com/google/android/gms/measurement/internal/zzar:zze	(Ljava/lang/String;Ljava/lang/Object;Ljava/lang/Object;)V
    //   1382: aload 23
    //   1384: astore 28
    //   1386: aload 22
    //   1388: astore 27
    //   1390: aload 25
    //   1392: astore 29
    //   1394: aload 18
    //   1396: astore 22
    //   1398: aload 19
    //   1400: astore 23
    //   1402: aload 20
    //   1404: astore 25
    //   1406: aload 16
    //   1408: astore 18
    //   1410: aload 17
    //   1412: astore 19
    //   1414: aload 21
    //   1416: astore 20
    //   1418: aload 29
    //   1420: astore 21
    //   1422: aload 28
    //   1424: astore 16
    //   1426: aload 15
    //   1428: astore 17
    //   1430: aload 25
    //   1432: astore 15
    //   1434: goto +1466 -> 2900
    //   1437: iload 4
    //   1439: ifeq +105 -> 1544
    //   1442: aload_0
    //   1443: invokevirtual 501	com/google/android/gms/measurement/internal/zzey:zzjo	()Lcom/google/android/gms/measurement/internal/zzfg;
    //   1446: pop
    //   1447: lconst_0
    //   1448: invokestatic 369	java/lang/Long:valueOf	(J)Ljava/lang/Long;
    //   1451: astore 24
    //   1453: aload 31
    //   1455: ldc_w 563
    //   1458: invokestatic 506	com/google/android/gms/measurement/internal/zzfg:zzb	(Lcom/google/android/gms/internal/measurement/zzgf;Ljava/lang/String;)Ljava/lang/Object;
    //   1461: astore 26
    //   1463: aload 26
    //   1465: ifnonnull +6 -> 1471
    //   1468: goto +7 -> 1475
    //   1471: aload 26
    //   1473: astore 24
    //   1475: aload 24
    //   1477: checkcast 162	java/lang/Long
    //   1480: invokevirtual 171	java/lang/Long:longValue	()J
    //   1483: lstore 11
    //   1485: lload 11
    //   1487: lconst_0
    //   1488: lcmp
    //   1489: ifgt +21 -> 1510
    //   1492: aload_0
    //   1493: invokevirtual 77	com/google/android/gms/measurement/internal/zzco:zzgo	()Lcom/google/android/gms/measurement/internal/zzap;
    //   1496: invokevirtual 83	com/google/android/gms/measurement/internal/zzap:zzjg	()Lcom/google/android/gms/measurement/internal/zzar;
    //   1499: ldc_w 565
    //   1502: aload 27
    //   1504: invokevirtual 101	com/google/android/gms/measurement/internal/zzar:zzg	(Ljava/lang/String;Ljava/lang/Object;)V
    //   1507: goto +18 -> 1525
    //   1510: aload_0
    //   1511: invokevirtual 431	com/google/android/gms/measurement/internal/zzey:zzjq	()Lcom/google/android/gms/measurement/internal/zzq;
    //   1514: aload_1
    //   1515: aload 32
    //   1517: lload 11
    //   1519: aload 31
    //   1521: invokevirtual 549	com/google/android/gms/measurement/internal/zzq:zza	(Ljava/lang/String;Ljava/lang/Long;JLcom/google/android/gms/internal/measurement/zzgf;)Z
    //   1524: pop
    //   1525: aload 32
    //   1527: astore 26
    //   1529: aload 28
    //   1531: astore 30
    //   1533: aload 31
    //   1535: astore 24
    //   1537: aload 27
    //   1539: astore 28
    //   1541: goto +19 -> 1560
    //   1544: aload 27
    //   1546: astore 29
    //   1548: aload 28
    //   1550: astore 27
    //   1552: aload 29
    //   1554: astore 28
    //   1556: aload 27
    //   1558: astore 30
    //   1560: aload 23
    //   1562: astore 29
    //   1564: aload 22
    //   1566: astore 27
    //   1568: aload 21
    //   1570: astore 23
    //   1572: aload_0
    //   1573: invokevirtual 431	com/google/android/gms/measurement/internal/zzey:zzjq	()Lcom/google/android/gms/measurement/internal/zzq;
    //   1576: aload 36
    //   1578: aload 31
    //   1580: getfield 490	com/google/android/gms/internal/measurement/zzgf:name	Ljava/lang/String;
    //   1583: invokevirtual 568	com/google/android/gms/measurement/internal/zzq:zzg	(Ljava/lang/String;Ljava/lang/String;)Lcom/google/android/gms/measurement/internal/zzz;
    //   1586: astore 21
    //   1588: aload 21
    //   1590: ifnonnull +62 -> 1652
    //   1593: aload_0
    //   1594: invokevirtual 77	com/google/android/gms/measurement/internal/zzco:zzgo	()Lcom/google/android/gms/measurement/internal/zzap;
    //   1597: invokevirtual 83	com/google/android/gms/measurement/internal/zzap:zzjg	()Lcom/google/android/gms/measurement/internal/zzar;
    //   1600: ldc_w 570
    //   1603: aload_1
    //   1604: invokestatic 574	com/google/android/gms/measurement/internal/zzap:zzbv	(Ljava/lang/String;)Ljava/lang/Object;
    //   1607: aload_0
    //   1608: invokevirtual 89	com/google/android/gms/measurement/internal/zzco:zzgl	()Lcom/google/android/gms/measurement/internal/zzan;
    //   1611: aload 28
    //   1613: invokevirtual 95	com/google/android/gms/measurement/internal/zzan:zzbs	(Ljava/lang/String;)Ljava/lang/String;
    //   1616: invokevirtual 144	com/google/android/gms/measurement/internal/zzar:zze	(Ljava/lang/String;Ljava/lang/Object;Ljava/lang/Object;)V
    //   1619: new 576	com/google/android/gms/measurement/internal/zzz
    //   1622: dup
    //   1623: aload_1
    //   1624: aload 31
    //   1626: getfield 490	com/google/android/gms/internal/measurement/zzgf:name	Ljava/lang/String;
    //   1629: lconst_1
    //   1630: lconst_1
    //   1631: aload 31
    //   1633: getfield 579	com/google/android/gms/internal/measurement/zzgf:zzawu	Ljava/lang/Long;
    //   1636: invokevirtual 171	java/lang/Long:longValue	()J
    //   1639: lconst_0
    //   1640: aconst_null
    //   1641: aconst_null
    //   1642: aconst_null
    //   1643: aconst_null
    //   1644: invokespecial 582	com/google/android/gms/measurement/internal/zzz:<init>	(Ljava/lang/String;Ljava/lang/String;JJJJLjava/lang/Long;Ljava/lang/Long;Ljava/lang/Long;Ljava/lang/Boolean;)V
    //   1647: astore 22
    //   1649: goto +10 -> 1659
    //   1652: aload 21
    //   1654: invokevirtual 586	com/google/android/gms/measurement/internal/zzz:zziu	()Lcom/google/android/gms/measurement/internal/zzz;
    //   1657: astore 22
    //   1659: aload 20
    //   1661: astore 21
    //   1663: aload 19
    //   1665: astore 20
    //   1667: aload 17
    //   1669: astore 19
    //   1671: aload 15
    //   1673: astore 17
    //   1675: aload 31
    //   1677: astore 32
    //   1679: aload_0
    //   1680: invokevirtual 431	com/google/android/gms/measurement/internal/zzey:zzjq	()Lcom/google/android/gms/measurement/internal/zzq;
    //   1683: aload 22
    //   1685: invokevirtual 589	com/google/android/gms/measurement/internal/zzq:zza	(Lcom/google/android/gms/measurement/internal/zzz;)V
    //   1688: aload 22
    //   1690: getfield 593	com/google/android/gms/measurement/internal/zzz:zzaie	J
    //   1693: lstore 13
    //   1695: aload 25
    //   1697: aload 28
    //   1699: invokeinterface 160 2 0
    //   1704: checkcast 124	java/util/Map
    //   1707: astore 22
    //   1709: aload 22
    //   1711: astore 15
    //   1713: aload 22
    //   1715: ifnonnull +46 -> 1761
    //   1718: aload_0
    //   1719: invokevirtual 431	com/google/android/gms/measurement/internal/zzey:zzjq	()Lcom/google/android/gms/measurement/internal/zzq;
    //   1722: aload 36
    //   1724: aload 28
    //   1726: invokevirtual 597	com/google/android/gms/measurement/internal/zzq:zzl	(Ljava/lang/String;Ljava/lang/String;)Ljava/util/Map;
    //   1729: astore 22
    //   1731: aload 22
    //   1733: astore 15
    //   1735: aload 22
    //   1737: ifnonnull +12 -> 1749
    //   1740: new 109	androidx/collection/ArrayMap
    //   1743: dup
    //   1744: invokespecial 110	androidx/collection/ArrayMap:<init>	()V
    //   1747: astore 15
    //   1749: aload 25
    //   1751: aload 28
    //   1753: aload 15
    //   1755: invokeinterface 128 3 0
    //   1760: pop
    //   1761: aload 15
    //   1763: astore 33
    //   1765: aload 33
    //   1767: invokeinterface 381 1 0
    //   1772: invokeinterface 385 1 0
    //   1777: astore 31
    //   1779: aload 18
    //   1781: astore 22
    //   1783: aload 16
    //   1785: astore 18
    //   1787: aload 29
    //   1789: astore 16
    //   1791: aload 23
    //   1793: astore 15
    //   1795: aload 33
    //   1797: astore 23
    //   1799: aload 32
    //   1801: astore 29
    //   1803: aload 28
    //   1805: astore 35
    //   1807: aload 31
    //   1809: invokeinterface 390 1 0
    //   1814: ifeq +1066 -> 2880
    //   1817: aload 31
    //   1819: invokeinterface 394 1 0
    //   1824: checkcast 305	java/lang/Integer
    //   1827: invokevirtual 308	java/lang/Integer:intValue	()I
    //   1830: istore 8
    //   1832: aload 20
    //   1834: iload 8
    //   1836: invokestatic 364	java/lang/Integer:valueOf	(I)Ljava/lang/Integer;
    //   1839: invokeinterface 118 2 0
    //   1844: ifeq +23 -> 1867
    //   1847: aload_0
    //   1848: invokevirtual 77	com/google/android/gms/measurement/internal/zzco:zzgo	()Lcom/google/android/gms/measurement/internal/zzap;
    //   1851: invokevirtual 206	com/google/android/gms/measurement/internal/zzap:zzjl	()Lcom/google/android/gms/measurement/internal/zzar;
    //   1854: aload 27
    //   1856: iload 8
    //   1858: invokestatic 364	java/lang/Integer:valueOf	(I)Ljava/lang/Integer;
    //   1861: invokevirtual 101	com/google/android/gms/measurement/internal/zzar:zzg	(Ljava/lang/String;Ljava/lang/Object;)V
    //   1864: goto -57 -> 1807
    //   1867: aload 21
    //   1869: astore 36
    //   1871: aload 36
    //   1873: iload 8
    //   1875: invokestatic 364	java/lang/Integer:valueOf	(I)Ljava/lang/Integer;
    //   1878: invokeinterface 160 2 0
    //   1883: checkcast 466	com/google/android/gms/internal/measurement/zzgd
    //   1886: astore 34
    //   1888: aload 19
    //   1890: astore 37
    //   1892: aload 37
    //   1894: iload 8
    //   1896: invokestatic 364	java/lang/Integer:valueOf	(I)Ljava/lang/Integer;
    //   1899: invokeinterface 160 2 0
    //   1904: checkcast 441	java/util/BitSet
    //   1907: astore 32
    //   1909: aload 29
    //   1911: astore 38
    //   1913: aload 18
    //   1915: astore 21
    //   1917: aload 21
    //   1919: iload 8
    //   1921: invokestatic 364	java/lang/Integer:valueOf	(I)Ljava/lang/Integer;
    //   1924: invokeinterface 160 2 0
    //   1929: checkcast 441	java/util/BitSet
    //   1932: astore 28
    //   1934: iload 10
    //   1936: ifeq +40 -> 1976
    //   1939: aload 17
    //   1941: iload 8
    //   1943: invokestatic 364	java/lang/Integer:valueOf	(I)Ljava/lang/Integer;
    //   1946: invokeinterface 160 2 0
    //   1951: checkcast 124	java/util/Map
    //   1954: astore 19
    //   1956: aload 16
    //   1958: iload 8
    //   1960: invokestatic 364	java/lang/Integer:valueOf	(I)Ljava/lang/Integer;
    //   1963: invokeinterface 160 2 0
    //   1968: checkcast 124	java/util/Map
    //   1971: astore 18
    //   1973: goto +9 -> 1982
    //   1976: aconst_null
    //   1977: astore 18
    //   1979: aconst_null
    //   1980: astore 19
    //   1982: aload 27
    //   1984: astore 39
    //   1986: aload 16
    //   1988: astore 33
    //   1990: aload 34
    //   1992: ifnonnull +157 -> 2149
    //   1995: new 466	com/google/android/gms/internal/measurement/zzgd
    //   1998: dup
    //   1999: invokespecial 467	com/google/android/gms/internal/measurement/zzgd:<init>	()V
    //   2002: astore 16
    //   2004: aload 36
    //   2006: iload 8
    //   2008: invokestatic 364	java/lang/Integer:valueOf	(I)Ljava/lang/Integer;
    //   2011: aload 16
    //   2013: invokeinterface 128 3 0
    //   2018: pop
    //   2019: aload 16
    //   2021: aload 15
    //   2023: putfield 470	com/google/android/gms/internal/measurement/zzgd:zzawo	Ljava/lang/Boolean;
    //   2026: new 441	java/util/BitSet
    //   2029: dup
    //   2030: invokespecial 446	java/util/BitSet:<init>	()V
    //   2033: astore 27
    //   2035: aload 37
    //   2037: iload 8
    //   2039: invokestatic 364	java/lang/Integer:valueOf	(I)Ljava/lang/Integer;
    //   2042: aload 27
    //   2044: invokeinterface 128 3 0
    //   2049: pop
    //   2050: new 441	java/util/BitSet
    //   2053: dup
    //   2054: invokespecial 446	java/util/BitSet:<init>	()V
    //   2057: astore 28
    //   2059: aload 21
    //   2061: iload 8
    //   2063: invokestatic 364	java/lang/Integer:valueOf	(I)Ljava/lang/Integer;
    //   2066: aload 28
    //   2068: invokeinterface 128 3 0
    //   2073: pop
    //   2074: iload 10
    //   2076: ifeq +54 -> 2130
    //   2079: new 109	androidx/collection/ArrayMap
    //   2082: dup
    //   2083: invokespecial 110	androidx/collection/ArrayMap:<init>	()V
    //   2086: astore 29
    //   2088: aload 17
    //   2090: iload 8
    //   2092: invokestatic 364	java/lang/Integer:valueOf	(I)Ljava/lang/Integer;
    //   2095: aload 29
    //   2097: invokeinterface 128 3 0
    //   2102: pop
    //   2103: new 109	androidx/collection/ArrayMap
    //   2106: dup
    //   2107: invokespecial 110	androidx/collection/ArrayMap:<init>	()V
    //   2110: astore 16
    //   2112: aload 33
    //   2114: iload 8
    //   2116: invokestatic 364	java/lang/Integer:valueOf	(I)Ljava/lang/Integer;
    //   2119: aload 16
    //   2121: invokeinterface 128 3 0
    //   2126: pop
    //   2127: goto +11 -> 2138
    //   2130: aload 18
    //   2132: astore 16
    //   2134: aload 19
    //   2136: astore 29
    //   2138: aload 27
    //   2140: astore 18
    //   2142: aload 16
    //   2144: astore 34
    //   2146: goto +15 -> 2161
    //   2149: aload 19
    //   2151: astore 29
    //   2153: aload 18
    //   2155: astore 34
    //   2157: aload 32
    //   2159: astore 18
    //   2161: aload 17
    //   2163: astore 32
    //   2165: aload 15
    //   2167: astore 27
    //   2169: aload 23
    //   2171: iload 8
    //   2173: invokestatic 364	java/lang/Integer:valueOf	(I)Ljava/lang/Integer;
    //   2176: invokeinterface 160 2 0
    //   2181: checkcast 246	java/util/List
    //   2184: invokeinterface 598 1 0
    //   2189: astore 40
    //   2191: aload 22
    //   2193: astore 19
    //   2195: aload 38
    //   2197: astore 17
    //   2199: aload 23
    //   2201: astore 16
    //   2203: aload 37
    //   2205: astore 22
    //   2207: aload 36
    //   2209: astore 15
    //   2211: aload 18
    //   2213: astore 23
    //   2215: aload 27
    //   2217: astore 18
    //   2219: aload 35
    //   2221: astore 27
    //   2223: aload 40
    //   2225: invokeinterface 390 1 0
    //   2230: ifeq +595 -> 2825
    //   2233: aload 40
    //   2235: invokeinterface 394 1 0
    //   2240: checkcast 34	com/google/android/gms/internal/measurement/zzfv
    //   2243: astore 38
    //   2245: aload_0
    //   2246: invokevirtual 77	com/google/android/gms/measurement/internal/zzco:zzgo	()Lcom/google/android/gms/measurement/internal/zzap;
    //   2249: iconst_2
    //   2250: invokevirtual 602	com/google/android/gms/measurement/internal/zzap:isLoggable	(I)Z
    //   2253: ifeq +62 -> 2315
    //   2256: aload_0
    //   2257: invokevirtual 77	com/google/android/gms/measurement/internal/zzco:zzgo	()Lcom/google/android/gms/measurement/internal/zzap;
    //   2260: invokevirtual 206	com/google/android/gms/measurement/internal/zzap:zzjl	()Lcom/google/android/gms/measurement/internal/zzar;
    //   2263: ldc_w 604
    //   2266: iload 8
    //   2268: invokestatic 364	java/lang/Integer:valueOf	(I)Ljava/lang/Integer;
    //   2271: aload 38
    //   2273: getfield 607	com/google/android/gms/internal/measurement/zzfv:zzave	Ljava/lang/Integer;
    //   2276: aload_0
    //   2277: invokevirtual 89	com/google/android/gms/measurement/internal/zzco:zzgl	()Lcom/google/android/gms/measurement/internal/zzan;
    //   2280: aload 38
    //   2282: getfield 610	com/google/android/gms/internal/measurement/zzfv:zzavf	Ljava/lang/String;
    //   2285: invokevirtual 95	com/google/android/gms/measurement/internal/zzan:zzbs	(Ljava/lang/String;)Ljava/lang/String;
    //   2288: invokevirtual 613	com/google/android/gms/measurement/internal/zzar:zzd	(Ljava/lang/String;Ljava/lang/Object;Ljava/lang/Object;Ljava/lang/Object;)V
    //   2291: aload_0
    //   2292: invokevirtual 77	com/google/android/gms/measurement/internal/zzco:zzgo	()Lcom/google/android/gms/measurement/internal/zzap;
    //   2295: invokevirtual 206	com/google/android/gms/measurement/internal/zzap:zzjl	()Lcom/google/android/gms/measurement/internal/zzar;
    //   2298: aload 19
    //   2300: aload_0
    //   2301: invokevirtual 501	com/google/android/gms/measurement/internal/zzey:zzjo	()Lcom/google/android/gms/measurement/internal/zzfg;
    //   2304: aload 38
    //   2306: invokevirtual 616	com/google/android/gms/measurement/internal/zzfg:zza	(Lcom/google/android/gms/internal/measurement/zzfv;)Ljava/lang/String;
    //   2309: invokevirtual 101	com/google/android/gms/measurement/internal/zzar:zzg	(Ljava/lang/String;Ljava/lang/Object;)V
    //   2312: goto +3 -> 2315
    //   2315: aload 38
    //   2317: getfield 607	com/google/android/gms/internal/measurement/zzfv:zzave	Ljava/lang/Integer;
    //   2320: ifnull +477 -> 2797
    //   2323: aload 38
    //   2325: getfield 607	com/google/android/gms/internal/measurement/zzfv:zzave	Ljava/lang/Integer;
    //   2328: invokevirtual 308	java/lang/Integer:intValue	()I
    //   2331: sipush 256
    //   2334: if_icmple +6 -> 2340
    //   2337: goto +460 -> 2797
    //   2340: iload 10
    //   2342: ifeq +301 -> 2643
    //   2345: aload 38
    //   2347: ifnull +28 -> 2375
    //   2350: aload 38
    //   2352: getfield 619	com/google/android/gms/internal/measurement/zzfv:zzavb	Ljava/lang/Boolean;
    //   2355: ifnull +20 -> 2375
    //   2358: aload 38
    //   2360: getfield 619	com/google/android/gms/internal/measurement/zzfv:zzavb	Ljava/lang/Boolean;
    //   2363: invokevirtual 50	java/lang/Boolean:booleanValue	()Z
    //   2366: ifeq +9 -> 2375
    //   2369: iconst_1
    //   2370: istore 4
    //   2372: goto +6 -> 2378
    //   2375: iconst_0
    //   2376: istore 4
    //   2378: aload 38
    //   2380: ifnull +28 -> 2408
    //   2383: aload 38
    //   2385: getfield 622	com/google/android/gms/internal/measurement/zzfv:zzavc	Ljava/lang/Boolean;
    //   2388: ifnull +20 -> 2408
    //   2391: aload 38
    //   2393: getfield 622	com/google/android/gms/internal/measurement/zzfv:zzavc	Ljava/lang/Boolean;
    //   2396: invokevirtual 50	java/lang/Boolean:booleanValue	()Z
    //   2399: ifeq +9 -> 2408
    //   2402: iconst_1
    //   2403: istore 7
    //   2405: goto +6 -> 2411
    //   2408: iconst_0
    //   2409: istore 7
    //   2411: aload 23
    //   2413: aload 38
    //   2415: getfield 607	com/google/android/gms/internal/measurement/zzfv:zzave	Ljava/lang/Integer;
    //   2418: invokevirtual 308	java/lang/Integer:intValue	()I
    //   2421: invokevirtual 624	java/util/BitSet:get	(I)Z
    //   2424: ifeq +39 -> 2463
    //   2427: iload 4
    //   2429: ifne +34 -> 2463
    //   2432: iload 7
    //   2434: ifne +29 -> 2463
    //   2437: aload_0
    //   2438: invokevirtual 77	com/google/android/gms/measurement/internal/zzco:zzgo	()Lcom/google/android/gms/measurement/internal/zzap;
    //   2441: invokevirtual 206	com/google/android/gms/measurement/internal/zzap:zzjl	()Lcom/google/android/gms/measurement/internal/zzar;
    //   2444: ldc_w 626
    //   2447: iload 8
    //   2449: invokestatic 364	java/lang/Integer:valueOf	(I)Ljava/lang/Integer;
    //   2452: aload 38
    //   2454: getfield 607	com/google/android/gms/internal/measurement/zzfv:zzave	Ljava/lang/Integer;
    //   2457: invokevirtual 144	com/google/android/gms/measurement/internal/zzar:zze	(Ljava/lang/String;Ljava/lang/Object;Ljava/lang/Object;)V
    //   2460: goto -237 -> 2223
    //   2463: aload 17
    //   2465: astore 36
    //   2467: aload_0
    //   2468: aload 38
    //   2470: aload 27
    //   2472: aload 30
    //   2474: lload 13
    //   2476: invokespecial 628	com/google/android/gms/measurement/internal/zzj:zza	(Lcom/google/android/gms/internal/measurement/zzfv;Ljava/lang/String;[Lcom/google/android/gms/internal/measurement/zzgg;J)Ljava/lang/Boolean;
    //   2479: astore 37
    //   2481: aload_0
    //   2482: invokevirtual 77	com/google/android/gms/measurement/internal/zzco:zzgo	()Lcom/google/android/gms/measurement/internal/zzap;
    //   2485: invokevirtual 206	com/google/android/gms/measurement/internal/zzap:zzjl	()Lcom/google/android/gms/measurement/internal/zzar;
    //   2488: astore 41
    //   2490: aload 37
    //   2492: ifnonnull +11 -> 2503
    //   2495: ldc_w 630
    //   2498: astore 35
    //   2500: goto +7 -> 2507
    //   2503: aload 37
    //   2505: astore 35
    //   2507: aload 41
    //   2509: ldc_w 632
    //   2512: aload 35
    //   2514: invokevirtual 101	com/google/android/gms/measurement/internal/zzar:zzg	(Ljava/lang/String;Ljava/lang/Object;)V
    //   2517: aload 37
    //   2519: ifnonnull +19 -> 2538
    //   2522: aload 20
    //   2524: iload 8
    //   2526: invokestatic 364	java/lang/Integer:valueOf	(I)Ljava/lang/Integer;
    //   2529: invokeinterface 107 2 0
    //   2534: pop
    //   2535: goto +287 -> 2822
    //   2538: aload 28
    //   2540: aload 38
    //   2542: getfield 607	com/google/android/gms/internal/measurement/zzfv:zzave	Ljava/lang/Integer;
    //   2545: invokevirtual 308	java/lang/Integer:intValue	()I
    //   2548: invokevirtual 458	java/util/BitSet:set	(I)V
    //   2551: aload 37
    //   2553: invokevirtual 50	java/lang/Boolean:booleanValue	()Z
    //   2556: ifeq +266 -> 2822
    //   2559: aload 23
    //   2561: aload 38
    //   2563: getfield 607	com/google/android/gms/internal/measurement/zzfv:zzave	Ljava/lang/Integer;
    //   2566: invokevirtual 308	java/lang/Integer:intValue	()I
    //   2569: invokevirtual 458	java/util/BitSet:set	(I)V
    //   2572: iload 4
    //   2574: ifne +8 -> 2582
    //   2577: iload 7
    //   2579: ifeq +243 -> 2822
    //   2582: aload 36
    //   2584: getfield 579	com/google/android/gms/internal/measurement/zzgf:zzawu	Ljava/lang/Long;
    //   2587: ifnull +235 -> 2822
    //   2590: iload 7
    //   2592: ifeq +27 -> 2619
    //   2595: aload 34
    //   2597: aload 38
    //   2599: getfield 607	com/google/android/gms/internal/measurement/zzfv:zzave	Ljava/lang/Integer;
    //   2602: invokevirtual 308	java/lang/Integer:intValue	()I
    //   2605: aload 36
    //   2607: getfield 579	com/google/android/gms/internal/measurement/zzgf:zzawu	Ljava/lang/Long;
    //   2610: invokevirtual 171	java/lang/Long:longValue	()J
    //   2613: invokestatic 634	com/google/android/gms/measurement/internal/zzj:zzb	(Ljava/util/Map;IJ)V
    //   2616: goto +206 -> 2822
    //   2619: aload 29
    //   2621: aload 38
    //   2623: getfield 607	com/google/android/gms/internal/measurement/zzfv:zzave	Ljava/lang/Integer;
    //   2626: invokevirtual 308	java/lang/Integer:intValue	()I
    //   2629: aload 36
    //   2631: getfield 579	com/google/android/gms/internal/measurement/zzgf:zzawu	Ljava/lang/Long;
    //   2634: invokevirtual 171	java/lang/Long:longValue	()J
    //   2637: invokestatic 636	com/google/android/gms/measurement/internal/zzj:zza	(Ljava/util/Map;IJ)V
    //   2640: goto +46 -> 2686
    //   2643: aload 23
    //   2645: astore 36
    //   2647: aload 36
    //   2649: aload 38
    //   2651: getfield 607	com/google/android/gms/internal/measurement/zzfv:zzave	Ljava/lang/Integer;
    //   2654: invokevirtual 308	java/lang/Integer:intValue	()I
    //   2657: invokevirtual 624	java/util/BitSet:get	(I)Z
    //   2660: ifeq +29 -> 2689
    //   2663: aload_0
    //   2664: invokevirtual 77	com/google/android/gms/measurement/internal/zzco:zzgo	()Lcom/google/android/gms/measurement/internal/zzap;
    //   2667: invokevirtual 206	com/google/android/gms/measurement/internal/zzap:zzjl	()Lcom/google/android/gms/measurement/internal/zzar;
    //   2670: ldc_w 638
    //   2673: iload 8
    //   2675: invokestatic 364	java/lang/Integer:valueOf	(I)Ljava/lang/Integer;
    //   2678: aload 38
    //   2680: getfield 607	com/google/android/gms/internal/measurement/zzfv:zzave	Ljava/lang/Integer;
    //   2683: invokevirtual 144	com/google/android/gms/measurement/internal/zzar:zze	(Ljava/lang/String;Ljava/lang/Object;Ljava/lang/Object;)V
    //   2686: goto -463 -> 2223
    //   2689: aload_0
    //   2690: aload 38
    //   2692: aload 27
    //   2694: aload 30
    //   2696: lload 13
    //   2698: invokespecial 628	com/google/android/gms/measurement/internal/zzj:zza	(Lcom/google/android/gms/internal/measurement/zzfv;Ljava/lang/String;[Lcom/google/android/gms/internal/measurement/zzgg;J)Ljava/lang/Boolean;
    //   2701: astore 37
    //   2703: aload_0
    //   2704: invokevirtual 77	com/google/android/gms/measurement/internal/zzco:zzgo	()Lcom/google/android/gms/measurement/internal/zzap;
    //   2707: invokevirtual 206	com/google/android/gms/measurement/internal/zzap:zzjl	()Lcom/google/android/gms/measurement/internal/zzar;
    //   2710: astore 41
    //   2712: aload 37
    //   2714: ifnonnull +11 -> 2725
    //   2717: ldc_w 630
    //   2720: astore 35
    //   2722: goto +7 -> 2729
    //   2725: aload 37
    //   2727: astore 35
    //   2729: aload 41
    //   2731: ldc_w 632
    //   2734: aload 35
    //   2736: invokevirtual 101	com/google/android/gms/measurement/internal/zzar:zzg	(Ljava/lang/String;Ljava/lang/Object;)V
    //   2739: aload 37
    //   2741: ifnonnull +19 -> 2760
    //   2744: aload 20
    //   2746: iload 8
    //   2748: invokestatic 364	java/lang/Integer:valueOf	(I)Ljava/lang/Integer;
    //   2751: invokeinterface 107 2 0
    //   2756: pop
    //   2757: goto +65 -> 2822
    //   2760: aload 28
    //   2762: aload 38
    //   2764: getfield 607	com/google/android/gms/internal/measurement/zzfv:zzave	Ljava/lang/Integer;
    //   2767: invokevirtual 308	java/lang/Integer:intValue	()I
    //   2770: invokevirtual 458	java/util/BitSet:set	(I)V
    //   2773: aload 37
    //   2775: invokevirtual 50	java/lang/Boolean:booleanValue	()Z
    //   2778: ifeq +44 -> 2822
    //   2781: aload 36
    //   2783: aload 38
    //   2785: getfield 607	com/google/android/gms/internal/measurement/zzfv:zzave	Ljava/lang/Integer;
    //   2788: invokevirtual 308	java/lang/Integer:intValue	()I
    //   2791: invokevirtual 458	java/util/BitSet:set	(I)V
    //   2794: goto +28 -> 2822
    //   2797: aload_0
    //   2798: invokevirtual 77	com/google/android/gms/measurement/internal/zzco:zzgo	()Lcom/google/android/gms/measurement/internal/zzap;
    //   2801: invokevirtual 83	com/google/android/gms/measurement/internal/zzap:zzjg	()Lcom/google/android/gms/measurement/internal/zzar;
    //   2804: ldc_w 640
    //   2807: aload_1
    //   2808: invokestatic 574	com/google/android/gms/measurement/internal/zzap:zzbv	(Ljava/lang/String;)Ljava/lang/Object;
    //   2811: aload 38
    //   2813: getfield 607	com/google/android/gms/internal/measurement/zzfv:zzave	Ljava/lang/Integer;
    //   2816: invokestatic 643	java/lang/String:valueOf	(Ljava/lang/Object;)Ljava/lang/String;
    //   2819: invokevirtual 144	com/google/android/gms/measurement/internal/zzar:zze	(Ljava/lang/String;Ljava/lang/Object;Ljava/lang/Object;)V
    //   2822: goto -599 -> 2223
    //   2825: aload 15
    //   2827: astore 28
    //   2829: aload 22
    //   2831: astore 34
    //   2833: aload 27
    //   2835: astore 35
    //   2837: aload 17
    //   2839: astore 29
    //   2841: aload 16
    //   2843: astore 23
    //   2845: aload 18
    //   2847: astore 15
    //   2849: aload 39
    //   2851: astore 27
    //   2853: aload 33
    //   2855: astore 16
    //   2857: aload 32
    //   2859: astore 17
    //   2861: aload 21
    //   2863: astore 18
    //   2865: aload 19
    //   2867: astore 22
    //   2869: aload 34
    //   2871: astore 19
    //   2873: aload 28
    //   2875: astore 21
    //   2877: goto -1070 -> 1807
    //   2880: aload 15
    //   2882: astore 28
    //   2884: aload 20
    //   2886: astore 23
    //   2888: aload 21
    //   2890: astore 15
    //   2892: aload 28
    //   2894: astore 20
    //   2896: aload 25
    //   2898: astore 21
    //   2900: iload 6
    //   2902: iconst_1
    //   2903: iadd
    //   2904: istore 6
    //   2906: aload 23
    //   2908: astore 28
    //   2910: aload 27
    //   2912: astore 25
    //   2914: aload 16
    //   2916: astore 23
    //   2918: aload 18
    //   2920: astore 16
    //   2922: aload 22
    //   2924: astore 18
    //   2926: aload 19
    //   2928: astore 27
    //   2930: aload 20
    //   2932: astore 29
    //   2934: aload 25
    //   2936: astore 22
    //   2938: aload 21
    //   2940: astore 25
    //   2942: aload 28
    //   2944: astore 19
    //   2946: aload 15
    //   2948: astore 20
    //   2950: aload 17
    //   2952: astore 15
    //   2954: aload 29
    //   2956: astore 21
    //   2958: aload 27
    //   2960: astore 17
    //   2962: goto -2219 -> 743
    //   2965: aload 33
    //   2967: astore 15
    //   2969: aload 32
    //   2971: astore 26
    //   2973: aload 31
    //   2975: astore 18
    //   2977: aload 30
    //   2979: astore 25
    //   2981: aload 28
    //   2983: astore 16
    //   2985: aload 27
    //   2987: astore 21
    //   2989: aload_3
    //   2990: astore 24
    //   2992: aload 15
    //   2994: astore_2
    //   2995: aload 25
    //   2997: astore 17
    //   2999: aload 16
    //   3001: astore 19
    //   3003: aload 21
    //   3005: astore 22
    //   3007: aload 18
    //   3009: astore 20
    //   3011: aload 24
    //   3013: ifnull +1309 -> 4322
    //   3016: new 109	androidx/collection/ArrayMap
    //   3019: dup
    //   3020: invokespecial 110	androidx/collection/ArrayMap:<init>	()V
    //   3023: astore 23
    //   3025: aload 24
    //   3027: arraylength
    //   3028: istore 4
    //   3030: iconst_0
    //   3031: istore 5
    //   3033: aload 29
    //   3035: astore 27
    //   3037: aload 15
    //   3039: astore_2
    //   3040: aload 25
    //   3042: astore 17
    //   3044: aload 16
    //   3046: astore 19
    //   3048: aload 21
    //   3050: astore 22
    //   3052: aload 18
    //   3054: astore 20
    //   3056: iload 5
    //   3058: iload 4
    //   3060: if_icmpge +1262 -> 4322
    //   3063: aload_3
    //   3064: iload 5
    //   3066: aaload
    //   3067: astore 33
    //   3069: aload 23
    //   3071: aload 33
    //   3073: getfield 222	com/google/android/gms/internal/measurement/zzgl:name	Ljava/lang/String;
    //   3076: invokeinterface 160 2 0
    //   3081: checkcast 124	java/util/Map
    //   3084: astore 24
    //   3086: aload 24
    //   3088: ifnonnull +51 -> 3139
    //   3091: aload_0
    //   3092: invokevirtual 431	com/google/android/gms/measurement/internal/zzey:zzjq	()Lcom/google/android/gms/measurement/internal/zzq;
    //   3095: aload_1
    //   3096: aload 33
    //   3098: getfield 222	com/google/android/gms/internal/measurement/zzgl:name	Ljava/lang/String;
    //   3101: invokevirtual 646	com/google/android/gms/measurement/internal/zzq:zzm	(Ljava/lang/String;Ljava/lang/String;)Ljava/util/Map;
    //   3104: astore_2
    //   3105: aload_2
    //   3106: astore 24
    //   3108: aload_2
    //   3109: ifnonnull +12 -> 3121
    //   3112: new 109	androidx/collection/ArrayMap
    //   3115: dup
    //   3116: invokespecial 110	androidx/collection/ArrayMap:<init>	()V
    //   3119: astore 24
    //   3121: aload 23
    //   3123: aload 33
    //   3125: getfield 222	com/google/android/gms/internal/measurement/zzgl:name	Ljava/lang/String;
    //   3128: aload 24
    //   3130: invokeinterface 128 3 0
    //   3135: pop
    //   3136: goto +3 -> 3139
    //   3139: aload 24
    //   3141: invokeinterface 381 1 0
    //   3146: invokeinterface 385 1 0
    //   3151: astore 17
    //   3153: aload 27
    //   3155: astore_2
    //   3156: aload 26
    //   3158: astore 20
    //   3160: aload 34
    //   3162: astore 19
    //   3164: aload 23
    //   3166: astore 22
    //   3168: aload 17
    //   3170: invokeinterface 390 1 0
    //   3175: ifeq +1123 -> 4298
    //   3178: aload 17
    //   3180: invokeinterface 394 1 0
    //   3185: checkcast 305	java/lang/Integer
    //   3188: invokevirtual 308	java/lang/Integer:intValue	()I
    //   3191: istore 8
    //   3193: aload 35
    //   3195: iload 8
    //   3197: invokestatic 364	java/lang/Integer:valueOf	(I)Ljava/lang/Integer;
    //   3200: invokeinterface 118 2 0
    //   3205: ifeq +23 -> 3228
    //   3208: aload_0
    //   3209: invokevirtual 77	com/google/android/gms/measurement/internal/zzco:zzgo	()Lcom/google/android/gms/measurement/internal/zzap;
    //   3212: invokevirtual 206	com/google/android/gms/measurement/internal/zzap:zzjl	()Lcom/google/android/gms/measurement/internal/zzar;
    //   3215: aload 19
    //   3217: iload 8
    //   3219: invokestatic 364	java/lang/Integer:valueOf	(I)Ljava/lang/Integer;
    //   3222: invokevirtual 101	com/google/android/gms/measurement/internal/zzar:zzg	(Ljava/lang/String;Ljava/lang/Object;)V
    //   3225: goto -57 -> 3168
    //   3228: aload 18
    //   3230: astore 26
    //   3232: aload 26
    //   3234: iload 8
    //   3236: invokestatic 364	java/lang/Integer:valueOf	(I)Ljava/lang/Integer;
    //   3239: invokeinterface 160 2 0
    //   3244: checkcast 466	com/google/android/gms/internal/measurement/zzgd
    //   3247: astore 27
    //   3249: aload 21
    //   3251: iload 8
    //   3253: invokestatic 364	java/lang/Integer:valueOf	(I)Ljava/lang/Integer;
    //   3256: invokeinterface 160 2 0
    //   3261: checkcast 441	java/util/BitSet
    //   3264: astore 29
    //   3266: aload 16
    //   3268: astore 31
    //   3270: aload 31
    //   3272: iload 8
    //   3274: invokestatic 364	java/lang/Integer:valueOf	(I)Ljava/lang/Integer;
    //   3277: invokeinterface 160 2 0
    //   3282: checkcast 441	java/util/BitSet
    //   3285: astore 30
    //   3287: iload 10
    //   3289: ifeq +40 -> 3329
    //   3292: aload 25
    //   3294: iload 8
    //   3296: invokestatic 364	java/lang/Integer:valueOf	(I)Ljava/lang/Integer;
    //   3299: invokeinterface 160 2 0
    //   3304: checkcast 124	java/util/Map
    //   3307: astore 18
    //   3309: aload 15
    //   3311: iload 8
    //   3313: invokestatic 364	java/lang/Integer:valueOf	(I)Ljava/lang/Integer;
    //   3316: invokeinterface 160 2 0
    //   3321: checkcast 124	java/util/Map
    //   3324: astore 16
    //   3326: goto +9 -> 3335
    //   3329: aconst_null
    //   3330: astore 16
    //   3332: aconst_null
    //   3333: astore 18
    //   3335: aload 17
    //   3337: astore 23
    //   3339: aload 15
    //   3341: astore 32
    //   3343: aload 27
    //   3345: ifnonnull +156 -> 3501
    //   3348: new 466	com/google/android/gms/internal/measurement/zzgd
    //   3351: dup
    //   3352: invokespecial 467	com/google/android/gms/internal/measurement/zzgd:<init>	()V
    //   3355: astore 15
    //   3357: aload 26
    //   3359: iload 8
    //   3361: invokestatic 364	java/lang/Integer:valueOf	(I)Ljava/lang/Integer;
    //   3364: aload 15
    //   3366: invokeinterface 128 3 0
    //   3371: pop
    //   3372: aload 15
    //   3374: aload_2
    //   3375: putfield 470	com/google/android/gms/internal/measurement/zzgd:zzawo	Ljava/lang/Boolean;
    //   3378: new 441	java/util/BitSet
    //   3381: dup
    //   3382: invokespecial 446	java/util/BitSet:<init>	()V
    //   3385: astore 29
    //   3387: aload 21
    //   3389: iload 8
    //   3391: invokestatic 364	java/lang/Integer:valueOf	(I)Ljava/lang/Integer;
    //   3394: aload 29
    //   3396: invokeinterface 128 3 0
    //   3401: pop
    //   3402: new 441	java/util/BitSet
    //   3405: dup
    //   3406: invokespecial 446	java/util/BitSet:<init>	()V
    //   3409: astore 30
    //   3411: aload 31
    //   3413: iload 8
    //   3415: invokestatic 364	java/lang/Integer:valueOf	(I)Ljava/lang/Integer;
    //   3418: aload 30
    //   3420: invokeinterface 128 3 0
    //   3425: pop
    //   3426: iload 10
    //   3428: ifeq +54 -> 3482
    //   3431: new 109	androidx/collection/ArrayMap
    //   3434: dup
    //   3435: invokespecial 110	androidx/collection/ArrayMap:<init>	()V
    //   3438: astore 16
    //   3440: aload 25
    //   3442: iload 8
    //   3444: invokestatic 364	java/lang/Integer:valueOf	(I)Ljava/lang/Integer;
    //   3447: aload 16
    //   3449: invokeinterface 128 3 0
    //   3454: pop
    //   3455: new 109	androidx/collection/ArrayMap
    //   3458: dup
    //   3459: invokespecial 110	androidx/collection/ArrayMap:<init>	()V
    //   3462: astore 15
    //   3464: aload 32
    //   3466: iload 8
    //   3468: invokestatic 364	java/lang/Integer:valueOf	(I)Ljava/lang/Integer;
    //   3471: aload 15
    //   3473: invokeinterface 128 3 0
    //   3478: pop
    //   3479: goto +11 -> 3490
    //   3482: aload 16
    //   3484: astore 15
    //   3486: aload 18
    //   3488: astore 16
    //   3490: aload 16
    //   3492: astore 27
    //   3494: aload 15
    //   3496: astore 28
    //   3498: goto +11 -> 3509
    //   3501: aload 16
    //   3503: astore 28
    //   3505: aload 18
    //   3507: astore 27
    //   3509: aload 25
    //   3511: astore 18
    //   3513: aload_2
    //   3514: astore 25
    //   3516: aload 24
    //   3518: iload 8
    //   3520: invokestatic 364	java/lang/Integer:valueOf	(I)Ljava/lang/Integer;
    //   3523: invokeinterface 160 2 0
    //   3528: checkcast 246	java/util/List
    //   3531: invokeinterface 598 1 0
    //   3536: astore_2
    //   3537: aload 26
    //   3539: astore 17
    //   3541: aload 19
    //   3543: astore 16
    //   3545: aload_2
    //   3546: astore 26
    //   3548: aload 32
    //   3550: astore 15
    //   3552: aload 24
    //   3554: astore 19
    //   3556: aload 31
    //   3558: astore_2
    //   3559: aload 26
    //   3561: invokeinterface 390 1 0
    //   3566: ifeq +695 -> 4261
    //   3569: aload 26
    //   3571: invokeinterface 394 1 0
    //   3576: checkcast 213	com/google/android/gms/internal/measurement/zzfy
    //   3579: astore 32
    //   3581: aload_0
    //   3582: invokevirtual 77	com/google/android/gms/measurement/internal/zzco:zzgo	()Lcom/google/android/gms/measurement/internal/zzap;
    //   3585: astore 24
    //   3587: aload 24
    //   3589: iconst_2
    //   3590: invokevirtual 602	com/google/android/gms/measurement/internal/zzap:isLoggable	(I)Z
    //   3593: ifeq +62 -> 3655
    //   3596: aload_0
    //   3597: invokevirtual 77	com/google/android/gms/measurement/internal/zzco:zzgo	()Lcom/google/android/gms/measurement/internal/zzap;
    //   3600: invokevirtual 206	com/google/android/gms/measurement/internal/zzap:zzjl	()Lcom/google/android/gms/measurement/internal/zzar;
    //   3603: ldc_w 648
    //   3606: iload 8
    //   3608: invokestatic 364	java/lang/Integer:valueOf	(I)Ljava/lang/Integer;
    //   3611: aload 32
    //   3613: getfield 649	com/google/android/gms/internal/measurement/zzfy:zzave	Ljava/lang/Integer;
    //   3616: aload_0
    //   3617: invokevirtual 89	com/google/android/gms/measurement/internal/zzco:zzgl	()Lcom/google/android/gms/measurement/internal/zzan;
    //   3620: aload 32
    //   3622: getfield 652	com/google/android/gms/internal/measurement/zzfy:zzavu	Ljava/lang/String;
    //   3625: invokevirtual 225	com/google/android/gms/measurement/internal/zzan:zzbu	(Ljava/lang/String;)Ljava/lang/String;
    //   3628: invokevirtual 613	com/google/android/gms/measurement/internal/zzar:zzd	(Ljava/lang/String;Ljava/lang/Object;Ljava/lang/Object;Ljava/lang/Object;)V
    //   3631: aload_0
    //   3632: invokevirtual 77	com/google/android/gms/measurement/internal/zzco:zzgo	()Lcom/google/android/gms/measurement/internal/zzap;
    //   3635: invokevirtual 206	com/google/android/gms/measurement/internal/zzap:zzjl	()Lcom/google/android/gms/measurement/internal/zzar;
    //   3638: aload 20
    //   3640: aload_0
    //   3641: invokevirtual 501	com/google/android/gms/measurement/internal/zzey:zzjo	()Lcom/google/android/gms/measurement/internal/zzfg;
    //   3644: aload 32
    //   3646: invokevirtual 655	com/google/android/gms/measurement/internal/zzfg:zza	(Lcom/google/android/gms/internal/measurement/zzfy;)Ljava/lang/String;
    //   3649: invokevirtual 101	com/google/android/gms/measurement/internal/zzar:zzg	(Ljava/lang/String;Ljava/lang/Object;)V
    //   3652: goto +3 -> 3655
    //   3655: aload 32
    //   3657: getfield 649	com/google/android/gms/internal/measurement/zzfy:zzave	Ljava/lang/Integer;
    //   3660: ifnull +514 -> 4174
    //   3663: aload 32
    //   3665: getfield 649	com/google/android/gms/internal/measurement/zzfy:zzave	Ljava/lang/Integer;
    //   3668: invokevirtual 308	java/lang/Integer:intValue	()I
    //   3671: sipush 256
    //   3674: if_icmple +6 -> 3680
    //   3677: goto +497 -> 4174
    //   3680: iload 10
    //   3682: ifeq +326 -> 4008
    //   3685: aload 32
    //   3687: ifnull +28 -> 3715
    //   3690: aload 32
    //   3692: getfield 656	com/google/android/gms/internal/measurement/zzfy:zzavb	Ljava/lang/Boolean;
    //   3695: ifnull +20 -> 3715
    //   3698: aload 32
    //   3700: getfield 656	com/google/android/gms/internal/measurement/zzfy:zzavb	Ljava/lang/Boolean;
    //   3703: invokevirtual 50	java/lang/Boolean:booleanValue	()Z
    //   3706: ifeq +9 -> 3715
    //   3709: iconst_1
    //   3710: istore 6
    //   3712: goto +6 -> 3718
    //   3715: iconst_0
    //   3716: istore 6
    //   3718: aload 32
    //   3720: ifnull +28 -> 3748
    //   3723: aload 32
    //   3725: getfield 657	com/google/android/gms/internal/measurement/zzfy:zzavc	Ljava/lang/Boolean;
    //   3728: ifnull +20 -> 3748
    //   3731: aload 32
    //   3733: getfield 657	com/google/android/gms/internal/measurement/zzfy:zzavc	Ljava/lang/Boolean;
    //   3736: invokevirtual 50	java/lang/Boolean:booleanValue	()Z
    //   3739: ifeq +9 -> 3748
    //   3742: iconst_1
    //   3743: istore 7
    //   3745: goto +6 -> 3751
    //   3748: iconst_0
    //   3749: istore 7
    //   3751: aload 29
    //   3753: aload 32
    //   3755: getfield 649	com/google/android/gms/internal/measurement/zzfy:zzave	Ljava/lang/Integer;
    //   3758: invokevirtual 308	java/lang/Integer:intValue	()I
    //   3761: invokevirtual 624	java/util/BitSet:get	(I)Z
    //   3764: ifeq +39 -> 3803
    //   3767: iload 6
    //   3769: ifne +34 -> 3803
    //   3772: iload 7
    //   3774: ifne +29 -> 3803
    //   3777: aload_0
    //   3778: invokevirtual 77	com/google/android/gms/measurement/internal/zzco:zzgo	()Lcom/google/android/gms/measurement/internal/zzap;
    //   3781: invokevirtual 206	com/google/android/gms/measurement/internal/zzap:zzjl	()Lcom/google/android/gms/measurement/internal/zzar;
    //   3784: ldc_w 659
    //   3787: iload 8
    //   3789: invokestatic 364	java/lang/Integer:valueOf	(I)Ljava/lang/Integer;
    //   3792: aload 32
    //   3794: getfield 649	com/google/android/gms/internal/measurement/zzfy:zzave	Ljava/lang/Integer;
    //   3797: invokevirtual 144	com/google/android/gms/measurement/internal/zzar:zze	(Ljava/lang/String;Ljava/lang/Object;Ljava/lang/Object;)V
    //   3800: goto -241 -> 3559
    //   3803: aload_0
    //   3804: aload 32
    //   3806: aload 33
    //   3808: invokespecial 661	com/google/android/gms/measurement/internal/zzj:zza	(Lcom/google/android/gms/internal/measurement/zzfy;Lcom/google/android/gms/internal/measurement/zzgl;)Ljava/lang/Boolean;
    //   3811: astore 31
    //   3813: aload_0
    //   3814: invokevirtual 77	com/google/android/gms/measurement/internal/zzco:zzgo	()Lcom/google/android/gms/measurement/internal/zzap;
    //   3817: astore 24
    //   3819: aload 24
    //   3821: invokevirtual 206	com/google/android/gms/measurement/internal/zzap:zzjl	()Lcom/google/android/gms/measurement/internal/zzar;
    //   3824: astore 34
    //   3826: aload 31
    //   3828: ifnonnull +11 -> 3839
    //   3831: ldc_w 630
    //   3834: astore 24
    //   3836: goto +7 -> 3843
    //   3839: aload 31
    //   3841: astore 24
    //   3843: aload 34
    //   3845: ldc_w 663
    //   3848: aload 24
    //   3850: invokevirtual 101	com/google/android/gms/measurement/internal/zzar:zzg	(Ljava/lang/String;Ljava/lang/Object;)V
    //   3853: aload 31
    //   3855: ifnonnull +23 -> 3878
    //   3858: aload 35
    //   3860: iload 8
    //   3862: invokestatic 364	java/lang/Integer:valueOf	(I)Ljava/lang/Integer;
    //   3865: invokeinterface 107 2 0
    //   3870: pop
    //   3871: aload 18
    //   3873: astore 24
    //   3875: goto +176 -> 4051
    //   3878: aload 30
    //   3880: aload 32
    //   3882: getfield 649	com/google/android/gms/internal/measurement/zzfy:zzave	Ljava/lang/Integer;
    //   3885: invokevirtual 308	java/lang/Integer:intValue	()I
    //   3888: invokevirtual 458	java/util/BitSet:set	(I)V
    //   3891: aload 29
    //   3893: aload 32
    //   3895: getfield 649	com/google/android/gms/internal/measurement/zzfy:zzave	Ljava/lang/Integer;
    //   3898: invokevirtual 308	java/lang/Integer:intValue	()I
    //   3901: aload 31
    //   3903: invokevirtual 50	java/lang/Boolean:booleanValue	()Z
    //   3906: invokevirtual 666	java/util/BitSet:set	(IZ)V
    //   3909: aload 18
    //   3911: astore 24
    //   3913: aload 31
    //   3915: invokevirtual 50	java/lang/Boolean:booleanValue	()Z
    //   3918: ifeq +133 -> 4051
    //   3921: iload 6
    //   3923: ifne +12 -> 3935
    //   3926: aload 18
    //   3928: astore 24
    //   3930: iload 7
    //   3932: ifeq +119 -> 4051
    //   3935: aload 18
    //   3937: astore 24
    //   3939: aload 33
    //   3941: getfield 669	com/google/android/gms/internal/measurement/zzgl:zzayl	Ljava/lang/Long;
    //   3944: ifnull +107 -> 4051
    //   3947: iload 7
    //   3949: ifeq +31 -> 3980
    //   3952: aload 28
    //   3954: aload 32
    //   3956: getfield 649	com/google/android/gms/internal/measurement/zzfy:zzave	Ljava/lang/Integer;
    //   3959: invokevirtual 308	java/lang/Integer:intValue	()I
    //   3962: aload 33
    //   3964: getfield 669	com/google/android/gms/internal/measurement/zzgl:zzayl	Ljava/lang/Long;
    //   3967: invokevirtual 171	java/lang/Long:longValue	()J
    //   3970: invokestatic 634	com/google/android/gms/measurement/internal/zzj:zzb	(Ljava/util/Map;IJ)V
    //   3973: aload 18
    //   3975: astore 24
    //   3977: goto +74 -> 4051
    //   3980: aload 27
    //   3982: aload 32
    //   3984: getfield 649	com/google/android/gms/internal/measurement/zzfy:zzave	Ljava/lang/Integer;
    //   3987: invokevirtual 308	java/lang/Integer:intValue	()I
    //   3990: aload 33
    //   3992: getfield 669	com/google/android/gms/internal/measurement/zzgl:zzayl	Ljava/lang/Long;
    //   3995: invokevirtual 171	java/lang/Long:longValue	()J
    //   3998: invokestatic 636	com/google/android/gms/measurement/internal/zzj:zza	(Ljava/util/Map;IJ)V
    //   4001: aload 18
    //   4003: astore 24
    //   4005: goto +46 -> 4051
    //   4008: aload 29
    //   4010: aload 32
    //   4012: getfield 649	com/google/android/gms/internal/measurement/zzfy:zzave	Ljava/lang/Integer;
    //   4015: invokevirtual 308	java/lang/Integer:intValue	()I
    //   4018: invokevirtual 624	java/util/BitSet:get	(I)Z
    //   4021: ifeq +37 -> 4058
    //   4024: aload_0
    //   4025: invokevirtual 77	com/google/android/gms/measurement/internal/zzco:zzgo	()Lcom/google/android/gms/measurement/internal/zzap;
    //   4028: invokevirtual 206	com/google/android/gms/measurement/internal/zzap:zzjl	()Lcom/google/android/gms/measurement/internal/zzar;
    //   4031: ldc_w 671
    //   4034: iload 8
    //   4036: invokestatic 364	java/lang/Integer:valueOf	(I)Ljava/lang/Integer;
    //   4039: aload 32
    //   4041: getfield 649	com/google/android/gms/internal/measurement/zzfy:zzave	Ljava/lang/Integer;
    //   4044: invokevirtual 144	com/google/android/gms/measurement/internal/zzar:zze	(Ljava/lang/String;Ljava/lang/Object;Ljava/lang/Object;)V
    //   4047: aload 18
    //   4049: astore 24
    //   4051: aload 24
    //   4053: astore 18
    //   4055: goto -496 -> 3559
    //   4058: aload_0
    //   4059: aload 32
    //   4061: aload 33
    //   4063: invokespecial 661	com/google/android/gms/measurement/internal/zzj:zza	(Lcom/google/android/gms/internal/measurement/zzfy;Lcom/google/android/gms/internal/measurement/zzgl;)Ljava/lang/Boolean;
    //   4066: astore 31
    //   4068: aload_0
    //   4069: invokevirtual 77	com/google/android/gms/measurement/internal/zzco:zzgo	()Lcom/google/android/gms/measurement/internal/zzap;
    //   4072: invokevirtual 206	com/google/android/gms/measurement/internal/zzap:zzjl	()Lcom/google/android/gms/measurement/internal/zzar;
    //   4075: astore 34
    //   4077: aload 31
    //   4079: ifnonnull +11 -> 4090
    //   4082: ldc_w 630
    //   4085: astore 24
    //   4087: goto +7 -> 4094
    //   4090: aload 31
    //   4092: astore 24
    //   4094: aload 34
    //   4096: ldc_w 663
    //   4099: aload 24
    //   4101: invokevirtual 101	com/google/android/gms/measurement/internal/zzar:zzg	(Ljava/lang/String;Ljava/lang/Object;)V
    //   4104: aload 31
    //   4106: ifnonnull +23 -> 4129
    //   4109: aload 35
    //   4111: iload 8
    //   4113: invokestatic 364	java/lang/Integer:valueOf	(I)Ljava/lang/Integer;
    //   4116: invokeinterface 107 2 0
    //   4121: pop
    //   4122: aload 18
    //   4124: astore 24
    //   4126: goto -75 -> 4051
    //   4129: aload 30
    //   4131: aload 32
    //   4133: getfield 649	com/google/android/gms/internal/measurement/zzfy:zzave	Ljava/lang/Integer;
    //   4136: invokevirtual 308	java/lang/Integer:intValue	()I
    //   4139: invokevirtual 458	java/util/BitSet:set	(I)V
    //   4142: aload 18
    //   4144: astore 24
    //   4146: aload 31
    //   4148: invokevirtual 50	java/lang/Boolean:booleanValue	()Z
    //   4151: ifeq -100 -> 4051
    //   4154: aload 29
    //   4156: aload 32
    //   4158: getfield 649	com/google/android/gms/internal/measurement/zzfy:zzave	Ljava/lang/Integer;
    //   4161: invokevirtual 308	java/lang/Integer:intValue	()I
    //   4164: invokevirtual 458	java/util/BitSet:set	(I)V
    //   4167: aload 18
    //   4169: astore 24
    //   4171: goto -120 -> 4051
    //   4174: aload_0
    //   4175: invokevirtual 77	com/google/android/gms/measurement/internal/zzco:zzgo	()Lcom/google/android/gms/measurement/internal/zzap;
    //   4178: invokevirtual 83	com/google/android/gms/measurement/internal/zzap:zzjg	()Lcom/google/android/gms/measurement/internal/zzar;
    //   4181: ldc_w 673
    //   4184: aload_1
    //   4185: invokestatic 574	com/google/android/gms/measurement/internal/zzap:zzbv	(Ljava/lang/String;)Ljava/lang/Object;
    //   4188: aload 32
    //   4190: getfield 649	com/google/android/gms/internal/measurement/zzfy:zzave	Ljava/lang/Integer;
    //   4193: invokestatic 643	java/lang/String:valueOf	(Ljava/lang/Object;)Ljava/lang/String;
    //   4196: invokevirtual 144	com/google/android/gms/measurement/internal/zzar:zze	(Ljava/lang/String;Ljava/lang/Object;Ljava/lang/Object;)V
    //   4199: aload 35
    //   4201: iload 8
    //   4203: invokestatic 364	java/lang/Integer:valueOf	(I)Ljava/lang/Integer;
    //   4206: invokeinterface 107 2 0
    //   4211: pop
    //   4212: aload 21
    //   4214: astore 27
    //   4216: aload 23
    //   4218: astore 21
    //   4220: aload 25
    //   4222: astore 23
    //   4224: aload 17
    //   4226: astore 26
    //   4228: aload 19
    //   4230: astore 24
    //   4232: aload 21
    //   4234: astore 17
    //   4236: aload 16
    //   4238: astore 19
    //   4240: aload 18
    //   4242: astore 25
    //   4244: aload_2
    //   4245: astore 16
    //   4247: aload 27
    //   4249: astore 21
    //   4251: aload 23
    //   4253: astore_2
    //   4254: aload 26
    //   4256: astore 18
    //   4258: goto -1090 -> 3168
    //   4261: aload 17
    //   4263: astore 26
    //   4265: aload 23
    //   4267: astore 17
    //   4269: aload 25
    //   4271: astore 23
    //   4273: aload 19
    //   4275: astore 24
    //   4277: aload 16
    //   4279: astore 19
    //   4281: aload 18
    //   4283: astore 25
    //   4285: aload_2
    //   4286: astore 16
    //   4288: aload 23
    //   4290: astore_2
    //   4291: aload 26
    //   4293: astore 18
    //   4295: goto -1127 -> 3168
    //   4298: iload 5
    //   4300: iconst_1
    //   4301: iadd
    //   4302: istore 5
    //   4304: aload 22
    //   4306: astore 23
    //   4308: aload 19
    //   4310: astore 34
    //   4312: aload 20
    //   4314: astore 26
    //   4316: aload_2
    //   4317: astore 27
    //   4319: goto -1282 -> 3037
    //   4322: aload 20
    //   4324: astore_3
    //   4325: aload 22
    //   4327: invokeinterface 375 1 0
    //   4332: anewarray 466	com/google/android/gms/internal/measurement/zzgd
    //   4335: astore 20
    //   4337: aload 22
    //   4339: invokeinterface 381 1 0
    //   4344: invokeinterface 385 1 0
    //   4349: astore 16
    //   4351: iconst_0
    //   4352: istore 4
    //   4354: aload_2
    //   4355: astore 15
    //   4357: aload 16
    //   4359: astore_2
    //   4360: aload_2
    //   4361: invokeinterface 390 1 0
    //   4366: ifeq +630 -> 4996
    //   4369: aload_2
    //   4370: invokeinterface 394 1 0
    //   4375: checkcast 305	java/lang/Integer
    //   4378: invokevirtual 308	java/lang/Integer:intValue	()I
    //   4381: istore 7
    //   4383: aload 35
    //   4385: iload 7
    //   4387: invokestatic 364	java/lang/Integer:valueOf	(I)Ljava/lang/Integer;
    //   4390: invokeinterface 118 2 0
    //   4395: ifne +598 -> 4993
    //   4398: aload_3
    //   4399: iload 7
    //   4401: invokestatic 364	java/lang/Integer:valueOf	(I)Ljava/lang/Integer;
    //   4404: invokeinterface 160 2 0
    //   4409: checkcast 466	com/google/android/gms/internal/measurement/zzgd
    //   4412: astore 18
    //   4414: aload 18
    //   4416: astore 16
    //   4418: aload 18
    //   4420: ifnonnull +12 -> 4432
    //   4423: new 466	com/google/android/gms/internal/measurement/zzgd
    //   4426: dup
    //   4427: invokespecial 467	com/google/android/gms/internal/measurement/zzgd:<init>	()V
    //   4430: astore 16
    //   4432: aload 20
    //   4434: iload 4
    //   4436: aload 16
    //   4438: aastore
    //   4439: aload 16
    //   4441: iload 7
    //   4443: invokestatic 364	java/lang/Integer:valueOf	(I)Ljava/lang/Integer;
    //   4446: putfield 676	com/google/android/gms/internal/measurement/zzgd:zzauy	Ljava/lang/Integer;
    //   4449: aload 16
    //   4451: new 439	com/google/android/gms/internal/measurement/zzgj
    //   4454: dup
    //   4455: invokespecial 475	com/google/android/gms/internal/measurement/zzgj:<init>	()V
    //   4458: putfield 478	com/google/android/gms/internal/measurement/zzgd:zzawm	Lcom/google/android/gms/internal/measurement/zzgj;
    //   4461: aload 16
    //   4463: getfield 478	com/google/android/gms/internal/measurement/zzgd:zzawm	Lcom/google/android/gms/internal/measurement/zzgj;
    //   4466: aload 22
    //   4468: iload 7
    //   4470: invokestatic 364	java/lang/Integer:valueOf	(I)Ljava/lang/Integer;
    //   4473: invokeinterface 160 2 0
    //   4478: checkcast 441	java/util/BitSet
    //   4481: invokestatic 481	com/google/android/gms/measurement/internal/zzfg:zza	(Ljava/util/BitSet;)[J
    //   4484: putfield 461	com/google/android/gms/internal/measurement/zzgj:zzayf	[J
    //   4487: aload 16
    //   4489: getfield 478	com/google/android/gms/internal/measurement/zzgd:zzawm	Lcom/google/android/gms/internal/measurement/zzgj;
    //   4492: aload 19
    //   4494: iload 7
    //   4496: invokestatic 364	java/lang/Integer:valueOf	(I)Ljava/lang/Integer;
    //   4499: invokeinterface 160 2 0
    //   4504: checkcast 441	java/util/BitSet
    //   4507: invokestatic 481	com/google/android/gms/measurement/internal/zzfg:zza	(Ljava/util/BitSet;)[J
    //   4510: putfield 450	com/google/android/gms/internal/measurement/zzgj:zzaye	[J
    //   4513: iload 10
    //   4515: ifeq +254 -> 4769
    //   4518: aload 16
    //   4520: getfield 478	com/google/android/gms/internal/measurement/zzgd:zzawm	Lcom/google/android/gms/internal/measurement/zzgj;
    //   4523: aload 17
    //   4525: iload 7
    //   4527: invokestatic 364	java/lang/Integer:valueOf	(I)Ljava/lang/Integer;
    //   4530: invokeinterface 160 2 0
    //   4535: checkcast 124	java/util/Map
    //   4538: invokestatic 483	com/google/android/gms/measurement/internal/zzj:zzd	(Ljava/util/Map;)[Lcom/google/android/gms/internal/measurement/zzge;
    //   4541: putfield 445	com/google/android/gms/internal/measurement/zzgj:zzayg	[Lcom/google/android/gms/internal/measurement/zzge;
    //   4544: aload 16
    //   4546: getfield 478	com/google/android/gms/internal/measurement/zzgd:zzawm	Lcom/google/android/gms/internal/measurement/zzgj;
    //   4549: astore 21
    //   4551: aload 15
    //   4553: iload 7
    //   4555: invokestatic 364	java/lang/Integer:valueOf	(I)Ljava/lang/Integer;
    //   4558: invokeinterface 160 2 0
    //   4563: checkcast 124	java/util/Map
    //   4566: astore 23
    //   4568: aload 23
    //   4570: ifnonnull +12 -> 4582
    //   4573: iconst_0
    //   4574: anewarray 678	com/google/android/gms/internal/measurement/zzgk
    //   4577: astore 18
    //   4579: goto +180 -> 4759
    //   4582: aload 23
    //   4584: invokeinterface 375 1 0
    //   4589: anewarray 678	com/google/android/gms/internal/measurement/zzgk
    //   4592: astore 18
    //   4594: aload 23
    //   4596: invokeinterface 381 1 0
    //   4601: invokeinterface 385 1 0
    //   4606: astore 24
    //   4608: iconst_0
    //   4609: istore 5
    //   4611: aload 24
    //   4613: invokeinterface 390 1 0
    //   4618: ifeq +141 -> 4759
    //   4621: aload 24
    //   4623: invokeinterface 394 1 0
    //   4628: checkcast 305	java/lang/Integer
    //   4631: astore 26
    //   4633: new 678	com/google/android/gms/internal/measurement/zzgk
    //   4636: dup
    //   4637: invokespecial 679	com/google/android/gms/internal/measurement/zzgk:<init>	()V
    //   4640: astore 25
    //   4642: aload 25
    //   4644: aload 26
    //   4646: putfield 680	com/google/android/gms/internal/measurement/zzgk:zzawq	Ljava/lang/Integer;
    //   4649: aload 23
    //   4651: aload 26
    //   4653: invokeinterface 160 2 0
    //   4658: checkcast 246	java/util/List
    //   4661: astore 27
    //   4663: aload 27
    //   4665: ifnull +78 -> 4743
    //   4668: aload 27
    //   4670: invokestatic 686	java/util/Collections:sort	(Ljava/util/List;)V
    //   4673: aload 27
    //   4675: invokeinterface 250 1 0
    //   4680: newarray long
    //   4682: astore 26
    //   4684: aload 27
    //   4686: invokeinterface 598 1 0
    //   4691: astore 27
    //   4693: iconst_0
    //   4694: istore 6
    //   4696: aload 27
    //   4698: invokeinterface 390 1 0
    //   4703: ifeq +30 -> 4733
    //   4706: aload 26
    //   4708: iload 6
    //   4710: aload 27
    //   4712: invokeinterface 394 1 0
    //   4717: checkcast 162	java/lang/Long
    //   4720: invokevirtual 171	java/lang/Long:longValue	()J
    //   4723: lastore
    //   4724: iload 6
    //   4726: iconst_1
    //   4727: iadd
    //   4728: istore 6
    //   4730: goto -34 -> 4696
    //   4733: aload 25
    //   4735: aload 26
    //   4737: putfield 689	com/google/android/gms/internal/measurement/zzgk:zzayj	[J
    //   4740: goto +3 -> 4743
    //   4743: aload 18
    //   4745: iload 5
    //   4747: aload 25
    //   4749: aastore
    //   4750: iload 5
    //   4752: iconst_1
    //   4753: iadd
    //   4754: istore 5
    //   4756: goto -145 -> 4611
    //   4759: aload 21
    //   4761: aload 18
    //   4763: putfield 693	com/google/android/gms/internal/measurement/zzgj:zzayh	[Lcom/google/android/gms/internal/measurement/zzgk;
    //   4766: goto +3 -> 4769
    //   4769: aload_0
    //   4770: invokevirtual 431	com/google/android/gms/measurement/internal/zzey:zzjq	()Lcom/google/android/gms/measurement/internal/zzq;
    //   4773: astore 18
    //   4775: aload 16
    //   4777: getfield 478	com/google/android/gms/internal/measurement/zzgd:zzawm	Lcom/google/android/gms/internal/measurement/zzgj;
    //   4780: astore 21
    //   4782: aload 18
    //   4784: invokevirtual 696	com/google/android/gms/measurement/internal/zzez:zzcl	()V
    //   4787: aload 18
    //   4789: invokevirtual 530	com/google/android/gms/measurement/internal/zzco:zzaf	()V
    //   4792: aload_1
    //   4793: invokestatic 410	com/google/android/gms/common/internal/Preconditions:checkNotEmpty	(Ljava/lang/String;)Ljava/lang/String;
    //   4796: pop
    //   4797: aload 21
    //   4799: invokestatic 297	com/google/android/gms/common/internal/Preconditions:checkNotNull	(Ljava/lang/Object;)Ljava/lang/Object;
    //   4802: pop
    //   4803: aload 21
    //   4805: invokevirtual 701	com/google/android/gms/internal/measurement/zzzg:zzvu	()I
    //   4808: newarray byte
    //   4810: astore 16
    //   4812: aload 16
    //   4814: arraylength
    //   4815: istore 5
    //   4817: aload 16
    //   4819: iconst_0
    //   4820: iload 5
    //   4822: invokestatic 707	com/google/android/gms/internal/measurement/zzyy:zzk	([BII)Lcom/google/android/gms/internal/measurement/zzyy;
    //   4825: astore 23
    //   4827: aload 21
    //   4829: aload 23
    //   4831: invokevirtual 710	com/google/android/gms/internal/measurement/zzzg:zza	(Lcom/google/android/gms/internal/measurement/zzyy;)V
    //   4834: aload 23
    //   4836: invokevirtual 713	com/google/android/gms/internal/measurement/zzyy:zzyt	()V
    //   4839: new 715	android/content/ContentValues
    //   4842: dup
    //   4843: invokespecial 716	android/content/ContentValues:<init>	()V
    //   4846: astore 21
    //   4848: aload 21
    //   4850: ldc_w 718
    //   4853: aload_1
    //   4854: invokevirtual 721	android/content/ContentValues:put	(Ljava/lang/String;Ljava/lang/String;)V
    //   4857: aload 21
    //   4859: ldc_w 723
    //   4862: iload 7
    //   4864: invokestatic 364	java/lang/Integer:valueOf	(I)Ljava/lang/Integer;
    //   4867: invokevirtual 726	android/content/ContentValues:put	(Ljava/lang/String;Ljava/lang/Integer;)V
    //   4870: aload 21
    //   4872: ldc_w 728
    //   4875: aload 16
    //   4877: invokevirtual 731	android/content/ContentValues:put	(Ljava/lang/String;[B)V
    //   4880: aload 18
    //   4882: invokevirtual 536	com/google/android/gms/measurement/internal/zzq:getWritableDatabase	()Landroid/database/sqlite/SQLiteDatabase;
    //   4885: astore 16
    //   4887: aload 16
    //   4889: ldc_w 733
    //   4892: aconst_null
    //   4893: aload 21
    //   4895: iconst_5
    //   4896: invokevirtual 737	android/database/sqlite/SQLiteDatabase:insertWithOnConflict	(Ljava/lang/String;Ljava/lang/String;Landroid/content/ContentValues;I)J
    //   4899: ldc2_w 738
    //   4902: lcmp
    //   4903: ifne +81 -> 4984
    //   4906: aload 18
    //   4908: invokevirtual 77	com/google/android/gms/measurement/internal/zzco:zzgo	()Lcom/google/android/gms/measurement/internal/zzap;
    //   4911: invokevirtual 513	com/google/android/gms/measurement/internal/zzap:zzjd	()Lcom/google/android/gms/measurement/internal/zzar;
    //   4914: ldc_w 741
    //   4917: aload_1
    //   4918: invokestatic 574	com/google/android/gms/measurement/internal/zzap:zzbv	(Ljava/lang/String;)Ljava/lang/Object;
    //   4921: invokevirtual 101	com/google/android/gms/measurement/internal/zzar:zzg	(Ljava/lang/String;Ljava/lang/Object;)V
    //   4924: goto +60 -> 4984
    //   4927: astore 16
    //   4929: goto +5 -> 4934
    //   4932: astore 16
    //   4934: aload 18
    //   4936: invokevirtual 77	com/google/android/gms/measurement/internal/zzco:zzgo	()Lcom/google/android/gms/measurement/internal/zzap;
    //   4939: invokevirtual 513	com/google/android/gms/measurement/internal/zzap:zzjd	()Lcom/google/android/gms/measurement/internal/zzar;
    //   4942: ldc_w 743
    //   4945: aload_1
    //   4946: invokestatic 574	com/google/android/gms/measurement/internal/zzap:zzbv	(Ljava/lang/String;)Ljava/lang/Object;
    //   4949: aload 16
    //   4951: invokevirtual 144	com/google/android/gms/measurement/internal/zzar:zze	(Ljava/lang/String;Ljava/lang/Object;Ljava/lang/Object;)V
    //   4954: goto +30 -> 4984
    //   4957: astore 16
    //   4959: goto +5 -> 4964
    //   4962: astore 16
    //   4964: aload 18
    //   4966: invokevirtual 77	com/google/android/gms/measurement/internal/zzco:zzgo	()Lcom/google/android/gms/measurement/internal/zzap;
    //   4969: invokevirtual 513	com/google/android/gms/measurement/internal/zzap:zzjd	()Lcom/google/android/gms/measurement/internal/zzar;
    //   4972: ldc_w 745
    //   4975: aload_1
    //   4976: invokestatic 574	com/google/android/gms/measurement/internal/zzap:zzbv	(Ljava/lang/String;)Ljava/lang/Object;
    //   4979: aload 16
    //   4981: invokevirtual 144	com/google/android/gms/measurement/internal/zzar:zze	(Ljava/lang/String;Ljava/lang/Object;Ljava/lang/Object;)V
    //   4984: iload 4
    //   4986: iconst_1
    //   4987: iadd
    //   4988: istore 4
    //   4990: goto -630 -> 4360
    //   4993: goto -633 -> 4360
    //   4996: aload 20
    //   4998: iload 4
    //   5000: invokestatic 556	java/util/Arrays:copyOf	([Ljava/lang/Object;I)[Ljava/lang/Object;
    //   5003: checkcast 747	[Lcom/google/android/gms/internal/measurement/zzgd;
    //   5006: areturn
    // Exception table:
    //   from	to	target	type
    //   1092	1109	1112	android/database/sqlite/SQLiteException
    //   1085	1092	1121	android/database/sqlite/SQLiteException
    //   4887	4924	4927	android/database/sqlite/SQLiteException
    //   4880	4887	4932	android/database/sqlite/SQLiteException
    //   4817	4839	4957	java/io/IOException
    //   4803	4817	4962	java/io/IOException
  }
  
  protected final boolean zzgt()
  {
    return false;
  }
}
