package com.google.android.gms.measurement.internal;

import android.content.Context;
import android.content.pm.ApplicationInfo;
import android.content.pm.PackageInfo;
import android.content.pm.PackageManager;
import android.content.pm.PackageManager.NameNotFoundException;
import android.database.sqlite.SQLiteDatabase;
import android.database.sqlite.SQLiteException;
import android.net.Uri;
import android.net.Uri.Builder;
import android.os.Build;
import android.os.Build.VERSION;
import android.os.Bundle;
import android.text.TextUtils;
import android.util.Pair;
import androidx.collection.ArrayMap;
import com.google.android.gms.common.internal.Preconditions;
import com.google.android.gms.common.util.Clock;
import com.google.android.gms.common.wrappers.PackageManagerWrapper;
import com.google.android.gms.common.wrappers.Wrappers;
import com.google.android.gms.internal.measurement.zzgd;
import com.google.android.gms.internal.measurement.zzgf;
import com.google.android.gms.internal.measurement.zzgg;
import com.google.android.gms.internal.measurement.zzgh;
import com.google.android.gms.internal.measurement.zzgi;
import com.google.android.gms.internal.measurement.zzgl;
import com.google.android.gms.internal.measurement.zzyy;
import com.google.android.gms.internal.measurement.zzzg;
import java.io.File;
import java.io.FileNotFoundException;
import java.io.IOException;
import java.io.RandomAccessFile;
import java.net.MalformedURLException;
import java.net.URL;
import java.nio.ByteBuffer;
import java.nio.channels.FileChannel;
import java.nio.channels.FileLock;
import java.security.SecureRandom;
import java.util.ArrayList;
import java.util.Arrays;
import java.util.Collection;
import java.util.Collections;
import java.util.Iterator;
import java.util.List;
import java.util.Locale;
import java.util.Map;
import java.util.concurrent.ExecutionException;
import java.util.concurrent.Future;
import java.util.concurrent.TimeUnit;
import java.util.concurrent.TimeoutException;

public class zzfa
  implements zzcq
{
  private static volatile zzfa zzatc;
  private final zzbt zzadj;
  private zzbn zzatd;
  private zzat zzate;
  private zzq zzatf;
  private zzay zzatg;
  private zzew zzath;
  private zzj zzati;
  private final zzfg zzatj;
  private boolean zzatk;
  private long zzatl;
  private List<Runnable> zzatm;
  private int zzatn;
  private int zzato;
  private boolean zzatp;
  private boolean zzatq;
  private boolean zzatr;
  private FileLock zzats;
  private FileChannel zzatt;
  private List<Long> zzatu;
  private List<Long> zzatv;
  private long zzatw;
  private boolean zzvz = false;
  
  private zzfa(zzff paramZzff)
  {
    this(paramZzff, null);
  }
  
  private zzfa(zzff paramZzff, zzbt paramZzbt)
  {
    Preconditions.checkNotNull(paramZzff);
    zzadj = zzbt.zza(zzri, null);
    zzatw = -1L;
    paramZzbt = new zzfg(this);
    paramZzbt.zzq();
    zzatj = paramZzbt;
    paramZzbt = new zzat(this);
    paramZzbt.zzq();
    zzate = paramZzbt;
    paramZzbt = new zzbn(this);
    paramZzbt.zzq();
    zzatd = paramZzbt;
    zzadj.zzgn().zzc(new zzfb(this, paramZzff));
  }
  
  private final int zza(FileChannel paramFileChannel)
  {
    zzaf();
    if ((paramFileChannel != null) && (paramFileChannel.isOpen()))
    {
      ByteBuffer localByteBuffer = ByteBuffer.allocate(4);
      try
      {
        paramFileChannel.position(0L);
        int i = paramFileChannel.read(localByteBuffer);
        if (i != 4)
        {
          if (i == -1) {
            break label114;
          }
          zzadj.zzgo().zzjg().zzg("Unexpected data length. Bytes read", Integer.valueOf(i));
          return 0;
        }
        localByteBuffer.flip();
        i = localByteBuffer.getInt();
        return i;
      }
      catch (IOException paramFileChannel)
      {
        zzadj.zzgo().zzjd().zzg("Failed to read from channel", paramFileChannel);
        return 0;
      }
    }
    zzadj.zzgo().zzjd().zzbx("Bad channel to read from");
    return 0;
    label114:
    return 0;
  }
  
  private final zzh zza(Context paramContext, String paramString1, String paramString2, boolean paramBoolean1, boolean paramBoolean2, boolean paramBoolean3, long paramLong, String paramString3)
  {
    String str2 = "Unknown";
    Object localObject = paramContext.getPackageManager();
    if (localObject == null)
    {
      zzadj.zzgo().zzjd().zzbx("PackageManager is null, can not log app install information");
      return null;
    }
    try
    {
      str1 = ((PackageManager)localObject).getInstallerPackageName(paramString1);
    }
    catch (IllegalArgumentException localIllegalArgumentException)
    {
      String str1;
      String str3;
      for (;;) {}
    }
    zzadj.zzgo().zzjd().zzg("Error retrieving installer package name. appId", zzap.zzbv(paramString1));
    str1 = "Unknown";
    if (str1 == null)
    {
      localObject = "manual_install";
    }
    else
    {
      localObject = str1;
      if ("com.android.vending".equals(str1)) {
        localObject = "";
      }
    }
    str3 = str2;
    try
    {
      PackageInfo localPackageInfo = Wrappers.packageManager(paramContext).getPackageInfo(paramString1, 0);
      int i;
      if (localPackageInfo != null)
      {
        str3 = str2;
        CharSequence localCharSequence = Wrappers.packageManager(paramContext).getApplicationLabel(paramString1);
        str1 = str2;
        str3 = str2;
        if (!TextUtils.isEmpty(localCharSequence))
        {
          str3 = str2;
          str1 = localCharSequence.toString();
        }
        str3 = str1;
        str2 = versionName;
        str3 = str1;
        i = versionCode;
        str1 = str2;
      }
      else
      {
        i = Integer.MIN_VALUE;
        str1 = "Unknown";
      }
      zzadj.zzgr();
      if (!zzadj.zzgq().zzbe(paramString1)) {
        paramLong = 0L;
      }
      return new zzh(paramString1, paramString2, str1, i, (String)localObject, zzadj.zzgq().zzhc(), zzadj.zzgm().zzd(paramContext, paramString1), null, paramBoolean1, false, "", 0L, paramLong, 0, paramBoolean2, paramBoolean3, false, paramString3);
    }
    catch (PackageManager.NameNotFoundException paramContext)
    {
      for (;;) {}
    }
    zzadj.zzgo().zzjd().zze("Error retrieving newly installed package info. appId, appName", zzap.zzbv(paramString1), str3);
    return null;
  }
  
  private static void zza(zzez paramZzez)
  {
    if (paramZzez != null)
    {
      if (paramZzez.isInitialized()) {
        return;
      }
      paramZzez = String.valueOf(paramZzez.getClass());
      StringBuilder localStringBuilder = new StringBuilder(String.valueOf(paramZzez).length() + 27);
      localStringBuilder.append("Component not initialized: ");
      localStringBuilder.append(paramZzez);
      throw new IllegalStateException(localStringBuilder.toString());
    }
    throw new IllegalStateException("Upload Component not created");
  }
  
  private final void zza(zzff paramZzff)
  {
    zzadj.zzgn().zzaf();
    paramZzff = new zzq(this);
    paramZzff.zzq();
    zzatf = paramZzff;
    zzadj.zzgq().zza(zzatd);
    paramZzff = new zzj(this);
    paramZzff.zzq();
    zzati = paramZzff;
    paramZzff = new zzew(this);
    paramZzff.zzq();
    zzath = paramZzff;
    zzatg = new zzay(this);
    if (zzatn != zzato) {
      zzadj.zzgo().zzjd().zze("Not all upload components initialized", Integer.valueOf(zzatn), Integer.valueOf(zzato));
    }
    zzvz = true;
  }
  
  private final boolean zza(int paramInt, FileChannel paramFileChannel)
  {
    zzaf();
    if ((paramFileChannel != null) && (paramFileChannel.isOpen()))
    {
      ByteBuffer localByteBuffer = ByteBuffer.allocate(4);
      localByteBuffer.putInt(paramInt);
      localByteBuffer.flip();
      try
      {
        paramFileChannel.truncate(0L);
        paramFileChannel.write(localByteBuffer);
        paramFileChannel.force(true);
        if (paramFileChannel.size() != 4L) {
          zzadj.zzgo().zzjd().zzg("Error writing to channel. Bytes written", Long.valueOf(paramFileChannel.size()));
        }
        return true;
      }
      catch (IOException paramFileChannel)
      {
        zzadj.zzgo().zzjd().zzg("Failed to write to channel", paramFileChannel);
        return false;
      }
    }
    zzadj.zzgo().zzjd().zzbx("Bad channel to read from");
    return false;
  }
  
  private final boolean zza(String paramString, zzad paramZzad)
  {
    String str = zzaid.getString("currency");
    long l1;
    if ("ecommerce_purchase".equals(name))
    {
      double d2 = zzaid.zzbq("value").doubleValue() * 1000000.0D;
      double d1 = d2;
      if (d2 == 0.0D)
      {
        d1 = zzaid.getLong("value").longValue();
        Double.isNaN(d1);
        d1 *= 1000000.0D;
      }
      if ((d1 <= 9.223372036854776E18D) && (d1 >= -9.223372036854776E18D))
      {
        l1 = Math.round(d1);
      }
      else
      {
        zzadj.zzgo().zzjg().zze("Data lost. Currency value is too big. appId", zzap.zzbv(paramString), Double.valueOf(d1));
        return false;
      }
    }
    else
    {
      l1 = zzaid.getLong("value").longValue();
    }
    if (!TextUtils.isEmpty(str))
    {
      str = str.toUpperCase(Locale.US);
      if (str.matches("[A-Z]{3}"))
      {
        str = String.valueOf(str);
        if (str.length() != 0) {
          str = "_ltv_".concat(str);
        } else {
          str = new String("_ltv_");
        }
        Object localObject = zzjq().zzi(paramString, str);
        if ((localObject != null) && ((value instanceof Long)))
        {
          long l2 = ((Long)value).longValue();
          paramZzad = new zzfj(paramString, origin, str, zzadj.zzbx().currentTimeMillis(), Long.valueOf(l2 + l1));
        }
        else
        {
          localObject = zzjq();
          int i = zzadj.zzgq().zzb(paramString, zzaf.zzakh);
          Preconditions.checkNotEmpty(paramString);
          ((zzco)localObject).zzaf();
          ((zzez)localObject).zzcl();
          try
          {
            ((zzq)localObject).getWritableDatabase().execSQL("delete from user_attributes where app_id=? and name in (select name from user_attributes where app_id=? and name like '_ltv_%' order by set_timestamp desc limit ?,10);", new String[] { paramString, paramString, String.valueOf(i - 1) });
          }
          catch (SQLiteException localSQLiteException)
          {
            ((zzco)localObject).zzgo().zzjd().zze("Error pruning currencies. appId", zzap.zzbv(paramString), localSQLiteException);
          }
          paramZzad = new zzfj(paramString, origin, str, zzadj.zzbx().currentTimeMillis(), Long.valueOf(l1));
        }
        if (!zzjq().zza(paramZzad))
        {
          zzadj.zzgo().zzjd().zzd("Too many unique user properties are set. Ignoring user property. appId", zzap.zzbv(paramString), zzadj.zzgl().zzbu(name), value);
          zzadj.zzgm().zza(paramString, 9, null, null, 0);
        }
      }
    }
    return true;
  }
  
  private final zzgd[] zza(String paramString, zzgl[] paramArrayOfZzgl, zzgf[] paramArrayOfZzgf)
  {
    Preconditions.checkNotEmpty(paramString);
    return zzjp().zza(paramString, paramArrayOfZzgf, paramArrayOfZzgl);
  }
  
  private static zzgg[] zza(zzgg[] paramArrayOfZzgg, int paramInt)
  {
    zzgg[] arrayOfZzgg = new zzgg[paramArrayOfZzgg.length - 1];
    if (paramInt > 0) {
      System.arraycopy(paramArrayOfZzgg, 0, arrayOfZzgg, 0, paramInt);
    }
    if (paramInt < arrayOfZzgg.length) {
      System.arraycopy(paramArrayOfZzgg, paramInt + 1, arrayOfZzgg, paramInt, arrayOfZzgg.length - paramInt);
    }
    return arrayOfZzgg;
  }
  
  private static zzgg[] zza(zzgg[] paramArrayOfZzgg, int paramInt, String paramString)
  {
    int i = 0;
    while (i < paramArrayOfZzgg.length)
    {
      if ("_err".equals(name)) {
        return paramArrayOfZzgg;
      }
      i += 1;
    }
    zzgg[] arrayOfZzgg = new zzgg[paramArrayOfZzgg.length + 2];
    System.arraycopy(paramArrayOfZzgg, 0, arrayOfZzgg, 0, paramArrayOfZzgg.length);
    paramArrayOfZzgg = new zzgg();
    name = "_err";
    zzawx = Long.valueOf(paramInt);
    zzgg localZzgg = new zzgg();
    name = "_ev";
    zzamp = paramString;
    arrayOfZzgg[(arrayOfZzgg.length - 2)] = paramArrayOfZzgg;
    arrayOfZzgg[(arrayOfZzgg.length - 1)] = localZzgg;
    return arrayOfZzgg;
  }
  
  private static zzgg[] zza(zzgg[] paramArrayOfZzgg, String paramString)
  {
    int i = 0;
    while (i < paramArrayOfZzgg.length)
    {
      if (paramString.equals(name)) {
        break label33;
      }
      i += 1;
    }
    i = -1;
    label33:
    if (i < 0) {
      return paramArrayOfZzgg;
    }
    return zza(paramArrayOfZzgg, i);
  }
  
  private final void zzaf()
  {
    zzadj.zzgn().zzaf();
  }
  
  private final void zzb(zzg paramZzg)
  {
    zzaf();
    if ((TextUtils.isEmpty(paramZzg.getGmpAppId())) && ((!zzn.zzic()) || (TextUtils.isEmpty(paramZzg.zzgw()))))
    {
      zzb(paramZzg.zzal(), 204, null, null, null);
      return;
    }
    Object localObject4 = zzadj.zzgq();
    Object localObject5 = new Uri.Builder();
    Object localObject3 = paramZzg.getGmpAppId();
    Object localObject1 = localObject3;
    if (TextUtils.isEmpty((CharSequence)localObject3))
    {
      localObject1 = localObject3;
      if (zzn.zzic()) {
        localObject1 = paramZzg.zzgw();
      }
    }
    localObject3 = ((Uri.Builder)localObject5).scheme((String)zzaf.zzajh.get()).encodedAuthority((String)zzaf.zzaji.get());
    localObject1 = String.valueOf(localObject1);
    if (((String)localObject1).length() != 0) {
      localObject1 = "config/app/".concat((String)localObject1);
    } else {
      localObject1 = new String("config/app/");
    }
    ((Uri.Builder)localObject3).path((String)localObject1).appendQueryParameter("app_instance_id", paramZzg.getAppInstanceId()).appendQueryParameter("platform", "android").appendQueryParameter("gmp_version", String.valueOf(((zzn)localObject4).zzhc()));
    localObject3 = ((Uri.Builder)localObject5).build().toString();
    try
    {
      localObject4 = new URL((String)localObject3);
      zzadj.zzgo().zzjl().zzg("Fetching remote configuration", paramZzg.zzal());
      localObject1 = zzln().zzcf(paramZzg.zzal());
      localObject5 = zzln().zzcg(paramZzg.zzal());
      if ((localObject1 == null) || (TextUtils.isEmpty((CharSequence)localObject5))) {
        break label393;
      }
      localObject1 = new ArrayMap();
      ((Map)localObject1).put("If-Modified-Since", localObject5);
    }
    catch (MalformedURLException localMalformedURLException)
    {
      for (;;)
      {
        String str;
        zzfd localZzfd;
        continue;
        Object localObject2 = null;
      }
    }
    zzatp = true;
    localObject5 = zzlo();
    str = paramZzg.zzal();
    localZzfd = new zzfd(this);
    ((zzco)localObject5).zzaf();
    ((zzez)localObject5).zzcl();
    Preconditions.checkNotNull(localObject4);
    Preconditions.checkNotNull(localZzfd);
    ((zzco)localObject5).zzgn().zzd(new zzax((zzat)localObject5, str, (URL)localObject4, null, (Map)localObject1, localZzfd));
    return;
    zzadj.zzgo().zzjd().zze("Failed to parse config URL. Not fetching. appId", zzap.zzbv(paramZzg.zzal()), localObject3);
  }
  
  private final Boolean zzc(zzg paramZzg)
  {
    try
    {
      if (paramZzg.zzha() != -2147483648L)
      {
        int i = packageManagerzzadj.getContext()).getPackageInfo(paramZzg.zzal(), 0).versionCode;
        if (paramZzg.zzha() == i) {
          return Boolean.valueOf(true);
        }
      }
      else
      {
        String str = packageManagerzzadj.getContext()).getPackageInfo(paramZzg.zzal(), 0).versionName;
        if ((paramZzg.zzak() != null) && (paramZzg.zzak().equals(str))) {
          return Boolean.valueOf(true);
        }
      }
      return Boolean.valueOf(false);
    }
    catch (PackageManager.NameNotFoundException paramZzg)
    {
      for (;;) {}
    }
    return null;
  }
  
  private final zzh zzco(String paramString)
  {
    zzg localZzg = zzjq().zzbl(paramString);
    if ((localZzg != null) && (!TextUtils.isEmpty(localZzg.zzak())))
    {
      Boolean localBoolean = zzc(localZzg);
      if ((localBoolean != null) && (!localBoolean.booleanValue()))
      {
        zzadj.zzgo().zzjd().zzg("App version does not match; dropping. appId", zzap.zzbv(paramString));
        return null;
      }
      return new zzh(paramString, localZzg.getGmpAppId(), localZzg.zzak(), localZzg.zzha(), localZzg.zzhb(), localZzg.zzhc(), localZzg.zzhd(), null, localZzg.isMeasurementEnabled(), false, localZzg.getFirebaseInstanceId(), localZzg.zzhq(), 0L, 0, localZzg.zzhr(), localZzg.zzhs(), false, localZzg.zzgw());
    }
    zzadj.zzgo().zzjk().zzg("No app data available; dropping", paramString);
    return null;
  }
  
  private final void zzd(zzad paramZzad, zzh paramZzh)
  {
    throw new Runtime("d2j fail translate: java.lang.RuntimeException: fail exe a24 = a19\n\tat com.googlecode.dex2jar.ir.ts.an.BaseAnalyze.exec(BaseAnalyze.java:92)\n\tat com.googlecode.dex2jar.ir.ts.an.BaseAnalyze.exec(BaseAnalyze.java:1)\n\tat com.googlecode.dex2jar.ir.ts.Cfg.dfs(Cfg.java:255)\n\tat com.googlecode.dex2jar.ir.ts.an.BaseAnalyze.analyze0(BaseAnalyze.java:75)\n\tat com.googlecode.dex2jar.ir.ts.an.BaseAnalyze.analyze(BaseAnalyze.java:69)\n\tat com.googlecode.dex2jar.ir.ts.UnSSATransformer.transform(UnSSATransformer.java:274)\n\tat com.googlecode.d2j.dex.Dex2jar$2.optimize(Dex2jar.java:163)\n\tat com.googlecode.d2j.dex.Dex2Asm.convertCode(Dex2Asm.java:414)\n\tat com.googlecode.d2j.dex.ExDex2Asm.convertCode(ExDex2Asm.java:42)\n\tat com.googlecode.d2j.dex.Dex2jar$2.convertCode(Dex2jar.java:128)\n\tat com.googlecode.d2j.dex.Dex2Asm.convertMethod(Dex2Asm.java:509)\n\tat com.googlecode.d2j.dex.Dex2Asm.convertClass(Dex2Asm.java:406)\n\tat com.googlecode.d2j.dex.Dex2Asm.convertDex(Dex2Asm.java:422)\n\tat com.googlecode.d2j.dex.Dex2jar.doTranslate(Dex2jar.java:172)\n\tat com.googlecode.d2j.dex.Dex2jar.to(Dex2jar.java:272)\n\tat com.googlecode.dex2jar.tools.Dex2jarCmd.doCommandLine(Dex2jarCmd.java:108)\n\tat com.googlecode.dex2jar.tools.BaseCmd.doMain(BaseCmd.java:288)\n\tat com.googlecode.dex2jar.tools.Dex2jarCmd.main(Dex2jarCmd.java:32)\nCaused by: java.lang.NullPointerException\n\tat com.googlecode.dex2jar.ir.ts.UnSSATransformer$LiveA.onUseLocal(UnSSATransformer.java:552)\n\tat com.googlecode.dex2jar.ir.ts.UnSSATransformer$LiveA.onUseLocal(UnSSATransformer.java:1)\n\tat com.googlecode.dex2jar.ir.ts.an.BaseAnalyze.onUse(BaseAnalyze.java:166)\n\tat com.googlecode.dex2jar.ir.ts.an.BaseAnalyze.onUse(BaseAnalyze.java:1)\n\tat com.googlecode.dex2jar.ir.ts.Cfg.travel(Cfg.java:331)\n\tat com.googlecode.dex2jar.ir.ts.Cfg.travel(Cfg.java:387)\n\tat com.googlecode.dex2jar.ir.ts.an.BaseAnalyze.exec(BaseAnalyze.java:90)\n\t... 17 more\n");
  }
  
  /* Error */
  private final boolean zzd(String paramString, long paramLong)
  {
    // Byte code:
    //   0: aload_0
    //   1: astore 23
    //   3: ldc_w 791
    //   6: astore 24
    //   8: aload_0
    //   9: invokevirtual 489	com/google/android/gms/measurement/internal/zzfa:zzjq	()Lcom/google/android/gms/measurement/internal/zzq;
    //   12: invokevirtual 794	com/google/android/gms/measurement/internal/zzq:beginTransaction	()V
    //   15: aconst_null
    //   16: astore 18
    //   18: new 8	com/google/android/gms/measurement/internal/zzfa$zza
    //   21: dup
    //   22: aload 23
    //   24: aconst_null
    //   25: invokespecial 797	com/google/android/gms/measurement/internal/zzfa$zza:<init>	(Lcom/google/android/gms/measurement/internal/zzfa;Lcom/google/android/gms/measurement/internal/zzfb;)V
    //   28: astore 19
    //   30: aload_0
    //   31: invokevirtual 489	com/google/android/gms/measurement/internal/zzfa:zzjq	()Lcom/google/android/gms/measurement/internal/zzq;
    //   34: astore 26
    //   36: aload 23
    //   38: getfield 83	com/google/android/gms/measurement/internal/zzfa:zzatw	J
    //   41: lstore 11
    //   43: aload 19
    //   45: invokestatic 66	com/google/android/gms/common/internal/Preconditions:checkNotNull	(Ljava/lang/Object;)Ljava/lang/Object;
    //   48: pop
    //   49: aload 26
    //   51: invokevirtual 346	com/google/android/gms/measurement/internal/zzco:zzaf	()V
    //   54: aload 26
    //   56: invokevirtual 528	com/google/android/gms/measurement/internal/zzez:zzcl	()V
    //   59: aload 26
    //   61: invokevirtual 532	com/google/android/gms/measurement/internal/zzq:getWritableDatabase	()Landroid/database/sqlite/SQLiteDatabase;
    //   64: astore 27
    //   66: aconst_null
    //   67: invokestatic 254	android/text/TextUtils:isEmpty	(Ljava/lang/CharSequence;)Z
    //   70: istore 13
    //   72: ldc -24
    //   74: astore 17
    //   76: iload 13
    //   78: ifeq +253 -> 331
    //   81: lload 11
    //   83: ldc2_w 80
    //   86: lcmp
    //   87: ifeq +67 -> 154
    //   90: aload 18
    //   92: astore_1
    //   93: iconst_2
    //   94: anewarray 226	java/lang/String
    //   97: astore 20
    //   99: aload 18
    //   101: astore_1
    //   102: aload 20
    //   104: iconst_0
    //   105: lload 11
    //   107: invokestatic 666	java/lang/String:valueOf	(J)Ljava/lang/String;
    //   110: aastore
    //   111: aload 18
    //   113: astore_1
    //   114: aload 20
    //   116: iconst_1
    //   117: lload_2
    //   118: invokestatic 666	java/lang/String:valueOf	(J)Ljava/lang/String;
    //   121: aastore
    //   122: aload 20
    //   124: astore_1
    //   125: goto +41 -> 166
    //   128: astore 18
    //   130: aload_1
    //   131: astore 17
    //   133: aload 18
    //   135: astore_1
    //   136: goto +5072 -> 5208
    //   139: astore_1
    //   140: aconst_null
    //   141: astore 17
    //   143: aload 17
    //   145: astore 18
    //   147: aload 17
    //   149: astore 20
    //   151: goto +1045 -> 1196
    //   154: iconst_1
    //   155: anewarray 226	java/lang/String
    //   158: astore_1
    //   159: aload_1
    //   160: iconst_0
    //   161: lload_2
    //   162: invokestatic 666	java/lang/String:valueOf	(J)Ljava/lang/String;
    //   165: aastore
    //   166: lload 11
    //   168: ldc2_w 80
    //   171: lcmp
    //   172: ifeq +8 -> 180
    //   175: ldc_w 799
    //   178: astore 17
    //   180: new 322	java/lang/StringBuilder
    //   183: dup
    //   184: aload 17
    //   186: invokevirtual 325	java/lang/String:length	()I
    //   189: sipush 148
    //   192: iadd
    //   193: invokespecial 328	java/lang/StringBuilder:<init>	(I)V
    //   196: astore 18
    //   198: aload 18
    //   200: ldc_w 801
    //   203: invokevirtual 334	java/lang/StringBuilder:append	(Ljava/lang/String;)Ljava/lang/StringBuilder;
    //   206: pop
    //   207: aload 18
    //   209: aload 17
    //   211: invokevirtual 334	java/lang/StringBuilder:append	(Ljava/lang/String;)Ljava/lang/StringBuilder;
    //   214: pop
    //   215: aload 18
    //   217: ldc_w 803
    //   220: invokevirtual 334	java/lang/StringBuilder:append	(Ljava/lang/String;)Ljava/lang/StringBuilder;
    //   223: pop
    //   224: aload 27
    //   226: aload 18
    //   228: invokevirtual 337	java/lang/StringBuilder:toString	()Ljava/lang/String;
    //   231: aload_1
    //   232: invokevirtual 807	android/database/sqlite/SQLiteDatabase:rawQuery	(Ljava/lang/String;[Ljava/lang/String;)Landroid/database/Cursor;
    //   235: astore 17
    //   237: aload 17
    //   239: astore_1
    //   240: aload 17
    //   242: astore 18
    //   244: aload 17
    //   246: invokeinterface 812 1 0
    //   251: istore 13
    //   253: iload 13
    //   255: ifne +18 -> 273
    //   258: aload 17
    //   260: ifnull +972 -> 1232
    //   263: aload 17
    //   265: invokeinterface 815 1 0
    //   270: goto +962 -> 1232
    //   273: aload 17
    //   275: astore_1
    //   276: aload 17
    //   278: astore 18
    //   280: aload 17
    //   282: iconst_0
    //   283: invokeinterface 817 2 0
    //   288: astore 20
    //   290: aload 17
    //   292: astore_1
    //   293: aload 17
    //   295: iconst_1
    //   296: invokeinterface 817 2 0
    //   301: astore 21
    //   303: aload 17
    //   305: astore_1
    //   306: aload 17
    //   308: invokeinterface 815 1 0
    //   313: aload 20
    //   315: astore_1
    //   316: goto +181 -> 497
    //   319: astore_1
    //   320: aload 17
    //   322: astore 18
    //   324: aload 20
    //   326: astore 17
    //   328: goto -181 -> 147
    //   331: lload 11
    //   333: ldc2_w 80
    //   336: lcmp
    //   337: ifeq +23 -> 360
    //   340: iconst_2
    //   341: anewarray 226	java/lang/String
    //   344: astore_1
    //   345: aload_1
    //   346: iconst_0
    //   347: aconst_null
    //   348: aastore
    //   349: aload_1
    //   350: iconst_1
    //   351: lload 11
    //   353: invokestatic 666	java/lang/String:valueOf	(J)Ljava/lang/String;
    //   356: aastore
    //   357: goto +4888 -> 5245
    //   360: iconst_1
    //   361: anewarray 226	java/lang/String
    //   364: astore_1
    //   365: aload_1
    //   366: iconst_0
    //   367: aconst_null
    //   368: aastore
    //   369: goto +4876 -> 5245
    //   372: new 322	java/lang/StringBuilder
    //   375: dup
    //   376: aload 17
    //   378: invokevirtual 325	java/lang/String:length	()I
    //   381: bipush 84
    //   383: iadd
    //   384: invokespecial 328	java/lang/StringBuilder:<init>	(I)V
    //   387: astore 18
    //   389: aload 18
    //   391: ldc_w 819
    //   394: invokevirtual 334	java/lang/StringBuilder:append	(Ljava/lang/String;)Ljava/lang/StringBuilder;
    //   397: pop
    //   398: aload 18
    //   400: aload 17
    //   402: invokevirtual 334	java/lang/StringBuilder:append	(Ljava/lang/String;)Ljava/lang/StringBuilder;
    //   405: pop
    //   406: aload 18
    //   408: ldc_w 821
    //   411: invokevirtual 334	java/lang/StringBuilder:append	(Ljava/lang/String;)Ljava/lang/StringBuilder;
    //   414: pop
    //   415: aload 27
    //   417: aload 18
    //   419: invokevirtual 337	java/lang/StringBuilder:toString	()Ljava/lang/String;
    //   422: aload_1
    //   423: invokevirtual 807	android/database/sqlite/SQLiteDatabase:rawQuery	(Ljava/lang/String;[Ljava/lang/String;)Landroid/database/Cursor;
    //   426: astore 17
    //   428: aload 17
    //   430: astore_1
    //   431: aload 17
    //   433: astore 18
    //   435: aload 17
    //   437: invokeinterface 812 1 0
    //   442: istore 13
    //   444: iload 13
    //   446: ifne +18 -> 464
    //   449: aload 17
    //   451: ifnull +781 -> 1232
    //   454: aload 17
    //   456: invokeinterface 815 1 0
    //   461: goto +771 -> 1232
    //   464: aload 17
    //   466: astore_1
    //   467: aload 17
    //   469: astore 18
    //   471: aload 17
    //   473: iconst_0
    //   474: invokeinterface 817 2 0
    //   479: astore 21
    //   481: aload 17
    //   483: astore_1
    //   484: aload 17
    //   486: astore 18
    //   488: aload 17
    //   490: invokeinterface 815 1 0
    //   495: aconst_null
    //   496: astore_1
    //   497: aload 17
    //   499: astore 18
    //   501: aload 27
    //   503: ldc_w 823
    //   506: iconst_1
    //   507: anewarray 226	java/lang/String
    //   510: dup
    //   511: iconst_0
    //   512: ldc_w 825
    //   515: aastore
    //   516: ldc_w 827
    //   519: iconst_2
    //   520: anewarray 226	java/lang/String
    //   523: dup
    //   524: iconst_0
    //   525: aload_1
    //   526: aastore
    //   527: dup
    //   528: iconst_1
    //   529: aload 21
    //   531: aastore
    //   532: aconst_null
    //   533: aconst_null
    //   534: ldc_w 829
    //   537: ldc_w 831
    //   540: invokevirtual 835	android/database/sqlite/SQLiteDatabase:query	(Ljava/lang/String;[Ljava/lang/String;Ljava/lang/String;[Ljava/lang/String;Ljava/lang/String;Ljava/lang/String;Ljava/lang/String;Ljava/lang/String;)Landroid/database/Cursor;
    //   543: astore 20
    //   545: aload 20
    //   547: astore 18
    //   549: aload 20
    //   551: astore 17
    //   553: aload 20
    //   555: invokeinterface 812 1 0
    //   560: ifne +44 -> 604
    //   563: aload 20
    //   565: astore 18
    //   567: aload 20
    //   569: astore 17
    //   571: aload 26
    //   573: invokevirtual 544	com/google/android/gms/measurement/internal/zzco:zzgo	()Lcom/google/android/gms/measurement/internal/zzap;
    //   576: invokevirtual 181	com/google/android/gms/measurement/internal/zzap:zzjd	()Lcom/google/android/gms/measurement/internal/zzar;
    //   579: ldc_w 837
    //   582: aload_1
    //   583: invokestatic 220	com/google/android/gms/measurement/internal/zzap:zzbv	(Ljava/lang/String;)Ljava/lang/Object;
    //   586: invokevirtual 170	com/google/android/gms/measurement/internal/zzar:zzg	(Ljava/lang/String;Ljava/lang/Object;)V
    //   589: aload 20
    //   591: ifnull +641 -> 1232
    //   594: aload 20
    //   596: invokeinterface 815 1 0
    //   601: goto +631 -> 1232
    //   604: aload 20
    //   606: astore 18
    //   608: aload 20
    //   610: astore 17
    //   612: aload 20
    //   614: iconst_0
    //   615: invokeinterface 841 2 0
    //   620: astore 22
    //   622: aload 20
    //   624: astore 18
    //   626: aload 20
    //   628: astore 17
    //   630: aload 22
    //   632: iconst_0
    //   633: aload 22
    //   635: arraylength
    //   636: invokestatic 847	com/google/android/gms/internal/measurement/zzyx:zzj	([BII)Lcom/google/android/gms/internal/measurement/zzyx;
    //   639: astore 22
    //   641: aload 20
    //   643: astore 18
    //   645: aload 20
    //   647: astore 17
    //   649: new 849	com/google/android/gms/internal/measurement/zzgi
    //   652: dup
    //   653: invokespecial 850	com/google/android/gms/internal/measurement/zzgi:<init>	()V
    //   656: astore 25
    //   658: aload 20
    //   660: astore 18
    //   662: aload 20
    //   664: astore 17
    //   666: aload 25
    //   668: aload 22
    //   670: invokevirtual 855	com/google/android/gms/internal/measurement/zzzg:zza	(Lcom/google/android/gms/internal/measurement/zzyx;)Lcom/google/android/gms/internal/measurement/zzzg;
    //   673: pop
    //   674: aload 20
    //   676: astore 18
    //   678: aload 20
    //   680: astore 17
    //   682: aload 20
    //   684: invokeinterface 858 1 0
    //   689: ifeq +29 -> 718
    //   692: aload 20
    //   694: astore 18
    //   696: aload 20
    //   698: astore 17
    //   700: aload 26
    //   702: invokevirtual 544	com/google/android/gms/measurement/internal/zzco:zzgo	()Lcom/google/android/gms/measurement/internal/zzap;
    //   705: invokevirtual 156	com/google/android/gms/measurement/internal/zzap:zzjg	()Lcom/google/android/gms/measurement/internal/zzar;
    //   708: ldc_w 860
    //   711: aload_1
    //   712: invokestatic 220	com/google/android/gms/measurement/internal/zzap:zzbv	(Ljava/lang/String;)Ljava/lang/Object;
    //   715: invokevirtual 170	com/google/android/gms/measurement/internal/zzar:zzg	(Ljava/lang/String;Ljava/lang/Object;)V
    //   718: aload 20
    //   720: astore 18
    //   722: aload 20
    //   724: astore 17
    //   726: aload 20
    //   728: invokeinterface 815 1 0
    //   733: aload 20
    //   735: astore 18
    //   737: aload 20
    //   739: astore 17
    //   741: aload 19
    //   743: aload 25
    //   745: invokeinterface 865 2 0
    //   750: lload 11
    //   752: ldc2_w 80
    //   755: lcmp
    //   756: ifeq +50 -> 806
    //   759: ldc_w 867
    //   762: astore 22
    //   764: aload 20
    //   766: astore 18
    //   768: aload 20
    //   770: astore 17
    //   772: iconst_3
    //   773: anewarray 226	java/lang/String
    //   776: dup
    //   777: iconst_0
    //   778: aload_1
    //   779: aastore
    //   780: dup
    //   781: iconst_1
    //   782: aload 21
    //   784: aastore
    //   785: dup
    //   786: iconst_2
    //   787: lload 11
    //   789: invokestatic 666	java/lang/String:valueOf	(J)Ljava/lang/String;
    //   792: aastore
    //   793: astore 25
    //   795: aload 22
    //   797: astore 21
    //   799: aload 25
    //   801: astore 22
    //   803: goto +35 -> 838
    //   806: ldc_w 827
    //   809: astore 25
    //   811: aload 20
    //   813: astore 18
    //   815: aload 20
    //   817: astore 17
    //   819: iconst_2
    //   820: anewarray 226	java/lang/String
    //   823: dup
    //   824: iconst_0
    //   825: aload_1
    //   826: aastore
    //   827: dup
    //   828: iconst_1
    //   829: aload 21
    //   831: aastore
    //   832: astore 22
    //   834: aload 25
    //   836: astore 21
    //   838: aload 20
    //   840: astore 18
    //   842: aload 20
    //   844: astore 17
    //   846: aload 27
    //   848: ldc_w 869
    //   851: iconst_4
    //   852: anewarray 226	java/lang/String
    //   855: dup
    //   856: iconst_0
    //   857: ldc_w 829
    //   860: aastore
    //   861: dup
    //   862: iconst_1
    //   863: ldc_w 870
    //   866: aastore
    //   867: dup
    //   868: iconst_2
    //   869: ldc_w 872
    //   872: aastore
    //   873: dup
    //   874: iconst_3
    //   875: ldc_w 874
    //   878: aastore
    //   879: aload 21
    //   881: aload 22
    //   883: aconst_null
    //   884: aconst_null
    //   885: ldc_w 829
    //   888: aconst_null
    //   889: invokevirtual 835	android/database/sqlite/SQLiteDatabase:query	(Ljava/lang/String;[Ljava/lang/String;Ljava/lang/String;[Ljava/lang/String;Ljava/lang/String;Ljava/lang/String;Ljava/lang/String;Ljava/lang/String;)Landroid/database/Cursor;
    //   892: astore 20
    //   894: aload 20
    //   896: invokeinterface 812 1 0
    //   901: ifne +36 -> 937
    //   904: aload 26
    //   906: invokevirtual 544	com/google/android/gms/measurement/internal/zzco:zzgo	()Lcom/google/android/gms/measurement/internal/zzap;
    //   909: invokevirtual 156	com/google/android/gms/measurement/internal/zzap:zzjg	()Lcom/google/android/gms/measurement/internal/zzar;
    //   912: ldc_w 876
    //   915: aload_1
    //   916: invokestatic 220	com/google/android/gms/measurement/internal/zzap:zzbv	(Ljava/lang/String;)Ljava/lang/Object;
    //   919: invokevirtual 170	com/google/android/gms/measurement/internal/zzar:zzg	(Ljava/lang/String;Ljava/lang/Object;)V
    //   922: aload 20
    //   924: ifnull +308 -> 1232
    //   927: aload 20
    //   929: invokeinterface 815 1 0
    //   934: goto +298 -> 1232
    //   937: aload 20
    //   939: iconst_0
    //   940: invokeinterface 879 2 0
    //   945: lstore_2
    //   946: aload 20
    //   948: iconst_3
    //   949: invokeinterface 841 2 0
    //   954: astore 17
    //   956: aload 17
    //   958: iconst_0
    //   959: aload 17
    //   961: arraylength
    //   962: invokestatic 847	com/google/android/gms/internal/measurement/zzyx:zzj	([BII)Lcom/google/android/gms/internal/measurement/zzyx;
    //   965: astore 17
    //   967: new 881	com/google/android/gms/internal/measurement/zzgf
    //   970: dup
    //   971: invokespecial 882	com/google/android/gms/internal/measurement/zzgf:<init>	()V
    //   974: astore 18
    //   976: aload 18
    //   978: aload 17
    //   980: invokevirtual 855	com/google/android/gms/internal/measurement/zzzg:zza	(Lcom/google/android/gms/internal/measurement/zzyx;)Lcom/google/android/gms/internal/measurement/zzzg;
    //   983: pop
    //   984: aload 18
    //   986: aload 20
    //   988: iconst_1
    //   989: invokeinterface 817 2 0
    //   994: putfield 883	com/google/android/gms/internal/measurement/zzgf:name	Ljava/lang/String;
    //   997: aload 18
    //   999: aload 20
    //   1001: iconst_2
    //   1002: invokeinterface 879 2 0
    //   1007: invokestatic 401	java/lang/Long:valueOf	(J)Ljava/lang/Long;
    //   1010: putfield 886	com/google/android/gms/internal/measurement/zzgf:zzawu	Ljava/lang/Long;
    //   1013: aload 19
    //   1015: lload_2
    //   1016: aload 18
    //   1018: invokeinterface 889 4 0
    //   1023: istore 13
    //   1025: iload 13
    //   1027: ifne +40 -> 1067
    //   1030: aload 20
    //   1032: ifnull +200 -> 1232
    //   1035: aload 20
    //   1037: invokeinterface 815 1 0
    //   1042: goto +190 -> 1232
    //   1045: astore 17
    //   1047: aload 26
    //   1049: invokevirtual 544	com/google/android/gms/measurement/internal/zzco:zzgo	()Lcom/google/android/gms/measurement/internal/zzap;
    //   1052: invokevirtual 181	com/google/android/gms/measurement/internal/zzap:zzjd	()Lcom/google/android/gms/measurement/internal/zzar;
    //   1055: ldc_w 891
    //   1058: aload_1
    //   1059: invokestatic 220	com/google/android/gms/measurement/internal/zzap:zzbv	(Ljava/lang/String;)Ljava/lang/Object;
    //   1062: aload 17
    //   1064: invokevirtual 309	com/google/android/gms/measurement/internal/zzar:zze	(Ljava/lang/String;Ljava/lang/Object;Ljava/lang/Object;)V
    //   1067: aload 20
    //   1069: invokeinterface 858 1 0
    //   1074: istore 13
    //   1076: iload 13
    //   1078: ifne -141 -> 937
    //   1081: aload 20
    //   1083: ifnull +149 -> 1232
    //   1086: aload 20
    //   1088: invokeinterface 815 1 0
    //   1093: goto +139 -> 1232
    //   1096: astore_1
    //   1097: aload 20
    //   1099: astore 17
    //   1101: goto +85 -> 1186
    //   1104: astore 21
    //   1106: aload_1
    //   1107: astore 17
    //   1109: aload 20
    //   1111: astore 18
    //   1113: aload 21
    //   1115: astore_1
    //   1116: goto -969 -> 147
    //   1119: astore 21
    //   1121: aload 20
    //   1123: astore 18
    //   1125: aload 20
    //   1127: astore 17
    //   1129: aload 26
    //   1131: invokevirtual 544	com/google/android/gms/measurement/internal/zzco:zzgo	()Lcom/google/android/gms/measurement/internal/zzap;
    //   1134: invokevirtual 181	com/google/android/gms/measurement/internal/zzap:zzjd	()Lcom/google/android/gms/measurement/internal/zzar;
    //   1137: ldc_w 893
    //   1140: aload_1
    //   1141: invokestatic 220	com/google/android/gms/measurement/internal/zzap:zzbv	(Ljava/lang/String;)Ljava/lang/Object;
    //   1144: aload 21
    //   1146: invokevirtual 309	com/google/android/gms/measurement/internal/zzar:zze	(Ljava/lang/String;Ljava/lang/Object;Ljava/lang/Object;)V
    //   1149: aload 20
    //   1151: ifnull +81 -> 1232
    //   1154: aload 20
    //   1156: invokeinterface 815 1 0
    //   1161: goto +71 -> 1232
    //   1164: astore 20
    //   1166: aload_1
    //   1167: astore 17
    //   1169: aload 20
    //   1171: astore_1
    //   1172: goto -1025 -> 147
    //   1175: astore_1
    //   1176: aconst_null
    //   1177: astore 17
    //   1179: goto -1032 -> 147
    //   1182: astore_1
    //   1183: aconst_null
    //   1184: astore 17
    //   1186: goto +4025 -> 5211
    //   1189: astore_1
    //   1190: aconst_null
    //   1191: astore 20
    //   1193: aconst_null
    //   1194: astore 18
    //   1196: aload 18
    //   1198: astore 17
    //   1200: aload 26
    //   1202: invokevirtual 544	com/google/android/gms/measurement/internal/zzco:zzgo	()Lcom/google/android/gms/measurement/internal/zzap;
    //   1205: invokevirtual 181	com/google/android/gms/measurement/internal/zzap:zzjd	()Lcom/google/android/gms/measurement/internal/zzar;
    //   1208: ldc_w 895
    //   1211: aload 20
    //   1213: invokestatic 220	com/google/android/gms/measurement/internal/zzap:zzbv	(Ljava/lang/String;)Ljava/lang/Object;
    //   1216: aload_1
    //   1217: invokevirtual 309	com/google/android/gms/measurement/internal/zzar:zze	(Ljava/lang/String;Ljava/lang/Object;Ljava/lang/Object;)V
    //   1220: aload 18
    //   1222: ifnull +10 -> 1232
    //   1225: aload 18
    //   1227: invokeinterface 815 1 0
    //   1232: aload 19
    //   1234: getfield 898	com/google/android/gms/measurement/internal/zzfa$zza:zzauc	Ljava/util/List;
    //   1237: ifnull +4031 -> 5268
    //   1240: aload 19
    //   1242: getfield 898	com/google/android/gms/measurement/internal/zzfa$zza:zzauc	Ljava/util/List;
    //   1245: invokeinterface 902 1 0
    //   1250: ifeq +4012 -> 5262
    //   1253: goto +4015 -> 5268
    //   1256: iload 4
    //   1258: ifne +3933 -> 5191
    //   1261: aload 19
    //   1263: getfield 906	com/google/android/gms/measurement/internal/zzfa$zza:zzaua	Lcom/google/android/gms/internal/measurement/zzgi;
    //   1266: astore 18
    //   1268: aload 18
    //   1270: aload 19
    //   1272: getfield 898	com/google/android/gms/measurement/internal/zzfa$zza:zzauc	Ljava/util/List;
    //   1275: invokeinterface 908 1 0
    //   1280: anewarray 881	com/google/android/gms/internal/measurement/zzgf
    //   1283: putfield 912	com/google/android/gms/internal/measurement/zzgi:zzaxb	[Lcom/google/android/gms/internal/measurement/zzgf;
    //   1286: aload 23
    //   1288: getfield 79	com/google/android/gms/measurement/internal/zzfa:zzadj	Lcom/google/android/gms/measurement/internal/zzbt;
    //   1291: invokevirtual 278	com/google/android/gms/measurement/internal/zzbt:zzgq	()Lcom/google/android/gms/measurement/internal/zzn;
    //   1294: aload 18
    //   1296: getfield 915	com/google/android/gms/internal/measurement/zzgi:zztt	Ljava/lang/String;
    //   1299: invokevirtual 918	com/google/android/gms/measurement/internal/zzn:zzax	(Ljava/lang/String;)Z
    //   1302: istore 15
    //   1304: iconst_0
    //   1305: istore 6
    //   1307: iconst_0
    //   1308: istore 5
    //   1310: iconst_0
    //   1311: istore 13
    //   1313: lconst_0
    //   1314: lstore_2
    //   1315: aload 24
    //   1317: astore 17
    //   1319: iload 6
    //   1321: aload 19
    //   1323: getfield 898	com/google/android/gms/measurement/internal/zzfa$zza:zzauc	Ljava/util/List;
    //   1326: invokeinterface 908 1 0
    //   1331: if_icmpge +1547 -> 2878
    //   1334: aload 19
    //   1336: getfield 898	com/google/android/gms/measurement/internal/zzfa$zza:zzauc	Ljava/util/List;
    //   1339: iload 6
    //   1341: invokeinterface 921 2 0
    //   1346: checkcast 881	com/google/android/gms/internal/measurement/zzgf
    //   1349: astore 24
    //   1351: aload_0
    //   1352: invokespecial 685	com/google/android/gms/measurement/internal/zzfa:zzln	()Lcom/google/android/gms/measurement/internal/zzbn;
    //   1355: aload 19
    //   1357: getfield 906	com/google/android/gms/measurement/internal/zzfa$zza:zzaua	Lcom/google/android/gms/internal/measurement/zzgi;
    //   1360: getfield 915	com/google/android/gms/internal/measurement/zzgi:zztt	Ljava/lang/String;
    //   1363: aload 24
    //   1365: getfield 883	com/google/android/gms/internal/measurement/zzgf:name	Ljava/lang/String;
    //   1368: invokevirtual 925	com/google/android/gms/measurement/internal/zzbn:zzo	(Ljava/lang/String;Ljava/lang/String;)Z
    //   1371: istore 14
    //   1373: iload 14
    //   1375: ifeq +138 -> 1513
    //   1378: aload 23
    //   1380: getfield 79	com/google/android/gms/measurement/internal/zzfa:zzadj	Lcom/google/android/gms/measurement/internal/zzbt;
    //   1383: invokevirtual 150	com/google/android/gms/measurement/internal/zzbt:zzgo	()Lcom/google/android/gms/measurement/internal/zzap;
    //   1386: invokevirtual 156	com/google/android/gms/measurement/internal/zzap:zzjg	()Lcom/google/android/gms/measurement/internal/zzar;
    //   1389: ldc_w 927
    //   1392: aload 19
    //   1394: getfield 906	com/google/android/gms/measurement/internal/zzfa$zza:zzaua	Lcom/google/android/gms/internal/measurement/zzgi;
    //   1397: getfield 915	com/google/android/gms/internal/measurement/zzgi:zztt	Ljava/lang/String;
    //   1400: invokestatic 220	com/google/android/gms/measurement/internal/zzap:zzbv	(Ljava/lang/String;)Ljava/lang/Object;
    //   1403: aload 23
    //   1405: getfield 79	com/google/android/gms/measurement/internal/zzfa:zzadj	Lcom/google/android/gms/measurement/internal/zzbt;
    //   1408: invokevirtual 555	com/google/android/gms/measurement/internal/zzbt:zzgl	()Lcom/google/android/gms/measurement/internal/zzan;
    //   1411: aload 24
    //   1413: getfield 883	com/google/android/gms/internal/measurement/zzgf:name	Ljava/lang/String;
    //   1416: invokevirtual 930	com/google/android/gms/measurement/internal/zzan:zzbs	(Ljava/lang/String;)Ljava/lang/String;
    //   1419: invokevirtual 309	com/google/android/gms/measurement/internal/zzar:zze	(Ljava/lang/String;Ljava/lang/Object;Ljava/lang/Object;)V
    //   1422: aload_0
    //   1423: invokespecial 685	com/google/android/gms/measurement/internal/zzfa:zzln	()Lcom/google/android/gms/measurement/internal/zzbn;
    //   1426: aload 19
    //   1428: getfield 906	com/google/android/gms/measurement/internal/zzfa$zza:zzaua	Lcom/google/android/gms/internal/measurement/zzgi;
    //   1431: getfield 915	com/google/android/gms/internal/measurement/zzgi:zztt	Ljava/lang/String;
    //   1434: invokevirtual 933	com/google/android/gms/measurement/internal/zzbn:zzck	(Ljava/lang/String;)Z
    //   1437: ifne +3843 -> 5280
    //   1440: aload_0
    //   1441: invokespecial 685	com/google/android/gms/measurement/internal/zzfa:zzln	()Lcom/google/android/gms/measurement/internal/zzbn;
    //   1444: aload 19
    //   1446: getfield 906	com/google/android/gms/measurement/internal/zzfa$zza:zzaua	Lcom/google/android/gms/internal/measurement/zzgi;
    //   1449: getfield 915	com/google/android/gms/internal/measurement/zzgi:zztt	Ljava/lang/String;
    //   1452: invokevirtual 935	com/google/android/gms/measurement/internal/zzbn:zzcl	(Ljava/lang/String;)Z
    //   1455: ifeq +3819 -> 5274
    //   1458: goto +3822 -> 5280
    //   1461: iload 4
    //   1463: ifne +3823 -> 5286
    //   1466: ldc_w 587
    //   1469: aload 24
    //   1471: getfield 883	com/google/android/gms/internal/measurement/zzgf:name	Ljava/lang/String;
    //   1474: invokevirtual 230	java/lang/String:equals	(Ljava/lang/Object;)Z
    //   1477: ifne +3809 -> 5286
    //   1480: aload 23
    //   1482: getfield 79	com/google/android/gms/measurement/internal/zzfa:zzadj	Lcom/google/android/gms/measurement/internal/zzbt;
    //   1485: invokevirtual 294	com/google/android/gms/measurement/internal/zzbt:zzgm	()Lcom/google/android/gms/measurement/internal/zzfk;
    //   1488: aload 19
    //   1490: getfield 906	com/google/android/gms/measurement/internal/zzfa$zza:zzaua	Lcom/google/android/gms/internal/measurement/zzgi;
    //   1493: getfield 915	com/google/android/gms/internal/measurement/zzgi:zztt	Ljava/lang/String;
    //   1496: bipush 11
    //   1498: ldc_w 595
    //   1501: aload 24
    //   1503: getfield 883	com/google/android/gms/internal/measurement/zzgf:name	Ljava/lang/String;
    //   1506: iconst_0
    //   1507: invokevirtual 567	com/google/android/gms/measurement/internal/zzfk:zza	(Ljava/lang/String;ILjava/lang/String;Ljava/lang/String;I)V
    //   1510: goto +3776 -> 5286
    //   1513: aload_0
    //   1514: invokespecial 685	com/google/android/gms/measurement/internal/zzfa:zzln	()Lcom/google/android/gms/measurement/internal/zzbn;
    //   1517: aload 19
    //   1519: getfield 906	com/google/android/gms/measurement/internal/zzfa$zza:zzaua	Lcom/google/android/gms/internal/measurement/zzgi;
    //   1522: getfield 915	com/google/android/gms/internal/measurement/zzgi:zztt	Ljava/lang/String;
    //   1525: aload 24
    //   1527: getfield 883	com/google/android/gms/internal/measurement/zzgf:name	Ljava/lang/String;
    //   1530: invokevirtual 938	com/google/android/gms/measurement/internal/zzbn:zzp	(Ljava/lang/String;Ljava/lang/String;)Z
    //   1533: istore 16
    //   1535: iload 16
    //   1537: ifne +100 -> 1637
    //   1540: aload_0
    //   1541: invokevirtual 942	com/google/android/gms/measurement/internal/zzfa:zzjo	()Lcom/google/android/gms/measurement/internal/zzfg;
    //   1544: pop
    //   1545: aload 24
    //   1547: getfield 883	com/google/android/gms/internal/measurement/zzgf:name	Ljava/lang/String;
    //   1550: astore_1
    //   1551: aload_1
    //   1552: invokestatic 525	com/google/android/gms/common/internal/Preconditions:checkNotEmpty	(Ljava/lang/String;)Ljava/lang/String;
    //   1555: pop
    //   1556: aload_1
    //   1557: invokevirtual 945	java/lang/String:hashCode	()I
    //   1560: istore 4
    //   1562: iload 4
    //   1564: ldc_w 946
    //   1567: if_icmpeq +54 -> 1621
    //   1570: iload 4
    //   1572: ldc_w 947
    //   1575: if_icmpeq +30 -> 1605
    //   1578: iload 4
    //   1580: ldc_w 948
    //   1583: if_icmpeq +6 -> 1589
    //   1586: goto +3703 -> 5289
    //   1589: aload_1
    //   1590: ldc_w 950
    //   1593: invokevirtual 230	java/lang/String:equals	(Ljava/lang/Object;)Z
    //   1596: ifeq +3693 -> 5289
    //   1599: iconst_1
    //   1600: istore 4
    //   1602: goto +3690 -> 5292
    //   1605: aload_1
    //   1606: ldc_w 952
    //   1609: invokevirtual 230	java/lang/String:equals	(Ljava/lang/Object;)Z
    //   1612: ifeq +3677 -> 5289
    //   1615: iconst_2
    //   1616: istore 4
    //   1618: goto +3674 -> 5292
    //   1621: aload_1
    //   1622: ldc_w 954
    //   1625: invokevirtual 230	java/lang/String:equals	(Ljava/lang/Object;)Z
    //   1628: ifeq +3661 -> 5289
    //   1631: iconst_0
    //   1632: istore 4
    //   1634: goto +3658 -> 5292
    //   1637: aload 24
    //   1639: getfield 958	com/google/android/gms/internal/measurement/zzgf:zzawt	[Lcom/google/android/gms/internal/measurement/zzgg;
    //   1642: ifnonnull +12 -> 1654
    //   1645: aload 24
    //   1647: iconst_0
    //   1648: anewarray 578	com/google/android/gms/internal/measurement/zzgg
    //   1651: putfield 958	com/google/android/gms/internal/measurement/zzgf:zzawt	[Lcom/google/android/gms/internal/measurement/zzgg;
    //   1654: aload 24
    //   1656: getfield 958	com/google/android/gms/internal/measurement/zzgf:zzawt	[Lcom/google/android/gms/internal/measurement/zzgg;
    //   1659: astore_1
    //   1660: aload_1
    //   1661: arraylength
    //   1662: istore 4
    //   1664: iconst_0
    //   1665: istore 7
    //   1667: iconst_0
    //   1668: istore 8
    //   1670: iconst_0
    //   1671: istore 9
    //   1673: iload 7
    //   1675: iload 4
    //   1677: if_icmpge +75 -> 1752
    //   1680: aload_1
    //   1681: iload 7
    //   1683: aaload
    //   1684: astore 20
    //   1686: ldc_w 960
    //   1689: aload 20
    //   1691: getfield 588	com/google/android/gms/internal/measurement/zzgg:name	Ljava/lang/String;
    //   1694: invokevirtual 230	java/lang/String:equals	(Ljava/lang/Object;)Z
    //   1697: ifeq +18 -> 1715
    //   1700: aload 20
    //   1702: lconst_1
    //   1703: invokestatic 401	java/lang/Long:valueOf	(J)Ljava/lang/Long;
    //   1706: putfield 593	com/google/android/gms/internal/measurement/zzgg:zzawx	Ljava/lang/Long;
    //   1709: iconst_1
    //   1710: istore 10
    //   1712: goto +3621 -> 5333
    //   1715: iload 8
    //   1717: istore 10
    //   1719: ldc_w 962
    //   1722: aload 20
    //   1724: getfield 588	com/google/android/gms/internal/measurement/zzgg:name	Ljava/lang/String;
    //   1727: invokevirtual 230	java/lang/String:equals	(Ljava/lang/Object;)Z
    //   1730: ifeq +3603 -> 5333
    //   1733: aload 20
    //   1735: lconst_1
    //   1736: invokestatic 401	java/lang/Long:valueOf	(J)Ljava/lang/Long;
    //   1739: putfield 593	com/google/android/gms/internal/measurement/zzgg:zzawx	Ljava/lang/Long;
    //   1742: iconst_1
    //   1743: istore 9
    //   1745: iload 8
    //   1747: istore 10
    //   1749: goto +3584 -> 5333
    //   1752: iload 8
    //   1754: ifne +3592 -> 5346
    //   1757: iload 16
    //   1759: ifeq +3587 -> 5346
    //   1762: aload 23
    //   1764: getfield 79	com/google/android/gms/measurement/internal/zzfa:zzadj	Lcom/google/android/gms/measurement/internal/zzbt;
    //   1767: invokevirtual 150	com/google/android/gms/measurement/internal/zzbt:zzgo	()Lcom/google/android/gms/measurement/internal/zzap;
    //   1770: invokevirtual 679	com/google/android/gms/measurement/internal/zzap:zzjl	()Lcom/google/android/gms/measurement/internal/zzar;
    //   1773: ldc_w 964
    //   1776: aload 23
    //   1778: getfield 79	com/google/android/gms/measurement/internal/zzfa:zzadj	Lcom/google/android/gms/measurement/internal/zzbt;
    //   1781: invokevirtual 555	com/google/android/gms/measurement/internal/zzbt:zzgl	()Lcom/google/android/gms/measurement/internal/zzan;
    //   1784: aload 24
    //   1786: getfield 883	com/google/android/gms/internal/measurement/zzgf:name	Ljava/lang/String;
    //   1789: invokevirtual 930	com/google/android/gms/measurement/internal/zzan:zzbs	(Ljava/lang/String;)Ljava/lang/String;
    //   1792: invokevirtual 170	com/google/android/gms/measurement/internal/zzar:zzg	(Ljava/lang/String;Ljava/lang/Object;)V
    //   1795: aload 24
    //   1797: getfield 958	com/google/android/gms/internal/measurement/zzgf:zzawt	[Lcom/google/android/gms/internal/measurement/zzgg;
    //   1800: aload 24
    //   1802: getfield 958	com/google/android/gms/internal/measurement/zzgf:zzawt	[Lcom/google/android/gms/internal/measurement/zzgg;
    //   1805: arraylength
    //   1806: iconst_1
    //   1807: iadd
    //   1808: invokestatic 970	java/util/Arrays:copyOf	([Ljava/lang/Object;I)[Ljava/lang/Object;
    //   1811: checkcast 971	[Lcom/google/android/gms/internal/measurement/zzgg;
    //   1814: astore_1
    //   1815: new 578	com/google/android/gms/internal/measurement/zzgg
    //   1818: dup
    //   1819: invokespecial 589	com/google/android/gms/internal/measurement/zzgg:<init>	()V
    //   1822: astore 20
    //   1824: aload 20
    //   1826: ldc_w 960
    //   1829: putfield 588	com/google/android/gms/internal/measurement/zzgg:name	Ljava/lang/String;
    //   1832: aload 20
    //   1834: lconst_1
    //   1835: invokestatic 401	java/lang/Long:valueOf	(J)Ljava/lang/Long;
    //   1838: putfield 593	com/google/android/gms/internal/measurement/zzgg:zzawx	Ljava/lang/Long;
    //   1841: aload_1
    //   1842: aload_1
    //   1843: arraylength
    //   1844: iconst_1
    //   1845: isub
    //   1846: aload 20
    //   1848: aastore
    //   1849: aload 24
    //   1851: aload_1
    //   1852: putfield 958	com/google/android/gms/internal/measurement/zzgf:zzawt	[Lcom/google/android/gms/internal/measurement/zzgg;
    //   1855: goto +3 -> 1858
    //   1858: iload 9
    //   1860: ifne +96 -> 1956
    //   1863: aload 23
    //   1865: getfield 79	com/google/android/gms/measurement/internal/zzfa:zzadj	Lcom/google/android/gms/measurement/internal/zzbt;
    //   1868: invokevirtual 150	com/google/android/gms/measurement/internal/zzbt:zzgo	()Lcom/google/android/gms/measurement/internal/zzap;
    //   1871: invokevirtual 679	com/google/android/gms/measurement/internal/zzap:zzjl	()Lcom/google/android/gms/measurement/internal/zzar;
    //   1874: ldc_w 973
    //   1877: aload 23
    //   1879: getfield 79	com/google/android/gms/measurement/internal/zzfa:zzadj	Lcom/google/android/gms/measurement/internal/zzbt;
    //   1882: invokevirtual 555	com/google/android/gms/measurement/internal/zzbt:zzgl	()Lcom/google/android/gms/measurement/internal/zzan;
    //   1885: aload 24
    //   1887: getfield 883	com/google/android/gms/internal/measurement/zzgf:name	Ljava/lang/String;
    //   1890: invokevirtual 930	com/google/android/gms/measurement/internal/zzan:zzbs	(Ljava/lang/String;)Ljava/lang/String;
    //   1893: invokevirtual 170	com/google/android/gms/measurement/internal/zzar:zzg	(Ljava/lang/String;Ljava/lang/Object;)V
    //   1896: aload 24
    //   1898: getfield 958	com/google/android/gms/internal/measurement/zzgf:zzawt	[Lcom/google/android/gms/internal/measurement/zzgg;
    //   1901: aload 24
    //   1903: getfield 958	com/google/android/gms/internal/measurement/zzgf:zzawt	[Lcom/google/android/gms/internal/measurement/zzgg;
    //   1906: arraylength
    //   1907: iconst_1
    //   1908: iadd
    //   1909: invokestatic 970	java/util/Arrays:copyOf	([Ljava/lang/Object;I)[Ljava/lang/Object;
    //   1912: checkcast 971	[Lcom/google/android/gms/internal/measurement/zzgg;
    //   1915: astore_1
    //   1916: new 578	com/google/android/gms/internal/measurement/zzgg
    //   1919: dup
    //   1920: invokespecial 589	com/google/android/gms/internal/measurement/zzgg:<init>	()V
    //   1923: astore 20
    //   1925: aload 20
    //   1927: ldc_w 962
    //   1930: putfield 588	com/google/android/gms/internal/measurement/zzgg:name	Ljava/lang/String;
    //   1933: aload 20
    //   1935: lconst_1
    //   1936: invokestatic 401	java/lang/Long:valueOf	(J)Ljava/lang/Long;
    //   1939: putfield 593	com/google/android/gms/internal/measurement/zzgg:zzawx	Ljava/lang/Long;
    //   1942: aload_1
    //   1943: aload_1
    //   1944: arraylength
    //   1945: iconst_1
    //   1946: isub
    //   1947: aload 20
    //   1949: aastore
    //   1950: aload 24
    //   1952: aload_1
    //   1953: putfield 958	com/google/android/gms/internal/measurement/zzgf:zzawt	[Lcom/google/android/gms/internal/measurement/zzgg;
    //   1956: aload_0
    //   1957: invokevirtual 489	com/google/android/gms/measurement/internal/zzfa:zzjq	()Lcom/google/android/gms/measurement/internal/zzq;
    //   1960: aload_0
    //   1961: invokespecial 976	com/google/android/gms/measurement/internal/zzfa:zzls	()J
    //   1964: aload 19
    //   1966: getfield 906	com/google/android/gms/measurement/internal/zzfa$zza:zzaua	Lcom/google/android/gms/internal/measurement/zzgi;
    //   1969: getfield 915	com/google/android/gms/internal/measurement/zzgi:zztt	Ljava/lang/String;
    //   1972: iconst_0
    //   1973: iconst_0
    //   1974: iconst_0
    //   1975: iconst_0
    //   1976: iconst_1
    //   1977: invokevirtual 979	com/google/android/gms/measurement/internal/zzq:zza	(JLjava/lang/String;ZZZZZ)Lcom/google/android/gms/measurement/internal/zzr;
    //   1980: getfield 984	com/google/android/gms/measurement/internal/zzr:zzahu	J
    //   1983: aload 23
    //   1985: getfield 79	com/google/android/gms/measurement/internal/zzfa:zzadj	Lcom/google/android/gms/measurement/internal/zzbt;
    //   1988: invokevirtual 278	com/google/android/gms/measurement/internal/zzbt:zzgq	()Lcom/google/android/gms/measurement/internal/zzn;
    //   1991: aload 19
    //   1993: getfield 906	com/google/android/gms/measurement/internal/zzfa$zza:zzaua	Lcom/google/android/gms/internal/measurement/zzgi;
    //   1996: getfield 915	com/google/android/gms/internal/measurement/zzgi:zztt	Ljava/lang/String;
    //   1999: invokevirtual 988	com/google/android/gms/measurement/internal/zzn:zzat	(Ljava/lang/String;)I
    //   2002: i2l
    //   2003: lcmp
    //   2004: ifle +3357 -> 5361
    //   2007: iconst_0
    //   2008: istore 4
    //   2010: iload 4
    //   2012: aload 24
    //   2014: getfield 958	com/google/android/gms/internal/measurement/zzgf:zzawt	[Lcom/google/android/gms/internal/measurement/zzgg;
    //   2017: arraylength
    //   2018: if_icmpge +3340 -> 5358
    //   2021: ldc_w 962
    //   2024: aload 24
    //   2026: getfield 958	com/google/android/gms/internal/measurement/zzgf:zzawt	[Lcom/google/android/gms/internal/measurement/zzgg;
    //   2029: iload 4
    //   2031: aaload
    //   2032: getfield 588	com/google/android/gms/internal/measurement/zzgg:name	Ljava/lang/String;
    //   2035: invokevirtual 230	java/lang/String:equals	(Ljava/lang/Object;)Z
    //   2038: ifeq +3311 -> 5349
    //   2041: aload 24
    //   2043: getfield 958	com/google/android/gms/internal/measurement/zzgf:zzawt	[Lcom/google/android/gms/internal/measurement/zzgg;
    //   2046: arraylength
    //   2047: iconst_1
    //   2048: isub
    //   2049: anewarray 578	com/google/android/gms/internal/measurement/zzgg
    //   2052: astore_1
    //   2053: iload 4
    //   2055: ifle +16 -> 2071
    //   2058: aload 24
    //   2060: getfield 958	com/google/android/gms/internal/measurement/zzgf:zzawt	[Lcom/google/android/gms/internal/measurement/zzgg;
    //   2063: iconst_0
    //   2064: aload_1
    //   2065: iconst_0
    //   2066: iload 4
    //   2068: invokestatic 584	java/lang/System:arraycopy	(Ljava/lang/Object;ILjava/lang/Object;II)V
    //   2071: iload 4
    //   2073: aload_1
    //   2074: arraylength
    //   2075: if_icmpge +23 -> 2098
    //   2078: aload 24
    //   2080: getfield 958	com/google/android/gms/internal/measurement/zzgf:zzawt	[Lcom/google/android/gms/internal/measurement/zzgg;
    //   2083: iload 4
    //   2085: iconst_1
    //   2086: iadd
    //   2087: aload_1
    //   2088: iload 4
    //   2090: aload_1
    //   2091: arraylength
    //   2092: iload 4
    //   2094: isub
    //   2095: invokestatic 584	java/lang/System:arraycopy	(Ljava/lang/Object;ILjava/lang/Object;II)V
    //   2098: aload 24
    //   2100: aload_1
    //   2101: putfield 958	com/google/android/gms/internal/measurement/zzgf:zzawt	[Lcom/google/android/gms/internal/measurement/zzgg;
    //   2104: goto +3254 -> 5358
    //   2107: iload 13
    //   2109: istore 14
    //   2111: aload 24
    //   2113: getfield 883	com/google/android/gms/internal/measurement/zzgf:name	Ljava/lang/String;
    //   2116: invokestatic 991	com/google/android/gms/measurement/internal/zzfk:zzcq	(Ljava/lang/String;)Z
    //   2119: ifeq +284 -> 2403
    //   2122: iload 13
    //   2124: istore 14
    //   2126: iload 16
    //   2128: ifeq +275 -> 2403
    //   2131: iload 13
    //   2133: istore 14
    //   2135: aload_0
    //   2136: invokevirtual 489	com/google/android/gms/measurement/internal/zzfa:zzjq	()Lcom/google/android/gms/measurement/internal/zzq;
    //   2139: aload_0
    //   2140: invokespecial 976	com/google/android/gms/measurement/internal/zzfa:zzls	()J
    //   2143: aload 19
    //   2145: getfield 906	com/google/android/gms/measurement/internal/zzfa$zza:zzaua	Lcom/google/android/gms/internal/measurement/zzgi;
    //   2148: getfield 915	com/google/android/gms/internal/measurement/zzgi:zztt	Ljava/lang/String;
    //   2151: iconst_0
    //   2152: iconst_0
    //   2153: iconst_1
    //   2154: iconst_0
    //   2155: iconst_0
    //   2156: invokevirtual 979	com/google/android/gms/measurement/internal/zzq:zza	(JLjava/lang/String;ZZZZZ)Lcom/google/android/gms/measurement/internal/zzr;
    //   2159: getfield 994	com/google/android/gms/measurement/internal/zzr:zzahs	J
    //   2162: aload 23
    //   2164: getfield 79	com/google/android/gms/measurement/internal/zzfa:zzadj	Lcom/google/android/gms/measurement/internal/zzbt;
    //   2167: invokevirtual 278	com/google/android/gms/measurement/internal/zzbt:zzgq	()Lcom/google/android/gms/measurement/internal/zzn;
    //   2170: aload 19
    //   2172: getfield 906	com/google/android/gms/measurement/internal/zzfa$zza:zzaua	Lcom/google/android/gms/internal/measurement/zzgi;
    //   2175: getfield 915	com/google/android/gms/internal/measurement/zzgi:zztt	Ljava/lang/String;
    //   2178: getstatic 997	com/google/android/gms/measurement/internal/zzaf:zzajq	Lcom/google/android/gms/measurement/internal/zzaf$zza;
    //   2181: invokevirtual 522	com/google/android/gms/measurement/internal/zzn:zzb	(Ljava/lang/String;Lcom/google/android/gms/measurement/internal/zzaf$zza;)I
    //   2184: i2l
    //   2185: lcmp
    //   2186: ifle +217 -> 2403
    //   2189: aload 23
    //   2191: getfield 79	com/google/android/gms/measurement/internal/zzfa:zzadj	Lcom/google/android/gms/measurement/internal/zzbt;
    //   2194: invokevirtual 150	com/google/android/gms/measurement/internal/zzbt:zzgo	()Lcom/google/android/gms/measurement/internal/zzap;
    //   2197: invokevirtual 156	com/google/android/gms/measurement/internal/zzap:zzjg	()Lcom/google/android/gms/measurement/internal/zzar;
    //   2200: ldc_w 999
    //   2203: aload 19
    //   2205: getfield 906	com/google/android/gms/measurement/internal/zzfa$zza:zzaua	Lcom/google/android/gms/internal/measurement/zzgi;
    //   2208: getfield 915	com/google/android/gms/internal/measurement/zzgi:zztt	Ljava/lang/String;
    //   2211: invokestatic 220	com/google/android/gms/measurement/internal/zzap:zzbv	(Ljava/lang/String;)Ljava/lang/Object;
    //   2214: invokevirtual 170	com/google/android/gms/measurement/internal/zzar:zzg	(Ljava/lang/String;Ljava/lang/Object;)V
    //   2217: aload 24
    //   2219: getfield 958	com/google/android/gms/internal/measurement/zzgf:zzawt	[Lcom/google/android/gms/internal/measurement/zzgg;
    //   2222: astore_1
    //   2223: aload_1
    //   2224: arraylength
    //   2225: istore 8
    //   2227: iconst_0
    //   2228: istore 4
    //   2230: iconst_0
    //   2231: istore 7
    //   2233: aconst_null
    //   2234: astore 20
    //   2236: iload 4
    //   2238: iload 8
    //   2240: if_icmpge +58 -> 2298
    //   2243: aload_1
    //   2244: iload 4
    //   2246: aaload
    //   2247: astore 22
    //   2249: ldc_w 960
    //   2252: aload 22
    //   2254: getfield 588	com/google/android/gms/internal/measurement/zzgg:name	Ljava/lang/String;
    //   2257: invokevirtual 230	java/lang/String:equals	(Ljava/lang/Object;)Z
    //   2260: ifeq +10 -> 2270
    //   2263: aload 22
    //   2265: astore 21
    //   2267: goto +3100 -> 5367
    //   2270: aload 20
    //   2272: astore 21
    //   2274: ldc_w 587
    //   2277: aload 22
    //   2279: getfield 588	com/google/android/gms/internal/measurement/zzgg:name	Ljava/lang/String;
    //   2282: invokevirtual 230	java/lang/String:equals	(Ljava/lang/Object;)Z
    //   2285: ifeq +3082 -> 5367
    //   2288: iconst_1
    //   2289: istore 7
    //   2291: aload 20
    //   2293: astore 21
    //   2295: goto +3072 -> 5367
    //   2298: iload 7
    //   2300: ifeq +40 -> 2340
    //   2303: aload 20
    //   2305: ifnull +35 -> 2340
    //   2308: aload 24
    //   2310: aload 24
    //   2312: getfield 958	com/google/android/gms/internal/measurement/zzgf:zzawt	[Lcom/google/android/gms/internal/measurement/zzgg;
    //   2315: iconst_1
    //   2316: anewarray 578	com/google/android/gms/internal/measurement/zzgg
    //   2319: dup
    //   2320: iconst_0
    //   2321: aload 20
    //   2323: aastore
    //   2324: invokestatic 1005	com/google/android/gms/common/util/ArrayUtils:removeAll	([Ljava/lang/Object;[Ljava/lang/Object;)[Ljava/lang/Object;
    //   2327: checkcast 971	[Lcom/google/android/gms/internal/measurement/zzgg;
    //   2330: putfield 958	com/google/android/gms/internal/measurement/zzgf:zzawt	[Lcom/google/android/gms/internal/measurement/zzgg;
    //   2333: iload 13
    //   2335: istore 14
    //   2337: goto +66 -> 2403
    //   2340: aload 20
    //   2342: ifnull +29 -> 2371
    //   2345: aload 20
    //   2347: ldc_w 587
    //   2350: putfield 588	com/google/android/gms/internal/measurement/zzgg:name	Ljava/lang/String;
    //   2353: aload 20
    //   2355: ldc2_w 1006
    //   2358: invokestatic 401	java/lang/Long:valueOf	(J)Ljava/lang/Long;
    //   2361: putfield 593	com/google/android/gms/internal/measurement/zzgg:zzawx	Ljava/lang/Long;
    //   2364: iload 13
    //   2366: istore 14
    //   2368: goto +35 -> 2403
    //   2371: aload 23
    //   2373: getfield 79	com/google/android/gms/measurement/internal/zzfa:zzadj	Lcom/google/android/gms/measurement/internal/zzbt;
    //   2376: invokevirtual 150	com/google/android/gms/measurement/internal/zzbt:zzgo	()Lcom/google/android/gms/measurement/internal/zzap;
    //   2379: invokevirtual 181	com/google/android/gms/measurement/internal/zzap:zzjd	()Lcom/google/android/gms/measurement/internal/zzar;
    //   2382: ldc_w 1009
    //   2385: aload 19
    //   2387: getfield 906	com/google/android/gms/measurement/internal/zzfa$zza:zzaua	Lcom/google/android/gms/internal/measurement/zzgi;
    //   2390: getfield 915	com/google/android/gms/internal/measurement/zzgi:zztt	Ljava/lang/String;
    //   2393: invokestatic 220	com/google/android/gms/measurement/internal/zzap:zzbv	(Ljava/lang/String;)Ljava/lang/Object;
    //   2396: invokevirtual 170	com/google/android/gms/measurement/internal/zzar:zzg	(Ljava/lang/String;Ljava/lang/Object;)V
    //   2399: iload 13
    //   2401: istore 14
    //   2403: lload_2
    //   2404: lstore 11
    //   2406: iload 5
    //   2408: istore 9
    //   2410: aload 23
    //   2412: getfield 79	com/google/android/gms/measurement/internal/zzfa:zzadj	Lcom/google/android/gms/measurement/internal/zzbt;
    //   2415: invokevirtual 278	com/google/android/gms/measurement/internal/zzbt:zzgq	()Lcom/google/android/gms/measurement/internal/zzn;
    //   2418: aload 19
    //   2420: getfield 906	com/google/android/gms/measurement/internal/zzfa$zza:zzaua	Lcom/google/android/gms/internal/measurement/zzgi;
    //   2423: getfield 915	com/google/android/gms/internal/measurement/zzgi:zztt	Ljava/lang/String;
    //   2426: invokevirtual 1012	com/google/android/gms/measurement/internal/zzn:zzbf	(Ljava/lang/String;)Z
    //   2429: ifeq +2997 -> 5426
    //   2432: iload 16
    //   2434: ifeq +2992 -> 5426
    //   2437: aload 24
    //   2439: getfield 958	com/google/android/gms/internal/measurement/zzgf:zzawt	[Lcom/google/android/gms/internal/measurement/zzgg;
    //   2442: astore 20
    //   2444: iconst_0
    //   2445: istore 4
    //   2447: iconst_m1
    //   2448: istore 5
    //   2450: iconst_m1
    //   2451: istore 7
    //   2453: iload 4
    //   2455: aload 20
    //   2457: arraylength
    //   2458: if_icmpge +59 -> 2517
    //   2461: ldc_w 426
    //   2464: aload 20
    //   2466: iload 4
    //   2468: aaload
    //   2469: getfield 588	com/google/android/gms/internal/measurement/zzgg:name	Ljava/lang/String;
    //   2472: invokevirtual 230	java/lang/String:equals	(Ljava/lang/Object;)Z
    //   2475: ifeq +10 -> 2485
    //   2478: iload 4
    //   2480: istore 8
    //   2482: goto +2898 -> 5380
    //   2485: iload 5
    //   2487: istore 8
    //   2489: ldc_w 414
    //   2492: aload 20
    //   2494: iload 4
    //   2496: aaload
    //   2497: getfield 588	com/google/android/gms/internal/measurement/zzgg:name	Ljava/lang/String;
    //   2500: invokevirtual 230	java/lang/String:equals	(Ljava/lang/Object;)Z
    //   2503: ifeq +2877 -> 5380
    //   2506: iload 4
    //   2508: istore 7
    //   2510: iload 5
    //   2512: istore 8
    //   2514: goto +2866 -> 5380
    //   2517: aload 20
    //   2519: astore_1
    //   2520: iload 5
    //   2522: iconst_m1
    //   2523: if_icmpeq +2870 -> 5393
    //   2526: aload 20
    //   2528: iload 5
    //   2530: aaload
    //   2531: getfield 593	com/google/android/gms/internal/measurement/zzgg:zzawx	Ljava/lang/Long;
    //   2534: ifnonnull +2862 -> 5396
    //   2537: aload 20
    //   2539: iload 5
    //   2541: aaload
    //   2542: getfield 1016	com/google/android/gms/internal/measurement/zzgg:zzauh	Ljava/lang/Double;
    //   2545: ifnonnull +2851 -> 5396
    //   2548: aload 23
    //   2550: getfield 79	com/google/android/gms/measurement/internal/zzfa:zzadj	Lcom/google/android/gms/measurement/internal/zzbt;
    //   2553: invokevirtual 150	com/google/android/gms/measurement/internal/zzbt:zzgo	()Lcom/google/android/gms/measurement/internal/zzap;
    //   2556: invokevirtual 1019	com/google/android/gms/measurement/internal/zzap:zzji	()Lcom/google/android/gms/measurement/internal/zzar;
    //   2559: ldc_w 1021
    //   2562: invokevirtual 189	com/google/android/gms/measurement/internal/zzar:zzbx	(Ljava/lang/String;)V
    //   2565: aload 20
    //   2567: iload 5
    //   2569: invokestatic 601	com/google/android/gms/measurement/internal/zzfa:zza	([Lcom/google/android/gms/internal/measurement/zzgg;I)[Lcom/google/android/gms/internal/measurement/zzgg;
    //   2572: ldc_w 960
    //   2575: invokestatic 1023	com/google/android/gms/measurement/internal/zzfa:zza	([Lcom/google/android/gms/internal/measurement/zzgg;Ljava/lang/String;)[Lcom/google/android/gms/internal/measurement/zzgg;
    //   2578: bipush 18
    //   2580: ldc_w 426
    //   2583: invokestatic 1025	com/google/android/gms/measurement/internal/zzfa:zza	([Lcom/google/android/gms/internal/measurement/zzgg;ILjava/lang/String;)[Lcom/google/android/gms/internal/measurement/zzgg;
    //   2586: astore_1
    //   2587: goto +2806 -> 5393
    //   2590: aload 20
    //   2592: iload 7
    //   2594: aaload
    //   2595: getfield 598	com/google/android/gms/internal/measurement/zzgg:zzamp	Ljava/lang/String;
    //   2598: astore_1
    //   2599: aload_1
    //   2600: ifnull +2820 -> 5420
    //   2603: aload_1
    //   2604: invokevirtual 325	java/lang/String:length	()I
    //   2607: iconst_3
    //   2608: if_icmpeq +2800 -> 5408
    //   2611: goto +2809 -> 5420
    //   2614: iload 4
    //   2616: aload_1
    //   2617: invokevirtual 325	java/lang/String:length	()I
    //   2620: if_icmpge +2794 -> 5414
    //   2623: aload_1
    //   2624: iload 4
    //   2626: invokevirtual 1029	java/lang/String:codePointAt	(I)I
    //   2629: istore 7
    //   2631: iload 7
    //   2633: invokestatic 1035	java/lang/Character:isLetter	(I)Z
    //   2636: ifne +6 -> 2642
    //   2639: goto +2781 -> 5420
    //   2642: iload 4
    //   2644: iload 7
    //   2646: invokestatic 1038	java/lang/Character:charCount	(I)I
    //   2649: iadd
    //   2650: istore 4
    //   2652: goto -38 -> 2614
    //   2655: aload 20
    //   2657: astore_1
    //   2658: iload 4
    //   2660: ifeq +42 -> 2702
    //   2663: aload 23
    //   2665: getfield 79	com/google/android/gms/measurement/internal/zzfa:zzadj	Lcom/google/android/gms/measurement/internal/zzbt;
    //   2668: invokevirtual 150	com/google/android/gms/measurement/internal/zzbt:zzgo	()Lcom/google/android/gms/measurement/internal/zzap;
    //   2671: invokevirtual 1019	com/google/android/gms/measurement/internal/zzap:zzji	()Lcom/google/android/gms/measurement/internal/zzar;
    //   2674: ldc_w 1040
    //   2677: invokevirtual 189	com/google/android/gms/measurement/internal/zzar:zzbx	(Ljava/lang/String;)V
    //   2680: aload 20
    //   2682: iload 5
    //   2684: invokestatic 601	com/google/android/gms/measurement/internal/zzfa:zza	([Lcom/google/android/gms/internal/measurement/zzgg;I)[Lcom/google/android/gms/internal/measurement/zzgg;
    //   2687: ldc_w 960
    //   2690: invokestatic 1023	com/google/android/gms/measurement/internal/zzfa:zza	([Lcom/google/android/gms/internal/measurement/zzgg;Ljava/lang/String;)[Lcom/google/android/gms/internal/measurement/zzgg;
    //   2693: bipush 19
    //   2695: ldc_w 414
    //   2698: invokestatic 1025	com/google/android/gms/measurement/internal/zzfa:zza	([Lcom/google/android/gms/internal/measurement/zzgg;ILjava/lang/String;)[Lcom/google/android/gms/internal/measurement/zzgg;
    //   2701: astore_1
    //   2702: aload 24
    //   2704: aload_1
    //   2705: putfield 958	com/google/android/gms/internal/measurement/zzgf:zzawt	[Lcom/google/android/gms/internal/measurement/zzgg;
    //   2708: goto +3 -> 2711
    //   2711: lload 11
    //   2713: lstore_2
    //   2714: iload 15
    //   2716: ifeq +137 -> 2853
    //   2719: lload 11
    //   2721: lstore_2
    //   2722: ldc_w 1042
    //   2725: aload 24
    //   2727: getfield 883	com/google/android/gms/internal/measurement/zzgf:name	Ljava/lang/String;
    //   2730: invokevirtual 230	java/lang/String:equals	(Ljava/lang/Object;)Z
    //   2733: ifeq +120 -> 2853
    //   2736: aload 24
    //   2738: getfield 958	com/google/android/gms/internal/measurement/zzgf:zzawt	[Lcom/google/android/gms/internal/measurement/zzgg;
    //   2741: ifnull +81 -> 2822
    //   2744: aload 24
    //   2746: getfield 958	com/google/android/gms/internal/measurement/zzgf:zzawt	[Lcom/google/android/gms/internal/measurement/zzgg;
    //   2749: arraylength
    //   2750: ifne +6 -> 2756
    //   2753: goto +69 -> 2822
    //   2756: aload_0
    //   2757: invokevirtual 942	com/google/android/gms/measurement/internal/zzfa:zzjo	()Lcom/google/android/gms/measurement/internal/zzfg;
    //   2760: pop
    //   2761: aload 24
    //   2763: ldc_w 1044
    //   2766: invokestatic 1047	com/google/android/gms/measurement/internal/zzfg:zzb	(Lcom/google/android/gms/internal/measurement/zzgf;Ljava/lang/String;)Ljava/lang/Object;
    //   2769: checkcast 398	java/lang/Long
    //   2772: astore_1
    //   2773: aload_1
    //   2774: ifnonnull +37 -> 2811
    //   2777: aload 23
    //   2779: getfield 79	com/google/android/gms/measurement/internal/zzfa:zzadj	Lcom/google/android/gms/measurement/internal/zzbt;
    //   2782: invokevirtual 150	com/google/android/gms/measurement/internal/zzbt:zzgo	()Lcom/google/android/gms/measurement/internal/zzap;
    //   2785: invokevirtual 156	com/google/android/gms/measurement/internal/zzap:zzjg	()Lcom/google/android/gms/measurement/internal/zzar;
    //   2788: ldc_w 1049
    //   2791: aload 19
    //   2793: getfield 906	com/google/android/gms/measurement/internal/zzfa$zza:zzaua	Lcom/google/android/gms/internal/measurement/zzgi;
    //   2796: getfield 915	com/google/android/gms/internal/measurement/zzgi:zztt	Ljava/lang/String;
    //   2799: invokestatic 220	com/google/android/gms/measurement/internal/zzap:zzbv	(Ljava/lang/String;)Ljava/lang/Object;
    //   2802: invokevirtual 170	com/google/android/gms/measurement/internal/zzar:zzg	(Ljava/lang/String;Ljava/lang/Object;)V
    //   2805: lload 11
    //   2807: lstore_2
    //   2808: goto +45 -> 2853
    //   2811: lload 11
    //   2813: aload_1
    //   2814: invokevirtual 445	java/lang/Long:longValue	()J
    //   2817: ladd
    //   2818: lstore_2
    //   2819: goto +34 -> 2853
    //   2822: aload 23
    //   2824: getfield 79	com/google/android/gms/measurement/internal/zzfa:zzadj	Lcom/google/android/gms/measurement/internal/zzbt;
    //   2827: invokevirtual 150	com/google/android/gms/measurement/internal/zzbt:zzgo	()Lcom/google/android/gms/measurement/internal/zzap;
    //   2830: invokevirtual 156	com/google/android/gms/measurement/internal/zzap:zzjg	()Lcom/google/android/gms/measurement/internal/zzar;
    //   2833: ldc_w 1051
    //   2836: aload 19
    //   2838: getfield 906	com/google/android/gms/measurement/internal/zzfa$zza:zzaua	Lcom/google/android/gms/internal/measurement/zzgi;
    //   2841: getfield 915	com/google/android/gms/internal/measurement/zzgi:zztt	Ljava/lang/String;
    //   2844: invokestatic 220	com/google/android/gms/measurement/internal/zzap:zzbv	(Ljava/lang/String;)Ljava/lang/Object;
    //   2847: invokevirtual 170	com/google/android/gms/measurement/internal/zzar:zzg	(Ljava/lang/String;Ljava/lang/Object;)V
    //   2850: lload 11
    //   2852: lstore_2
    //   2853: aload 18
    //   2855: getfield 912	com/google/android/gms/internal/measurement/zzgi:zzaxb	[Lcom/google/android/gms/internal/measurement/zzgf;
    //   2858: astore_1
    //   2859: iload 9
    //   2861: iconst_1
    //   2862: iadd
    //   2863: istore 5
    //   2865: aload_1
    //   2866: iload 9
    //   2868: aload 24
    //   2870: aastore
    //   2871: iload 14
    //   2873: istore 13
    //   2875: goto +2554 -> 5429
    //   2878: iload 5
    //   2880: aload 19
    //   2882: getfield 898	com/google/android/gms/measurement/internal/zzfa$zza:zzauc	Ljava/util/List;
    //   2885: invokeinterface 908 1 0
    //   2890: if_icmpge +21 -> 2911
    //   2893: aload 18
    //   2895: aload 18
    //   2897: getfield 912	com/google/android/gms/internal/measurement/zzgi:zzaxb	[Lcom/google/android/gms/internal/measurement/zzgf;
    //   2900: iload 5
    //   2902: invokestatic 970	java/util/Arrays:copyOf	([Ljava/lang/Object;I)[Ljava/lang/Object;
    //   2905: checkcast 1052	[Lcom/google/android/gms/internal/measurement/zzgf;
    //   2908: putfield 912	com/google/android/gms/internal/measurement/zzgi:zzaxb	[Lcom/google/android/gms/internal/measurement/zzgf;
    //   2911: iload 15
    //   2913: ifeq +300 -> 3213
    //   2916: aload_0
    //   2917: invokevirtual 489	com/google/android/gms/measurement/internal/zzfa:zzjq	()Lcom/google/android/gms/measurement/internal/zzq;
    //   2920: aload 18
    //   2922: getfield 915	com/google/android/gms/internal/measurement/zzgi:zztt	Ljava/lang/String;
    //   2925: aload 17
    //   2927: invokevirtual 493	com/google/android/gms/measurement/internal/zzq:zzi	(Ljava/lang/String;Ljava/lang/String;)Lcom/google/android/gms/measurement/internal/zzfj;
    //   2930: astore_1
    //   2931: aload_1
    //   2932: ifnull +63 -> 2995
    //   2935: aload_1
    //   2936: getfield 498	com/google/android/gms/measurement/internal/zzfj:value	Ljava/lang/Object;
    //   2939: ifnonnull +6 -> 2945
    //   2942: goto +53 -> 2995
    //   2945: new 495	com/google/android/gms/measurement/internal/zzfj
    //   2948: dup
    //   2949: aload 18
    //   2951: getfield 915	com/google/android/gms/internal/measurement/zzgi:zztt	Ljava/lang/String;
    //   2954: ldc_w 1054
    //   2957: ldc_w 791
    //   2960: aload 23
    //   2962: getfield 79	com/google/android/gms/measurement/internal/zzfa:zzadj	Lcom/google/android/gms/measurement/internal/zzbt;
    //   2965: invokevirtual 504	com/google/android/gms/measurement/internal/zzbt:zzbx	()Lcom/google/android/gms/common/util/Clock;
    //   2968: invokeinterface 509 1 0
    //   2973: aload_1
    //   2974: getfield 498	com/google/android/gms/measurement/internal/zzfj:value	Ljava/lang/Object;
    //   2977: checkcast 398	java/lang/Long
    //   2980: invokevirtual 445	java/lang/Long:longValue	()J
    //   2983: lload_2
    //   2984: ladd
    //   2985: invokestatic 401	java/lang/Long:valueOf	(J)Ljava/lang/Long;
    //   2988: invokespecial 512	com/google/android/gms/measurement/internal/zzfj:<init>	(Ljava/lang/String;Ljava/lang/String;Ljava/lang/String;JLjava/lang/Object;)V
    //   2991: astore_1
    //   2992: goto +39 -> 3031
    //   2995: new 495	com/google/android/gms/measurement/internal/zzfj
    //   2998: dup
    //   2999: aload 18
    //   3001: getfield 915	com/google/android/gms/internal/measurement/zzgi:zztt	Ljava/lang/String;
    //   3004: ldc_w 1054
    //   3007: ldc_w 791
    //   3010: aload 23
    //   3012: getfield 79	com/google/android/gms/measurement/internal/zzfa:zzadj	Lcom/google/android/gms/measurement/internal/zzbt;
    //   3015: invokevirtual 504	com/google/android/gms/measurement/internal/zzbt:zzbx	()Lcom/google/android/gms/common/util/Clock;
    //   3018: invokeinterface 509 1 0
    //   3023: lload_2
    //   3024: invokestatic 401	java/lang/Long:valueOf	(J)Ljava/lang/Long;
    //   3027: invokespecial 512	com/google/android/gms/measurement/internal/zzfj:<init>	(Ljava/lang/String;Ljava/lang/String;Ljava/lang/String;JLjava/lang/Object;)V
    //   3030: astore_1
    //   3031: new 1056	com/google/android/gms/internal/measurement/zzgl
    //   3034: dup
    //   3035: invokespecial 1057	com/google/android/gms/internal/measurement/zzgl:<init>	()V
    //   3038: astore 20
    //   3040: aload 20
    //   3042: aload 17
    //   3044: putfield 1058	com/google/android/gms/internal/measurement/zzgl:name	Ljava/lang/String;
    //   3047: aload 20
    //   3049: aload 23
    //   3051: getfield 79	com/google/android/gms/measurement/internal/zzfa:zzadj	Lcom/google/android/gms/measurement/internal/zzbt;
    //   3054: invokevirtual 504	com/google/android/gms/measurement/internal/zzbt:zzbx	()Lcom/google/android/gms/common/util/Clock;
    //   3057: invokeinterface 509 1 0
    //   3062: invokestatic 401	java/lang/Long:valueOf	(J)Ljava/lang/Long;
    //   3065: putfield 1061	com/google/android/gms/internal/measurement/zzgl:zzayl	Ljava/lang/Long;
    //   3068: aload 20
    //   3070: aload_1
    //   3071: getfield 498	com/google/android/gms/measurement/internal/zzfj:value	Ljava/lang/Object;
    //   3074: checkcast 398	java/lang/Long
    //   3077: putfield 1062	com/google/android/gms/internal/measurement/zzgl:zzawx	Ljava/lang/Long;
    //   3080: iconst_0
    //   3081: istore 4
    //   3083: iload 4
    //   3085: aload 18
    //   3087: getfield 1066	com/google/android/gms/internal/measurement/zzgi:zzaxc	[Lcom/google/android/gms/internal/measurement/zzgl;
    //   3090: arraylength
    //   3091: if_icmpge +2356 -> 5447
    //   3094: aload 17
    //   3096: aload 18
    //   3098: getfield 1066	com/google/android/gms/internal/measurement/zzgi:zzaxc	[Lcom/google/android/gms/internal/measurement/zzgl;
    //   3101: iload 4
    //   3103: aaload
    //   3104: getfield 1058	com/google/android/gms/internal/measurement/zzgl:name	Ljava/lang/String;
    //   3107: invokevirtual 230	java/lang/String:equals	(Ljava/lang/Object;)Z
    //   3110: ifeq +2328 -> 5438
    //   3113: aload 18
    //   3115: getfield 1066	com/google/android/gms/internal/measurement/zzgi:zzaxc	[Lcom/google/android/gms/internal/measurement/zzgl;
    //   3118: iload 4
    //   3120: aload 20
    //   3122: aastore
    //   3123: iconst_1
    //   3124: istore 4
    //   3126: goto +3 -> 3129
    //   3129: iload 4
    //   3131: ifne +46 -> 3177
    //   3134: aload 18
    //   3136: aload 18
    //   3138: getfield 1066	com/google/android/gms/internal/measurement/zzgi:zzaxc	[Lcom/google/android/gms/internal/measurement/zzgl;
    //   3141: aload 18
    //   3143: getfield 1066	com/google/android/gms/internal/measurement/zzgi:zzaxc	[Lcom/google/android/gms/internal/measurement/zzgl;
    //   3146: arraylength
    //   3147: iconst_1
    //   3148: iadd
    //   3149: invokestatic 970	java/util/Arrays:copyOf	([Ljava/lang/Object;I)[Ljava/lang/Object;
    //   3152: checkcast 1067	[Lcom/google/android/gms/internal/measurement/zzgl;
    //   3155: putfield 1066	com/google/android/gms/internal/measurement/zzgi:zzaxc	[Lcom/google/android/gms/internal/measurement/zzgl;
    //   3158: aload 18
    //   3160: getfield 1066	com/google/android/gms/internal/measurement/zzgi:zzaxc	[Lcom/google/android/gms/internal/measurement/zzgl;
    //   3163: aload 19
    //   3165: getfield 906	com/google/android/gms/measurement/internal/zzfa$zza:zzaua	Lcom/google/android/gms/internal/measurement/zzgi;
    //   3168: getfield 1066	com/google/android/gms/internal/measurement/zzgi:zzaxc	[Lcom/google/android/gms/internal/measurement/zzgl;
    //   3171: arraylength
    //   3172: iconst_1
    //   3173: isub
    //   3174: aload 20
    //   3176: aastore
    //   3177: lload_2
    //   3178: lconst_0
    //   3179: lcmp
    //   3180: ifle +33 -> 3213
    //   3183: aload_0
    //   3184: invokevirtual 489	com/google/android/gms/measurement/internal/zzfa:zzjq	()Lcom/google/android/gms/measurement/internal/zzq;
    //   3187: aload_1
    //   3188: invokevirtual 549	com/google/android/gms/measurement/internal/zzq:zza	(Lcom/google/android/gms/measurement/internal/zzfj;)Z
    //   3191: pop
    //   3192: aload 23
    //   3194: getfield 79	com/google/android/gms/measurement/internal/zzfa:zzadj	Lcom/google/android/gms/measurement/internal/zzbt;
    //   3197: invokevirtual 150	com/google/android/gms/measurement/internal/zzbt:zzgo	()Lcom/google/android/gms/measurement/internal/zzap;
    //   3200: invokevirtual 778	com/google/android/gms/measurement/internal/zzap:zzjk	()Lcom/google/android/gms/measurement/internal/zzar;
    //   3203: ldc_w 1069
    //   3206: aload_1
    //   3207: getfield 498	com/google/android/gms/measurement/internal/zzfj:value	Ljava/lang/Object;
    //   3210: invokevirtual 170	com/google/android/gms/measurement/internal/zzar:zzg	(Ljava/lang/String;Ljava/lang/Object;)V
    //   3213: aload 18
    //   3215: aload 23
    //   3217: aload 18
    //   3219: getfield 915	com/google/android/gms/internal/measurement/zzgi:zztt	Ljava/lang/String;
    //   3222: aload 18
    //   3224: getfield 1066	com/google/android/gms/internal/measurement/zzgi:zzaxc	[Lcom/google/android/gms/internal/measurement/zzgl;
    //   3227: aload 18
    //   3229: getfield 912	com/google/android/gms/internal/measurement/zzgi:zzaxb	[Lcom/google/android/gms/internal/measurement/zzgf;
    //   3232: invokespecial 1071	com/google/android/gms/measurement/internal/zzfa:zza	(Ljava/lang/String;[Lcom/google/android/gms/internal/measurement/zzgl;[Lcom/google/android/gms/internal/measurement/zzgf;)[Lcom/google/android/gms/internal/measurement/zzgd;
    //   3235: putfield 1075	com/google/android/gms/internal/measurement/zzgi:zzaxt	[Lcom/google/android/gms/internal/measurement/zzgd;
    //   3238: aload 23
    //   3240: getfield 79	com/google/android/gms/measurement/internal/zzfa:zzadj	Lcom/google/android/gms/measurement/internal/zzbt;
    //   3243: invokevirtual 278	com/google/android/gms/measurement/internal/zzbt:zzgq	()Lcom/google/android/gms/measurement/internal/zzn;
    //   3246: aload 19
    //   3248: getfield 906	com/google/android/gms/measurement/internal/zzfa$zza:zzaua	Lcom/google/android/gms/internal/measurement/zzgi;
    //   3251: getfield 915	com/google/android/gms/internal/measurement/zzgi:zztt	Ljava/lang/String;
    //   3254: invokevirtual 1078	com/google/android/gms/measurement/internal/zzn:zzaw	(Ljava/lang/String;)Z
    //   3257: istore 14
    //   3259: iload 14
    //   3261: ifeq +2257 -> 5518
    //   3264: new 1080	java/util/HashMap
    //   3267: dup
    //   3268: invokespecial 1081	java/util/HashMap:<init>	()V
    //   3271: astore_1
    //   3272: aload 18
    //   3274: getfield 912	com/google/android/gms/internal/measurement/zzgi:zzaxb	[Lcom/google/android/gms/internal/measurement/zzgf;
    //   3277: arraylength
    //   3278: anewarray 881	com/google/android/gms/internal/measurement/zzgf
    //   3281: astore 24
    //   3283: aload 23
    //   3285: getfield 79	com/google/android/gms/measurement/internal/zzfa:zzadj	Lcom/google/android/gms/measurement/internal/zzbt;
    //   3288: invokevirtual 294	com/google/android/gms/measurement/internal/zzbt:zzgm	()Lcom/google/android/gms/measurement/internal/zzfk;
    //   3291: invokevirtual 1085	com/google/android/gms/measurement/internal/zzfk:zzmd	()Ljava/security/SecureRandom;
    //   3294: astore 20
    //   3296: aload 18
    //   3298: getfield 912	com/google/android/gms/internal/measurement/zzgi:zzaxb	[Lcom/google/android/gms/internal/measurement/zzgf;
    //   3301: astore 21
    //   3303: aload 21
    //   3305: arraylength
    //   3306: istore 6
    //   3308: iconst_0
    //   3309: istore 7
    //   3311: iconst_0
    //   3312: istore 5
    //   3314: aload_0
    //   3315: astore 22
    //   3317: iload 7
    //   3319: iload 6
    //   3321: if_icmpge +1121 -> 4442
    //   3324: aload 21
    //   3326: iload 7
    //   3328: aaload
    //   3329: astore 25
    //   3331: aload 25
    //   3333: getfield 883	com/google/android/gms/internal/measurement/zzgf:name	Ljava/lang/String;
    //   3336: ldc_w 1087
    //   3339: invokevirtual 230	java/lang/String:equals	(Ljava/lang/Object;)Z
    //   3342: istore 14
    //   3344: iload 14
    //   3346: ifeq +187 -> 3533
    //   3349: aload_0
    //   3350: invokevirtual 942	com/google/android/gms/measurement/internal/zzfa:zzjo	()Lcom/google/android/gms/measurement/internal/zzfg;
    //   3353: pop
    //   3354: aload 25
    //   3356: ldc_w 1089
    //   3359: invokestatic 1047	com/google/android/gms/measurement/internal/zzfg:zzb	(Lcom/google/android/gms/internal/measurement/zzgf;Ljava/lang/String;)Ljava/lang/Object;
    //   3362: checkcast 226	java/lang/String
    //   3365: astore 23
    //   3367: aload_1
    //   3368: aload 23
    //   3370: invokeinterface 1091 2 0
    //   3375: checkcast 1093	com/google/android/gms/measurement/internal/zzz
    //   3378: astore 22
    //   3380: aload 22
    //   3382: astore 17
    //   3384: aload 22
    //   3386: ifnonnull +33 -> 3419
    //   3389: aload_0
    //   3390: invokevirtual 489	com/google/android/gms/measurement/internal/zzfa:zzjq	()Lcom/google/android/gms/measurement/internal/zzq;
    //   3393: aload 19
    //   3395: getfield 906	com/google/android/gms/measurement/internal/zzfa$zza:zzaua	Lcom/google/android/gms/internal/measurement/zzgi;
    //   3398: getfield 915	com/google/android/gms/internal/measurement/zzgi:zztt	Ljava/lang/String;
    //   3401: aload 23
    //   3403: invokevirtual 1096	com/google/android/gms/measurement/internal/zzq:zzg	(Ljava/lang/String;Ljava/lang/String;)Lcom/google/android/gms/measurement/internal/zzz;
    //   3406: astore 17
    //   3408: aload_1
    //   3409: aload 23
    //   3411: aload 17
    //   3413: invokeinterface 703 3 0
    //   3418: pop
    //   3419: aload 17
    //   3421: getfield 1099	com/google/android/gms/measurement/internal/zzz:zzaij	Ljava/lang/Long;
    //   3424: ifnonnull +102 -> 3526
    //   3427: aload 17
    //   3429: getfield 1102	com/google/android/gms/measurement/internal/zzz:zzaik	Ljava/lang/Long;
    //   3432: invokevirtual 445	java/lang/Long:longValue	()J
    //   3435: lconst_1
    //   3436: lcmp
    //   3437: ifle +29 -> 3466
    //   3440: aload_0
    //   3441: invokevirtual 942	com/google/android/gms/measurement/internal/zzfa:zzjo	()Lcom/google/android/gms/measurement/internal/zzfg;
    //   3444: pop
    //   3445: aload 25
    //   3447: aload 25
    //   3449: getfield 958	com/google/android/gms/internal/measurement/zzgf:zzawt	[Lcom/google/android/gms/internal/measurement/zzgg;
    //   3452: ldc_w 1104
    //   3455: aload 17
    //   3457: getfield 1102	com/google/android/gms/measurement/internal/zzz:zzaik	Ljava/lang/Long;
    //   3460: invokestatic 1107	com/google/android/gms/measurement/internal/zzfg:zza	([Lcom/google/android/gms/internal/measurement/zzgg;Ljava/lang/String;Ljava/lang/Object;)[Lcom/google/android/gms/internal/measurement/zzgg;
    //   3463: putfield 958	com/google/android/gms/internal/measurement/zzgf:zzawt	[Lcom/google/android/gms/internal/measurement/zzgg;
    //   3466: aload 17
    //   3468: getfield 1111	com/google/android/gms/measurement/internal/zzz:zzail	Ljava/lang/Boolean;
    //   3471: ifnull +39 -> 3510
    //   3474: aload 17
    //   3476: getfield 1111	com/google/android/gms/measurement/internal/zzz:zzail	Ljava/lang/Boolean;
    //   3479: invokevirtual 751	java/lang/Boolean:booleanValue	()Z
    //   3482: ifeq +28 -> 3510
    //   3485: aload_0
    //   3486: invokevirtual 942	com/google/android/gms/measurement/internal/zzfa:zzjo	()Lcom/google/android/gms/measurement/internal/zzfg;
    //   3489: pop
    //   3490: aload 25
    //   3492: aload 25
    //   3494: getfield 958	com/google/android/gms/internal/measurement/zzgf:zzawt	[Lcom/google/android/gms/internal/measurement/zzgg;
    //   3497: ldc_w 1113
    //   3500: lconst_1
    //   3501: invokestatic 401	java/lang/Long:valueOf	(J)Ljava/lang/Long;
    //   3504: invokestatic 1107	com/google/android/gms/measurement/internal/zzfg:zza	([Lcom/google/android/gms/internal/measurement/zzgg;Ljava/lang/String;Ljava/lang/Object;)[Lcom/google/android/gms/internal/measurement/zzgg;
    //   3507: putfield 958	com/google/android/gms/internal/measurement/zzgf:zzawt	[Lcom/google/android/gms/internal/measurement/zzgg;
    //   3510: aload 24
    //   3512: iload 5
    //   3514: aload 25
    //   3516: aastore
    //   3517: iload 5
    //   3519: iconst_1
    //   3520: iadd
    //   3521: istore 4
    //   3523: goto +1982 -> 5505
    //   3526: iload 5
    //   3528: istore 4
    //   3530: goto -7 -> 3523
    //   3533: aload_0
    //   3534: invokespecial 685	com/google/android/gms/measurement/internal/zzfa:zzln	()Lcom/google/android/gms/measurement/internal/zzbn;
    //   3537: aload 19
    //   3539: getfield 906	com/google/android/gms/measurement/internal/zzfa$zza:zzaua	Lcom/google/android/gms/internal/measurement/zzgi;
    //   3542: getfield 915	com/google/android/gms/internal/measurement/zzgi:zztt	Ljava/lang/String;
    //   3545: invokevirtual 1117	com/google/android/gms/measurement/internal/zzbn:zzcj	(Ljava/lang/String;)J
    //   3548: lstore_2
    //   3549: aload 22
    //   3551: getfield 79	com/google/android/gms/measurement/internal/zzfa:zzadj	Lcom/google/android/gms/measurement/internal/zzbt;
    //   3554: invokevirtual 294	com/google/android/gms/measurement/internal/zzbt:zzgm	()Lcom/google/android/gms/measurement/internal/zzfk;
    //   3557: pop
    //   3558: aload 25
    //   3560: getfield 886	com/google/android/gms/internal/measurement/zzgf:zzawu	Ljava/lang/Long;
    //   3563: invokevirtual 445	java/lang/Long:longValue	()J
    //   3566: lload_2
    //   3567: invokestatic 1120	com/google/android/gms/measurement/internal/zzfk:zzc	(JJ)J
    //   3570: lstore 11
    //   3572: lconst_1
    //   3573: invokestatic 401	java/lang/Long:valueOf	(J)Ljava/lang/Long;
    //   3576: astore 23
    //   3578: ldc_w 1122
    //   3581: invokestatic 254	android/text/TextUtils:isEmpty	(Ljava/lang/CharSequence;)Z
    //   3584: istore 14
    //   3586: iload 14
    //   3588: ifne +1880 -> 5468
    //   3591: aload 23
    //   3593: ifnonnull +6 -> 3599
    //   3596: goto +1872 -> 5468
    //   3599: aload 25
    //   3601: getfield 958	com/google/android/gms/internal/measurement/zzgf:zzawt	[Lcom/google/android/gms/internal/measurement/zzgg;
    //   3604: astore 17
    //   3606: aload 17
    //   3608: arraylength
    //   3609: istore 4
    //   3611: iconst_0
    //   3612: istore 8
    //   3614: iload 8
    //   3616: iload 4
    //   3618: if_icmpge +1850 -> 5468
    //   3621: aload 17
    //   3623: iload 8
    //   3625: aaload
    //   3626: astore 26
    //   3628: ldc_w 1122
    //   3631: aload 26
    //   3633: getfield 588	com/google/android/gms/internal/measurement/zzgg:name	Ljava/lang/String;
    //   3636: invokevirtual 230	java/lang/String:equals	(Ljava/lang/Object;)Z
    //   3639: ifeq +1820 -> 5459
    //   3642: aload 23
    //   3644: instanceof 398
    //   3647: ifeq +16 -> 3663
    //   3650: aload 23
    //   3652: aload 26
    //   3654: getfield 593	com/google/android/gms/internal/measurement/zzgg:zzawx	Ljava/lang/Long;
    //   3657: invokevirtual 1123	java/lang/Object:equals	(Ljava/lang/Object;)Z
    //   3660: ifne +1793 -> 5453
    //   3663: aload 23
    //   3665: instanceof 226
    //   3668: ifeq +16 -> 3684
    //   3671: aload 23
    //   3673: aload 26
    //   3675: getfield 598	com/google/android/gms/internal/measurement/zzgg:zzamp	Ljava/lang/String;
    //   3678: invokevirtual 1123	java/lang/Object:equals	(Ljava/lang/Object;)Z
    //   3681: ifne +1772 -> 5453
    //   3684: aload 23
    //   3686: instanceof 432
    //   3689: ifeq +1779 -> 5468
    //   3692: aload 23
    //   3694: aload 26
    //   3696: getfield 1016	com/google/android/gms/internal/measurement/zzgg:zzauh	Ljava/lang/Double;
    //   3699: invokevirtual 1123	java/lang/Object:equals	(Ljava/lang/Object;)Z
    //   3702: ifeq +1766 -> 5468
    //   3705: goto +1748 -> 5453
    //   3708: iload 4
    //   3710: ifne +1764 -> 5474
    //   3713: aload_0
    //   3714: invokespecial 685	com/google/android/gms/measurement/internal/zzfa:zzln	()Lcom/google/android/gms/measurement/internal/zzbn;
    //   3717: aload 19
    //   3719: getfield 906	com/google/android/gms/measurement/internal/zzfa$zza:zzaua	Lcom/google/android/gms/internal/measurement/zzgi;
    //   3722: getfield 915	com/google/android/gms/internal/measurement/zzgi:zztt	Ljava/lang/String;
    //   3725: aload 25
    //   3727: getfield 883	com/google/android/gms/internal/measurement/zzgf:name	Ljava/lang/String;
    //   3730: invokevirtual 1126	com/google/android/gms/measurement/internal/zzbn:zzq	(Ljava/lang/String;Ljava/lang/String;)I
    //   3733: istore 4
    //   3735: goto +3 -> 3738
    //   3738: iload 4
    //   3740: ifgt +46 -> 3786
    //   3743: aload 22
    //   3745: getfield 79	com/google/android/gms/measurement/internal/zzfa:zzadj	Lcom/google/android/gms/measurement/internal/zzbt;
    //   3748: invokevirtual 150	com/google/android/gms/measurement/internal/zzbt:zzgo	()Lcom/google/android/gms/measurement/internal/zzap;
    //   3751: invokevirtual 156	com/google/android/gms/measurement/internal/zzap:zzjg	()Lcom/google/android/gms/measurement/internal/zzar;
    //   3754: ldc_w 1128
    //   3757: aload 25
    //   3759: getfield 883	com/google/android/gms/internal/measurement/zzgf:name	Ljava/lang/String;
    //   3762: iload 4
    //   3764: invokestatic 164	java/lang/Integer:valueOf	(I)Ljava/lang/Integer;
    //   3767: invokevirtual 309	com/google/android/gms/measurement/internal/zzar:zze	(Ljava/lang/String;Ljava/lang/Object;Ljava/lang/Object;)V
    //   3770: iload 5
    //   3772: iconst_1
    //   3773: iadd
    //   3774: istore 4
    //   3776: aload 24
    //   3778: iload 5
    //   3780: aload 25
    //   3782: aastore
    //   3783: goto -260 -> 3523
    //   3786: aload_1
    //   3787: aload 25
    //   3789: getfield 883	com/google/android/gms/internal/measurement/zzgf:name	Ljava/lang/String;
    //   3792: invokeinterface 1091 2 0
    //   3797: checkcast 1093	com/google/android/gms/measurement/internal/zzz
    //   3800: astore 23
    //   3802: aload 23
    //   3804: astore 17
    //   3806: aload 23
    //   3808: ifnonnull +101 -> 3909
    //   3811: aload_0
    //   3812: invokevirtual 489	com/google/android/gms/measurement/internal/zzfa:zzjq	()Lcom/google/android/gms/measurement/internal/zzq;
    //   3815: aload 19
    //   3817: getfield 906	com/google/android/gms/measurement/internal/zzfa$zza:zzaua	Lcom/google/android/gms/internal/measurement/zzgi;
    //   3820: getfield 915	com/google/android/gms/internal/measurement/zzgi:zztt	Ljava/lang/String;
    //   3823: aload 25
    //   3825: getfield 883	com/google/android/gms/internal/measurement/zzgf:name	Ljava/lang/String;
    //   3828: invokevirtual 1096	com/google/android/gms/measurement/internal/zzq:zzg	(Ljava/lang/String;Ljava/lang/String;)Lcom/google/android/gms/measurement/internal/zzz;
    //   3831: astore 23
    //   3833: aload 23
    //   3835: astore 17
    //   3837: aload 23
    //   3839: ifnonnull +70 -> 3909
    //   3842: aload 22
    //   3844: getfield 79	com/google/android/gms/measurement/internal/zzfa:zzadj	Lcom/google/android/gms/measurement/internal/zzbt;
    //   3847: invokevirtual 150	com/google/android/gms/measurement/internal/zzbt:zzgo	()Lcom/google/android/gms/measurement/internal/zzap;
    //   3850: invokevirtual 156	com/google/android/gms/measurement/internal/zzap:zzjg	()Lcom/google/android/gms/measurement/internal/zzar;
    //   3853: ldc_w 1130
    //   3856: aload 19
    //   3858: getfield 906	com/google/android/gms/measurement/internal/zzfa$zza:zzaua	Lcom/google/android/gms/internal/measurement/zzgi;
    //   3861: getfield 915	com/google/android/gms/internal/measurement/zzgi:zztt	Ljava/lang/String;
    //   3864: aload 25
    //   3866: getfield 883	com/google/android/gms/internal/measurement/zzgf:name	Ljava/lang/String;
    //   3869: invokevirtual 309	com/google/android/gms/measurement/internal/zzar:zze	(Ljava/lang/String;Ljava/lang/Object;Ljava/lang/Object;)V
    //   3872: new 1093	com/google/android/gms/measurement/internal/zzz
    //   3875: dup
    //   3876: aload 19
    //   3878: getfield 906	com/google/android/gms/measurement/internal/zzfa$zza:zzaua	Lcom/google/android/gms/internal/measurement/zzgi;
    //   3881: getfield 915	com/google/android/gms/internal/measurement/zzgi:zztt	Ljava/lang/String;
    //   3884: aload 25
    //   3886: getfield 883	com/google/android/gms/internal/measurement/zzgf:name	Ljava/lang/String;
    //   3889: lconst_1
    //   3890: lconst_1
    //   3891: aload 25
    //   3893: getfield 886	com/google/android/gms/internal/measurement/zzgf:zzawu	Ljava/lang/Long;
    //   3896: invokevirtual 445	java/lang/Long:longValue	()J
    //   3899: lconst_0
    //   3900: aconst_null
    //   3901: aconst_null
    //   3902: aconst_null
    //   3903: aconst_null
    //   3904: invokespecial 1133	com/google/android/gms/measurement/internal/zzz:<init>	(Ljava/lang/String;Ljava/lang/String;JJJJLjava/lang/Long;Ljava/lang/Long;Ljava/lang/Long;Ljava/lang/Boolean;)V
    //   3907: astore 17
    //   3909: aload_0
    //   3910: invokevirtual 942	com/google/android/gms/measurement/internal/zzfa:zzjo	()Lcom/google/android/gms/measurement/internal/zzfg;
    //   3913: pop
    //   3914: aload 25
    //   3916: ldc_w 1135
    //   3919: invokestatic 1047	com/google/android/gms/measurement/internal/zzfg:zzb	(Lcom/google/android/gms/internal/measurement/zzgf;Ljava/lang/String;)Ljava/lang/Object;
    //   3922: checkcast 398	java/lang/Long
    //   3925: astore 26
    //   3927: aload 26
    //   3929: ifnull +1551 -> 5480
    //   3932: iconst_1
    //   3933: istore 14
    //   3935: goto +3 -> 3938
    //   3938: iload 14
    //   3940: invokestatic 737	java/lang/Boolean:valueOf	(Z)Ljava/lang/Boolean;
    //   3943: astore 23
    //   3945: iload 4
    //   3947: iconst_1
    //   3948: if_icmpne +87 -> 4035
    //   3951: iload 5
    //   3953: iconst_1
    //   3954: iadd
    //   3955: istore 8
    //   3957: aload 24
    //   3959: iload 5
    //   3961: aload 25
    //   3963: aastore
    //   3964: iload 8
    //   3966: istore 4
    //   3968: aload 23
    //   3970: invokevirtual 751	java/lang/Boolean:booleanValue	()Z
    //   3973: ifeq -190 -> 3783
    //   3976: aload 17
    //   3978: getfield 1099	com/google/android/gms/measurement/internal/zzz:zzaij	Ljava/lang/Long;
    //   3981: ifnonnull +23 -> 4004
    //   3984: aload 17
    //   3986: getfield 1102	com/google/android/gms/measurement/internal/zzz:zzaik	Ljava/lang/Long;
    //   3989: ifnonnull +15 -> 4004
    //   3992: iload 8
    //   3994: istore 4
    //   3996: aload 17
    //   3998: getfield 1111	com/google/android/gms/measurement/internal/zzz:zzail	Ljava/lang/Boolean;
    //   4001: ifnull -218 -> 3783
    //   4004: aload 17
    //   4006: aconst_null
    //   4007: aconst_null
    //   4008: aconst_null
    //   4009: invokevirtual 1138	com/google/android/gms/measurement/internal/zzz:zza	(Ljava/lang/Long;Ljava/lang/Long;Ljava/lang/Boolean;)Lcom/google/android/gms/measurement/internal/zzz;
    //   4012: astore 17
    //   4014: aload_1
    //   4015: aload 25
    //   4017: getfield 883	com/google/android/gms/internal/measurement/zzgf:name	Ljava/lang/String;
    //   4020: aload 17
    //   4022: invokeinterface 703 3 0
    //   4027: pop
    //   4028: iload 8
    //   4030: istore 4
    //   4032: goto -249 -> 3783
    //   4035: aload 20
    //   4037: iload 4
    //   4039: invokevirtual 1143	java/security/SecureRandom:nextInt	(I)I
    //   4042: istore 8
    //   4044: iload 8
    //   4046: ifne +104 -> 4150
    //   4049: aload_0
    //   4050: invokevirtual 942	com/google/android/gms/measurement/internal/zzfa:zzjo	()Lcom/google/android/gms/measurement/internal/zzfg;
    //   4053: pop
    //   4054: aload 25
    //   4056: getfield 958	com/google/android/gms/internal/measurement/zzgf:zzawt	[Lcom/google/android/gms/internal/measurement/zzgg;
    //   4059: astore 22
    //   4061: iload 4
    //   4063: i2l
    //   4064: lstore_2
    //   4065: aload 25
    //   4067: aload 22
    //   4069: ldc_w 1104
    //   4072: lload_2
    //   4073: invokestatic 401	java/lang/Long:valueOf	(J)Ljava/lang/Long;
    //   4076: invokestatic 1107	com/google/android/gms/measurement/internal/zzfg:zza	([Lcom/google/android/gms/internal/measurement/zzgg;Ljava/lang/String;Ljava/lang/Object;)[Lcom/google/android/gms/internal/measurement/zzgg;
    //   4079: putfield 958	com/google/android/gms/internal/measurement/zzgf:zzawt	[Lcom/google/android/gms/internal/measurement/zzgg;
    //   4082: aload 24
    //   4084: iload 5
    //   4086: aload 25
    //   4088: aastore
    //   4089: aload 17
    //   4091: astore 22
    //   4093: aload 23
    //   4095: invokevirtual 751	java/lang/Boolean:booleanValue	()Z
    //   4098: ifeq +16 -> 4114
    //   4101: aload 17
    //   4103: aconst_null
    //   4104: lload_2
    //   4105: invokestatic 401	java/lang/Long:valueOf	(J)Ljava/lang/Long;
    //   4108: aconst_null
    //   4109: invokevirtual 1138	com/google/android/gms/measurement/internal/zzz:zza	(Ljava/lang/Long;Ljava/lang/Long;Ljava/lang/Boolean;)Lcom/google/android/gms/measurement/internal/zzz;
    //   4112: astore 22
    //   4114: aload_1
    //   4115: aload 25
    //   4117: getfield 883	com/google/android/gms/internal/measurement/zzgf:name	Ljava/lang/String;
    //   4120: aload 22
    //   4122: aload 25
    //   4124: getfield 886	com/google/android/gms/internal/measurement/zzgf:zzawu	Ljava/lang/Long;
    //   4127: invokevirtual 445	java/lang/Long:longValue	()J
    //   4130: lload 11
    //   4132: invokevirtual 1146	com/google/android/gms/measurement/internal/zzz:zza	(JJ)Lcom/google/android/gms/measurement/internal/zzz;
    //   4135: invokeinterface 703 3 0
    //   4140: pop
    //   4141: iload 5
    //   4143: iconst_1
    //   4144: iadd
    //   4145: istore 4
    //   4147: goto +1358 -> 5505
    //   4150: aload 22
    //   4152: getfield 79	com/google/android/gms/measurement/internal/zzfa:zzadj	Lcom/google/android/gms/measurement/internal/zzbt;
    //   4155: invokevirtual 278	com/google/android/gms/measurement/internal/zzbt:zzgq	()Lcom/google/android/gms/measurement/internal/zzn;
    //   4158: aload 19
    //   4160: getfield 906	com/google/android/gms/measurement/internal/zzfa$zza:zzaua	Lcom/google/android/gms/internal/measurement/zzgi;
    //   4163: getfield 915	com/google/android/gms/internal/measurement/zzgi:zztt	Ljava/lang/String;
    //   4166: invokevirtual 1149	com/google/android/gms/measurement/internal/zzn:zzbh	(Ljava/lang/String;)Z
    //   4169: ifeq +52 -> 4221
    //   4172: aload 17
    //   4174: getfield 1152	com/google/android/gms/measurement/internal/zzz:zzaii	Ljava/lang/Long;
    //   4177: astore 27
    //   4179: aload 27
    //   4181: ifnull +15 -> 4196
    //   4184: aload 17
    //   4186: getfield 1152	com/google/android/gms/measurement/internal/zzz:zzaii	Ljava/lang/Long;
    //   4189: invokevirtual 445	java/lang/Long:longValue	()J
    //   4192: lstore_2
    //   4193: goto +1293 -> 5486
    //   4196: aload 22
    //   4198: getfield 79	com/google/android/gms/measurement/internal/zzfa:zzadj	Lcom/google/android/gms/measurement/internal/zzbt;
    //   4201: invokevirtual 294	com/google/android/gms/measurement/internal/zzbt:zzgm	()Lcom/google/android/gms/measurement/internal/zzfk;
    //   4204: pop
    //   4205: aload 25
    //   4207: getfield 1155	com/google/android/gms/internal/measurement/zzgf:zzawv	Ljava/lang/Long;
    //   4210: invokevirtual 445	java/lang/Long:longValue	()J
    //   4213: lload_2
    //   4214: invokestatic 1120	com/google/android/gms/measurement/internal/zzfk:zzc	(JJ)J
    //   4217: lstore_2
    //   4218: goto +1268 -> 5486
    //   4221: aload 17
    //   4223: getfield 1158	com/google/android/gms/measurement/internal/zzz:zzaih	J
    //   4226: lstore_2
    //   4227: aload 25
    //   4229: getfield 886	com/google/android/gms/internal/measurement/zzgf:zzawu	Ljava/lang/Long;
    //   4232: invokevirtual 445	java/lang/Long:longValue	()J
    //   4235: lload_2
    //   4236: lsub
    //   4237: invokestatic 1162	java/lang/Math:abs	(J)J
    //   4240: ldc2_w 1163
    //   4243: lcmp
    //   4244: iflt +1255 -> 5499
    //   4247: goto +1246 -> 5493
    //   4250: iload 8
    //   4252: ifeq +140 -> 4392
    //   4255: aload_0
    //   4256: invokevirtual 942	com/google/android/gms/measurement/internal/zzfa:zzjo	()Lcom/google/android/gms/measurement/internal/zzfg;
    //   4259: pop
    //   4260: aload 25
    //   4262: aload 25
    //   4264: getfield 958	com/google/android/gms/internal/measurement/zzgf:zzawt	[Lcom/google/android/gms/internal/measurement/zzgg;
    //   4267: ldc_w 1113
    //   4270: lconst_1
    //   4271: invokestatic 401	java/lang/Long:valueOf	(J)Ljava/lang/Long;
    //   4274: invokestatic 1107	com/google/android/gms/measurement/internal/zzfg:zza	([Lcom/google/android/gms/internal/measurement/zzgg;Ljava/lang/String;Ljava/lang/Object;)[Lcom/google/android/gms/internal/measurement/zzgg;
    //   4277: putfield 958	com/google/android/gms/internal/measurement/zzgf:zzawt	[Lcom/google/android/gms/internal/measurement/zzgg;
    //   4280: aload_0
    //   4281: invokevirtual 942	com/google/android/gms/measurement/internal/zzfa:zzjo	()Lcom/google/android/gms/measurement/internal/zzfg;
    //   4284: pop
    //   4285: aload 25
    //   4287: getfield 958	com/google/android/gms/internal/measurement/zzgf:zzawt	[Lcom/google/android/gms/internal/measurement/zzgg;
    //   4290: astore 22
    //   4292: iload 4
    //   4294: i2l
    //   4295: lstore_2
    //   4296: aload 25
    //   4298: aload 22
    //   4300: ldc_w 1104
    //   4303: lload_2
    //   4304: invokestatic 401	java/lang/Long:valueOf	(J)Ljava/lang/Long;
    //   4307: invokestatic 1107	com/google/android/gms/measurement/internal/zzfg:zza	([Lcom/google/android/gms/internal/measurement/zzgg;Ljava/lang/String;Ljava/lang/Object;)[Lcom/google/android/gms/internal/measurement/zzgg;
    //   4310: putfield 958	com/google/android/gms/internal/measurement/zzgf:zzawt	[Lcom/google/android/gms/internal/measurement/zzgg;
    //   4313: aload 24
    //   4315: iload 5
    //   4317: aload 25
    //   4319: aastore
    //   4320: aload 17
    //   4322: astore 22
    //   4324: aload 23
    //   4326: invokevirtual 751	java/lang/Boolean:booleanValue	()Z
    //   4329: ifeq +19 -> 4348
    //   4332: aload 17
    //   4334: aconst_null
    //   4335: lload_2
    //   4336: invokestatic 401	java/lang/Long:valueOf	(J)Ljava/lang/Long;
    //   4339: iconst_1
    //   4340: invokestatic 737	java/lang/Boolean:valueOf	(Z)Ljava/lang/Boolean;
    //   4343: invokevirtual 1138	com/google/android/gms/measurement/internal/zzz:zza	(Ljava/lang/Long;Ljava/lang/Long;Ljava/lang/Boolean;)Lcom/google/android/gms/measurement/internal/zzz;
    //   4346: astore 22
    //   4348: aload 25
    //   4350: getfield 883	com/google/android/gms/internal/measurement/zzgf:name	Ljava/lang/String;
    //   4353: astore 17
    //   4355: aload 22
    //   4357: aload 25
    //   4359: getfield 886	com/google/android/gms/internal/measurement/zzgf:zzawu	Ljava/lang/Long;
    //   4362: invokevirtual 445	java/lang/Long:longValue	()J
    //   4365: lload 11
    //   4367: invokevirtual 1146	com/google/android/gms/measurement/internal/zzz:zza	(JJ)Lcom/google/android/gms/measurement/internal/zzz;
    //   4370: astore 22
    //   4372: aload_1
    //   4373: aload 17
    //   4375: aload 22
    //   4377: invokeinterface 703 3 0
    //   4382: pop
    //   4383: iload 5
    //   4385: iconst_1
    //   4386: iadd
    //   4387: istore 4
    //   4389: goto +1116 -> 5505
    //   4392: aload_1
    //   4393: astore 22
    //   4395: aload 22
    //   4397: astore_1
    //   4398: iload 5
    //   4400: istore 4
    //   4402: aload 23
    //   4404: invokevirtual 751	java/lang/Boolean:booleanValue	()Z
    //   4407: ifeq +1098 -> 5505
    //   4410: aload 22
    //   4412: aload 25
    //   4414: getfield 883	com/google/android/gms/internal/measurement/zzgf:name	Ljava/lang/String;
    //   4417: aload 17
    //   4419: aload 26
    //   4421: aconst_null
    //   4422: aconst_null
    //   4423: invokevirtual 1138	com/google/android/gms/measurement/internal/zzz:zza	(Ljava/lang/Long;Ljava/lang/Long;Ljava/lang/Boolean;)Lcom/google/android/gms/measurement/internal/zzz;
    //   4426: invokeinterface 703 3 0
    //   4431: pop
    //   4432: aload 22
    //   4434: astore_1
    //   4435: iload 5
    //   4437: istore 4
    //   4439: goto +1066 -> 5505
    //   4442: iload 5
    //   4444: aload 18
    //   4446: getfield 912	com/google/android/gms/internal/measurement/zzgi:zzaxb	[Lcom/google/android/gms/internal/measurement/zzgf;
    //   4449: arraylength
    //   4450: if_icmpge +18 -> 4468
    //   4453: aload 18
    //   4455: aload 24
    //   4457: iload 5
    //   4459: invokestatic 970	java/util/Arrays:copyOf	([Ljava/lang/Object;I)[Ljava/lang/Object;
    //   4462: checkcast 1052	[Lcom/google/android/gms/internal/measurement/zzgf;
    //   4465: putfield 912	com/google/android/gms/internal/measurement/zzgi:zzaxb	[Lcom/google/android/gms/internal/measurement/zzgf;
    //   4468: aload_1
    //   4469: invokeinterface 1168 1 0
    //   4474: invokeinterface 1174 1 0
    //   4479: astore 20
    //   4481: aload 18
    //   4483: astore_1
    //   4484: aload 19
    //   4486: astore 17
    //   4488: aload 20
    //   4490: invokeinterface 1179 1 0
    //   4495: ifeq +33 -> 4528
    //   4498: aload 20
    //   4500: invokeinterface 1182 1 0
    //   4505: checkcast 1184	java/util/Map$Entry
    //   4508: astore_1
    //   4509: aload_0
    //   4510: invokevirtual 489	com/google/android/gms/measurement/internal/zzfa:zzjq	()Lcom/google/android/gms/measurement/internal/zzq;
    //   4513: aload_1
    //   4514: invokeinterface 1187 1 0
    //   4519: checkcast 1093	com/google/android/gms/measurement/internal/zzz
    //   4522: invokevirtual 1190	com/google/android/gms/measurement/internal/zzq:zza	(Lcom/google/android/gms/measurement/internal/zzz;)V
    //   4525: goto -44 -> 4481
    //   4528: aload_1
    //   4529: ldc2_w 1191
    //   4532: invokestatic 401	java/lang/Long:valueOf	(J)Ljava/lang/Long;
    //   4535: putfield 1195	com/google/android/gms/internal/measurement/zzgi:zzaxe	Ljava/lang/Long;
    //   4538: aload_1
    //   4539: ldc2_w 1196
    //   4542: invokestatic 401	java/lang/Long:valueOf	(J)Ljava/lang/Long;
    //   4545: putfield 1200	com/google/android/gms/internal/measurement/zzgi:zzaxf	Ljava/lang/Long;
    //   4548: iconst_0
    //   4549: istore 4
    //   4551: iload 4
    //   4553: aload_1
    //   4554: getfield 912	com/google/android/gms/internal/measurement/zzgi:zzaxb	[Lcom/google/android/gms/internal/measurement/zzgf;
    //   4557: arraylength
    //   4558: if_icmpge +71 -> 4629
    //   4561: aload_1
    //   4562: getfield 912	com/google/android/gms/internal/measurement/zzgi:zzaxb	[Lcom/google/android/gms/internal/measurement/zzgf;
    //   4565: iload 4
    //   4567: aaload
    //   4568: astore 18
    //   4570: aload 18
    //   4572: getfield 886	com/google/android/gms/internal/measurement/zzgf:zzawu	Ljava/lang/Long;
    //   4575: invokevirtual 445	java/lang/Long:longValue	()J
    //   4578: aload_1
    //   4579: getfield 1195	com/google/android/gms/internal/measurement/zzgi:zzaxe	Ljava/lang/Long;
    //   4582: invokevirtual 445	java/lang/Long:longValue	()J
    //   4585: lcmp
    //   4586: ifge +12 -> 4598
    //   4589: aload_1
    //   4590: aload 18
    //   4592: getfield 886	com/google/android/gms/internal/measurement/zzgf:zzawu	Ljava/lang/Long;
    //   4595: putfield 1195	com/google/android/gms/internal/measurement/zzgi:zzaxe	Ljava/lang/Long;
    //   4598: aload 18
    //   4600: getfield 886	com/google/android/gms/internal/measurement/zzgf:zzawu	Ljava/lang/Long;
    //   4603: invokevirtual 445	java/lang/Long:longValue	()J
    //   4606: aload_1
    //   4607: getfield 1200	com/google/android/gms/internal/measurement/zzgi:zzaxf	Ljava/lang/Long;
    //   4610: invokevirtual 445	java/lang/Long:longValue	()J
    //   4613: lcmp
    //   4614: ifle +914 -> 5528
    //   4617: aload_1
    //   4618: aload 18
    //   4620: getfield 886	com/google/android/gms/internal/measurement/zzgf:zzawu	Ljava/lang/Long;
    //   4623: putfield 1200	com/google/android/gms/internal/measurement/zzgi:zzaxf	Ljava/lang/Long;
    //   4626: goto +902 -> 5528
    //   4629: aload 17
    //   4631: getfield 906	com/google/android/gms/measurement/internal/zzfa$zza:zzaua	Lcom/google/android/gms/internal/measurement/zzgi;
    //   4634: getfield 915	com/google/android/gms/internal/measurement/zzgi:zztt	Ljava/lang/String;
    //   4637: astore 19
    //   4639: aload_0
    //   4640: invokevirtual 489	com/google/android/gms/measurement/internal/zzfa:zzjq	()Lcom/google/android/gms/measurement/internal/zzq;
    //   4643: aload 19
    //   4645: invokevirtual 746	com/google/android/gms/measurement/internal/zzq:zzbl	(Ljava/lang/String;)Lcom/google/android/gms/measurement/internal/zzg;
    //   4648: astore 20
    //   4650: aload 20
    //   4652: ifnonnull +33 -> 4685
    //   4655: aload_0
    //   4656: getfield 79	com/google/android/gms/measurement/internal/zzfa:zzadj	Lcom/google/android/gms/measurement/internal/zzbt;
    //   4659: invokevirtual 150	com/google/android/gms/measurement/internal/zzbt:zzgo	()Lcom/google/android/gms/measurement/internal/zzap;
    //   4662: invokevirtual 181	com/google/android/gms/measurement/internal/zzap:zzjd	()Lcom/google/android/gms/measurement/internal/zzar;
    //   4665: ldc_w 1202
    //   4668: aload 17
    //   4670: getfield 906	com/google/android/gms/measurement/internal/zzfa$zza:zzaua	Lcom/google/android/gms/internal/measurement/zzgi;
    //   4673: getfield 915	com/google/android/gms/internal/measurement/zzgi:zztt	Ljava/lang/String;
    //   4676: invokestatic 220	com/google/android/gms/measurement/internal/zzap:zzbv	(Ljava/lang/String;)Ljava/lang/Object;
    //   4679: invokevirtual 170	com/google/android/gms/measurement/internal/zzar:zzg	(Ljava/lang/String;Ljava/lang/Object;)V
    //   4682: goto +136 -> 4818
    //   4685: aload_1
    //   4686: getfield 912	com/google/android/gms/internal/measurement/zzgi:zzaxb	[Lcom/google/android/gms/internal/measurement/zzgf;
    //   4689: arraylength
    //   4690: ifle +128 -> 4818
    //   4693: aload 20
    //   4695: invokevirtual 1205	com/google/android/gms/measurement/internal/zzg:zzgz	()J
    //   4698: lstore_2
    //   4699: lload_2
    //   4700: lconst_0
    //   4701: lcmp
    //   4702: ifeq +835 -> 5537
    //   4705: lload_2
    //   4706: invokestatic 401	java/lang/Long:valueOf	(J)Ljava/lang/Long;
    //   4709: astore 18
    //   4711: goto +3 -> 4714
    //   4714: aload_1
    //   4715: aload 18
    //   4717: putfield 1208	com/google/android/gms/internal/measurement/zzgi:zzaxh	Ljava/lang/Long;
    //   4720: aload 20
    //   4722: invokevirtual 1211	com/google/android/gms/measurement/internal/zzg:zzgy	()J
    //   4725: lstore 11
    //   4727: lload 11
    //   4729: lconst_0
    //   4730: lcmp
    //   4731: ifne +812 -> 5543
    //   4734: goto +3 -> 4737
    //   4737: lload_2
    //   4738: lconst_0
    //   4739: lcmp
    //   4740: ifeq +809 -> 5549
    //   4743: lload_2
    //   4744: invokestatic 401	java/lang/Long:valueOf	(J)Ljava/lang/Long;
    //   4747: astore 18
    //   4749: goto +3 -> 4752
    //   4752: aload_1
    //   4753: aload 18
    //   4755: putfield 1214	com/google/android/gms/internal/measurement/zzgi:zzaxg	Ljava/lang/Long;
    //   4758: aload 20
    //   4760: invokevirtual 1217	com/google/android/gms/measurement/internal/zzg:zzhh	()V
    //   4763: aload_1
    //   4764: aload 20
    //   4766: invokevirtual 1220	com/google/android/gms/measurement/internal/zzg:zzhe	()J
    //   4769: l2i
    //   4770: invokestatic 164	java/lang/Integer:valueOf	(I)Ljava/lang/Integer;
    //   4773: putfield 1224	com/google/android/gms/internal/measurement/zzgi:zzaxr	Ljava/lang/Integer;
    //   4776: aload 20
    //   4778: aload_1
    //   4779: getfield 1195	com/google/android/gms/internal/measurement/zzgi:zzaxe	Ljava/lang/Long;
    //   4782: invokevirtual 445	java/lang/Long:longValue	()J
    //   4785: invokevirtual 1228	com/google/android/gms/measurement/internal/zzg:zzs	(J)V
    //   4788: aload 20
    //   4790: aload_1
    //   4791: getfield 1200	com/google/android/gms/internal/measurement/zzgi:zzaxf	Ljava/lang/Long;
    //   4794: invokevirtual 445	java/lang/Long:longValue	()J
    //   4797: invokevirtual 1231	com/google/android/gms/measurement/internal/zzg:zzt	(J)V
    //   4800: aload_1
    //   4801: aload 20
    //   4803: invokevirtual 1234	com/google/android/gms/measurement/internal/zzg:zzhp	()Ljava/lang/String;
    //   4806: putfield 1237	com/google/android/gms/internal/measurement/zzgi:zzagv	Ljava/lang/String;
    //   4809: aload_0
    //   4810: invokevirtual 489	com/google/android/gms/measurement/internal/zzfa:zzjq	()Lcom/google/android/gms/measurement/internal/zzq;
    //   4813: aload 20
    //   4815: invokevirtual 1239	com/google/android/gms/measurement/internal/zzq:zza	(Lcom/google/android/gms/measurement/internal/zzg;)V
    //   4818: aload_0
    //   4819: astore 18
    //   4821: aload_1
    //   4822: getfield 912	com/google/android/gms/internal/measurement/zzgi:zzaxb	[Lcom/google/android/gms/internal/measurement/zzgf;
    //   4825: arraylength
    //   4826: ifle +123 -> 4949
    //   4829: aload 18
    //   4831: getfield 79	com/google/android/gms/measurement/internal/zzfa:zzadj	Lcom/google/android/gms/measurement/internal/zzbt;
    //   4834: invokevirtual 274	com/google/android/gms/measurement/internal/zzbt:zzgr	()Lcom/google/android/gms/measurement/internal/zzk;
    //   4837: pop
    //   4838: aload_0
    //   4839: invokespecial 685	com/google/android/gms/measurement/internal/zzfa:zzln	()Lcom/google/android/gms/measurement/internal/zzbn;
    //   4842: aload 17
    //   4844: getfield 906	com/google/android/gms/measurement/internal/zzfa$zza:zzaua	Lcom/google/android/gms/internal/measurement/zzgi;
    //   4847: getfield 915	com/google/android/gms/internal/measurement/zzgi:zztt	Ljava/lang/String;
    //   4850: invokevirtual 689	com/google/android/gms/measurement/internal/zzbn:zzcf	(Ljava/lang/String;)Lcom/google/android/gms/internal/measurement/zzgb;
    //   4853: astore 20
    //   4855: aload 20
    //   4857: ifnull +26 -> 4883
    //   4860: aload 20
    //   4862: getfield 1244	com/google/android/gms/internal/measurement/zzgb:zzawe	Ljava/lang/Long;
    //   4865: ifnonnull +6 -> 4871
    //   4868: goto +15 -> 4883
    //   4871: aload_1
    //   4872: aload 20
    //   4874: getfield 1244	com/google/android/gms/internal/measurement/zzgb:zzawe	Ljava/lang/Long;
    //   4877: putfield 1247	com/google/android/gms/internal/measurement/zzgi:zzaxy	Ljava/lang/Long;
    //   4880: goto +58 -> 4938
    //   4883: aload 17
    //   4885: getfield 906	com/google/android/gms/measurement/internal/zzfa$zza:zzaua	Lcom/google/android/gms/internal/measurement/zzgi;
    //   4888: getfield 1250	com/google/android/gms/internal/measurement/zzgi:zzafx	Ljava/lang/String;
    //   4891: invokestatic 254	android/text/TextUtils:isEmpty	(Ljava/lang/CharSequence;)Z
    //   4894: ifeq +16 -> 4910
    //   4897: aload_1
    //   4898: ldc2_w 80
    //   4901: invokestatic 401	java/lang/Long:valueOf	(J)Ljava/lang/Long;
    //   4904: putfield 1247	com/google/android/gms/internal/measurement/zzgi:zzaxy	Ljava/lang/Long;
    //   4907: goto +31 -> 4938
    //   4910: aload 18
    //   4912: getfield 79	com/google/android/gms/measurement/internal/zzfa:zzadj	Lcom/google/android/gms/measurement/internal/zzbt;
    //   4915: invokevirtual 150	com/google/android/gms/measurement/internal/zzbt:zzgo	()Lcom/google/android/gms/measurement/internal/zzap;
    //   4918: invokevirtual 156	com/google/android/gms/measurement/internal/zzap:zzjg	()Lcom/google/android/gms/measurement/internal/zzar;
    //   4921: ldc_w 1252
    //   4924: aload 17
    //   4926: getfield 906	com/google/android/gms/measurement/internal/zzfa$zza:zzaua	Lcom/google/android/gms/internal/measurement/zzgi;
    //   4929: getfield 915	com/google/android/gms/internal/measurement/zzgi:zztt	Ljava/lang/String;
    //   4932: invokestatic 220	com/google/android/gms/measurement/internal/zzap:zzbv	(Ljava/lang/String;)Ljava/lang/Object;
    //   4935: invokevirtual 170	com/google/android/gms/measurement/internal/zzar:zzg	(Ljava/lang/String;Ljava/lang/Object;)V
    //   4938: aload_0
    //   4939: invokevirtual 489	com/google/android/gms/measurement/internal/zzfa:zzjq	()Lcom/google/android/gms/measurement/internal/zzq;
    //   4942: aload_1
    //   4943: iload 13
    //   4945: invokevirtual 1255	com/google/android/gms/measurement/internal/zzq:zza	(Lcom/google/android/gms/internal/measurement/zzgi;Z)Z
    //   4948: pop
    //   4949: aload_0
    //   4950: invokevirtual 489	com/google/android/gms/measurement/internal/zzfa:zzjq	()Lcom/google/android/gms/measurement/internal/zzq;
    //   4953: astore_1
    //   4954: aload 17
    //   4956: getfield 1258	com/google/android/gms/measurement/internal/zzfa$zza:zzaub	Ljava/util/List;
    //   4959: astore 17
    //   4961: aload 17
    //   4963: invokestatic 66	com/google/android/gms/common/internal/Preconditions:checkNotNull	(Ljava/lang/Object;)Ljava/lang/Object;
    //   4966: pop
    //   4967: aload_1
    //   4968: invokevirtual 346	com/google/android/gms/measurement/internal/zzco:zzaf	()V
    //   4971: aload_1
    //   4972: invokevirtual 528	com/google/android/gms/measurement/internal/zzez:zzcl	()V
    //   4975: new 322	java/lang/StringBuilder
    //   4978: dup
    //   4979: ldc_w 1260
    //   4982: invokespecial 1261	java/lang/StringBuilder:<init>	(Ljava/lang/String;)V
    //   4985: astore 18
    //   4987: iconst_0
    //   4988: istore 4
    //   4990: iload 4
    //   4992: aload 17
    //   4994: invokeinterface 908 1 0
    //   4999: if_icmpge +47 -> 5046
    //   5002: iload 4
    //   5004: ifeq +12 -> 5016
    //   5007: aload 18
    //   5009: ldc_w 1263
    //   5012: invokevirtual 334	java/lang/StringBuilder:append	(Ljava/lang/String;)Ljava/lang/StringBuilder;
    //   5015: pop
    //   5016: aload 18
    //   5018: aload 17
    //   5020: iload 4
    //   5022: invokeinterface 921 2 0
    //   5027: checkcast 398	java/lang/Long
    //   5030: invokevirtual 445	java/lang/Long:longValue	()J
    //   5033: invokevirtual 1266	java/lang/StringBuilder:append	(J)Ljava/lang/StringBuilder;
    //   5036: pop
    //   5037: iload 4
    //   5039: iconst_1
    //   5040: iadd
    //   5041: istore 4
    //   5043: goto -53 -> 4990
    //   5046: aload 18
    //   5048: ldc_w 1268
    //   5051: invokevirtual 334	java/lang/StringBuilder:append	(Ljava/lang/String;)Ljava/lang/StringBuilder;
    //   5054: pop
    //   5055: aload_1
    //   5056: invokevirtual 532	com/google/android/gms/measurement/internal/zzq:getWritableDatabase	()Landroid/database/sqlite/SQLiteDatabase;
    //   5059: ldc_w 869
    //   5062: aload 18
    //   5064: invokevirtual 337	java/lang/StringBuilder:toString	()Ljava/lang/String;
    //   5067: aconst_null
    //   5068: invokevirtual 1272	android/database/sqlite/SQLiteDatabase:delete	(Ljava/lang/String;Ljava/lang/String;[Ljava/lang/String;)I
    //   5071: istore 4
    //   5073: iload 4
    //   5075: aload 17
    //   5077: invokeinterface 908 1 0
    //   5082: if_icmpeq +31 -> 5113
    //   5085: aload_1
    //   5086: invokevirtual 544	com/google/android/gms/measurement/internal/zzco:zzgo	()Lcom/google/android/gms/measurement/internal/zzap;
    //   5089: invokevirtual 181	com/google/android/gms/measurement/internal/zzap:zzjd	()Lcom/google/android/gms/measurement/internal/zzar;
    //   5092: ldc_w 1274
    //   5095: iload 4
    //   5097: invokestatic 164	java/lang/Integer:valueOf	(I)Ljava/lang/Integer;
    //   5100: aload 17
    //   5102: invokeinterface 908 1 0
    //   5107: invokestatic 164	java/lang/Integer:valueOf	(I)Ljava/lang/Integer;
    //   5110: invokevirtual 309	com/google/android/gms/measurement/internal/zzar:zze	(Ljava/lang/String;Ljava/lang/Object;Ljava/lang/Object;)V
    //   5113: aload_0
    //   5114: invokevirtual 489	com/google/android/gms/measurement/internal/zzfa:zzjq	()Lcom/google/android/gms/measurement/internal/zzq;
    //   5117: astore_1
    //   5118: aload_1
    //   5119: invokevirtual 532	com/google/android/gms/measurement/internal/zzq:getWritableDatabase	()Landroid/database/sqlite/SQLiteDatabase;
    //   5122: astore 17
    //   5124: aload 17
    //   5126: ldc_w 1276
    //   5129: iconst_2
    //   5130: anewarray 226	java/lang/String
    //   5133: dup
    //   5134: iconst_0
    //   5135: aload 19
    //   5137: aastore
    //   5138: dup
    //   5139: iconst_1
    //   5140: aload 19
    //   5142: aastore
    //   5143: invokevirtual 543	android/database/sqlite/SQLiteDatabase:execSQL	(Ljava/lang/String;[Ljava/lang/Object;)V
    //   5146: goto +25 -> 5171
    //   5149: astore 17
    //   5151: aload_1
    //   5152: invokevirtual 544	com/google/android/gms/measurement/internal/zzco:zzgo	()Lcom/google/android/gms/measurement/internal/zzap;
    //   5155: invokevirtual 181	com/google/android/gms/measurement/internal/zzap:zzjd	()Lcom/google/android/gms/measurement/internal/zzar;
    //   5158: ldc_w 1278
    //   5161: aload 19
    //   5163: invokestatic 220	com/google/android/gms/measurement/internal/zzap:zzbv	(Ljava/lang/String;)Ljava/lang/Object;
    //   5166: aload 17
    //   5168: invokevirtual 309	com/google/android/gms/measurement/internal/zzar:zze	(Ljava/lang/String;Ljava/lang/Object;Ljava/lang/Object;)V
    //   5171: aload_0
    //   5172: invokevirtual 489	com/google/android/gms/measurement/internal/zzfa:zzjq	()Lcom/google/android/gms/measurement/internal/zzq;
    //   5175: invokevirtual 1281	com/google/android/gms/measurement/internal/zzq:setTransactionSuccessful	()V
    //   5178: aload_0
    //   5179: invokevirtual 489	com/google/android/gms/measurement/internal/zzfa:zzjq	()Lcom/google/android/gms/measurement/internal/zzq;
    //   5182: invokevirtual 1284	com/google/android/gms/measurement/internal/zzq:endTransaction	()V
    //   5185: iconst_1
    //   5186: ireturn
    //   5187: astore_1
    //   5188: goto +42 -> 5230
    //   5191: aload_0
    //   5192: invokevirtual 489	com/google/android/gms/measurement/internal/zzfa:zzjq	()Lcom/google/android/gms/measurement/internal/zzq;
    //   5195: invokevirtual 1281	com/google/android/gms/measurement/internal/zzq:setTransactionSuccessful	()V
    //   5198: aload_0
    //   5199: invokevirtual 489	com/google/android/gms/measurement/internal/zzfa:zzjq	()Lcom/google/android/gms/measurement/internal/zzq;
    //   5202: invokevirtual 1284	com/google/android/gms/measurement/internal/zzq:endTransaction	()V
    //   5205: iconst_0
    //   5206: ireturn
    //   5207: astore_1
    //   5208: goto -4022 -> 1186
    //   5211: aload 17
    //   5213: ifnull +10 -> 5223
    //   5216: aload 17
    //   5218: invokeinterface 815 1 0
    //   5223: aload_1
    //   5224: athrow
    //   5225: astore_1
    //   5226: goto +4 -> 5230
    //   5229: astore_1
    //   5230: aload_0
    //   5231: invokevirtual 489	com/google/android/gms/measurement/internal/zzfa:zzjq	()Lcom/google/android/gms/measurement/internal/zzq;
    //   5234: invokevirtual 1284	com/google/android/gms/measurement/internal/zzq:endTransaction	()V
    //   5237: goto +5 -> 5242
    //   5240: aload_1
    //   5241: athrow
    //   5242: goto -2 -> 5240
    //   5245: lload 11
    //   5247: ldc2_w 80
    //   5250: lcmp
    //   5251: ifeq -4879 -> 372
    //   5254: ldc_w 1286
    //   5257: astore 17
    //   5259: goto -4887 -> 372
    //   5262: iconst_0
    //   5263: istore 4
    //   5265: goto -4009 -> 1256
    //   5268: iconst_1
    //   5269: istore 4
    //   5271: goto -4015 -> 1256
    //   5274: iconst_0
    //   5275: istore 4
    //   5277: goto -3816 -> 1461
    //   5280: iconst_1
    //   5281: istore 4
    //   5283: goto -3822 -> 1461
    //   5286: goto +143 -> 5429
    //   5289: iconst_m1
    //   5290: istore 4
    //   5292: iload 4
    //   5294: ifeq +21 -> 5315
    //   5297: iload 4
    //   5299: iconst_1
    //   5300: if_icmpeq +15 -> 5315
    //   5303: iload 4
    //   5305: iconst_2
    //   5306: if_icmpeq +9 -> 5315
    //   5309: iconst_0
    //   5310: istore 4
    //   5312: goto +6 -> 5318
    //   5315: iconst_1
    //   5316: istore 4
    //   5318: iload 4
    //   5320: ifeq +6 -> 5326
    //   5323: goto -3686 -> 1637
    //   5326: iload 13
    //   5328: istore 14
    //   5330: goto -2927 -> 2403
    //   5333: iload 7
    //   5335: iconst_1
    //   5336: iadd
    //   5337: istore 7
    //   5339: iload 10
    //   5341: istore 8
    //   5343: goto -3670 -> 1673
    //   5346: goto -3488 -> 1858
    //   5349: iload 4
    //   5351: iconst_1
    //   5352: iadd
    //   5353: istore 4
    //   5355: goto -3345 -> 2010
    //   5358: goto -3251 -> 2107
    //   5361: iconst_1
    //   5362: istore 13
    //   5364: goto -3257 -> 2107
    //   5367: iload 4
    //   5369: iconst_1
    //   5370: iadd
    //   5371: istore 4
    //   5373: aload 21
    //   5375: astore 20
    //   5377: goto -3141 -> 2236
    //   5380: iload 4
    //   5382: iconst_1
    //   5383: iadd
    //   5384: istore 4
    //   5386: iload 8
    //   5388: istore 5
    //   5390: goto -2937 -> 2453
    //   5393: goto -2691 -> 2702
    //   5396: iload 7
    //   5398: iconst_m1
    //   5399: if_icmpne -2809 -> 2590
    //   5402: iconst_1
    //   5403: istore 4
    //   5405: goto -2750 -> 2655
    //   5408: iconst_0
    //   5409: istore 4
    //   5411: goto -2797 -> 2614
    //   5414: iconst_0
    //   5415: istore 4
    //   5417: goto -2762 -> 2655
    //   5420: iconst_1
    //   5421: istore 4
    //   5423: goto -2768 -> 2655
    //   5426: goto -2715 -> 2711
    //   5429: iload 6
    //   5431: iconst_1
    //   5432: iadd
    //   5433: istore 6
    //   5435: goto -4116 -> 1319
    //   5438: iload 4
    //   5440: iconst_1
    //   5441: iadd
    //   5442: istore 4
    //   5444: goto -2361 -> 3083
    //   5447: iconst_0
    //   5448: istore 4
    //   5450: goto -2321 -> 3129
    //   5453: iconst_1
    //   5454: istore 4
    //   5456: goto -1748 -> 3708
    //   5459: iload 8
    //   5461: iconst_1
    //   5462: iadd
    //   5463: istore 8
    //   5465: goto -1851 -> 3614
    //   5468: iconst_0
    //   5469: istore 4
    //   5471: goto -1763 -> 3708
    //   5474: iconst_1
    //   5475: istore 4
    //   5477: goto -1739 -> 3738
    //   5480: iconst_0
    //   5481: istore 14
    //   5483: goto -1545 -> 3938
    //   5486: lload_2
    //   5487: lload 11
    //   5489: lcmp
    //   5490: ifeq +9 -> 5499
    //   5493: iconst_1
    //   5494: istore 8
    //   5496: goto -1246 -> 4250
    //   5499: iconst_0
    //   5500: istore 8
    //   5502: goto -1252 -> 4250
    //   5505: iload 7
    //   5507: iconst_1
    //   5508: iadd
    //   5509: istore 7
    //   5511: iload 4
    //   5513: istore 5
    //   5515: goto -2201 -> 3314
    //   5518: aload 19
    //   5520: astore 17
    //   5522: aload 18
    //   5524: astore_1
    //   5525: goto -997 -> 4528
    //   5528: iload 4
    //   5530: iconst_1
    //   5531: iadd
    //   5532: istore 4
    //   5534: goto -983 -> 4551
    //   5537: aconst_null
    //   5538: astore 18
    //   5540: goto -826 -> 4714
    //   5543: lload 11
    //   5545: lstore_2
    //   5546: goto -809 -> 4737
    //   5549: aconst_null
    //   5550: astore 18
    //   5552: goto -800 -> 4752
    // Local variable table:
    //   start	length	slot	name	signature
    //   0	5555	0	this	zzfa
    //   0	5555	1	paramString	String
    //   0	5555	2	paramLong	long
    //   1256	4277	4	i	int
    //   1308	4206	5	j	int
    //   1305	4129	6	k	int
    //   1665	3845	7	m	int
    //   1668	3833	8	n	int
    //   1671	1196	9	i1	int
    //   1710	3630	10	i2	int
    //   41	5503	11	l	long
    //   70	5293	13	bool1	boolean
    //   1371	4111	14	bool2	boolean
    //   1302	1610	15	bool3	boolean
    //   1533	900	16	bool4	boolean
    //   74	905	17	localObject1	Object
    //   1045	18	17	localIOException1	IOException
    //   1099	4026	17	localObject2	Object
    //   5149	68	17	localSQLiteException1	SQLiteException
    //   5257	264	17	localObject3	Object
    //   16	96	18	localObject4	Object
    //   128	6	18	localObject5	Object
    //   145	5406	18	localObject6	Object
    //   28	5491	19	localObject7	Object
    //   97	1058	20	localObject8	Object
    //   1164	6	20	localSQLiteException2	SQLiteException
    //   1191	4185	20	localObject9	Object
    //   301	579	21	localObject10	Object
    //   1104	10	21	localSQLiteException3	SQLiteException
    //   1119	26	21	localIOException2	IOException
    //   2265	3109	21	localObject11	Object
    //   620	3813	22	localObject12	Object
    //   1	4402	23	localObject13	Object
    //   6	4450	24	localObject14	Object
    //   656	3757	25	localObject15	Object
    //   34	4386	26	localObject16	Object
    //   64	4116	27	localObject17	Object
    // Exception table:
    //   from	to	target	type
    //   93	99	128	finally
    //   102	111	128	finally
    //   114	122	128	finally
    //   244	253	128	finally
    //   280	290	128	finally
    //   293	303	128	finally
    //   306	313	128	finally
    //   435	444	128	finally
    //   471	481	128	finally
    //   488	495	128	finally
    //   93	99	139	android/database/sqlite/SQLiteException
    //   102	111	139	android/database/sqlite/SQLiteException
    //   114	122	139	android/database/sqlite/SQLiteException
    //   293	303	319	android/database/sqlite/SQLiteException
    //   306	313	319	android/database/sqlite/SQLiteException
    //   976	984	1045	java/io/IOException
    //   894	922	1096	finally
    //   937	976	1096	finally
    //   976	984	1096	finally
    //   984	1025	1096	finally
    //   1047	1067	1096	finally
    //   1067	1076	1096	finally
    //   894	922	1104	android/database/sqlite/SQLiteException
    //   937	976	1104	android/database/sqlite/SQLiteException
    //   976	984	1104	android/database/sqlite/SQLiteException
    //   984	1025	1104	android/database/sqlite/SQLiteException
    //   1047	1067	1104	android/database/sqlite/SQLiteException
    //   1067	1076	1104	android/database/sqlite/SQLiteException
    //   666	674	1119	java/io/IOException
    //   501	545	1164	android/database/sqlite/SQLiteException
    //   553	563	1164	android/database/sqlite/SQLiteException
    //   571	589	1164	android/database/sqlite/SQLiteException
    //   612	622	1164	android/database/sqlite/SQLiteException
    //   630	641	1164	android/database/sqlite/SQLiteException
    //   649	658	1164	android/database/sqlite/SQLiteException
    //   666	674	1164	android/database/sqlite/SQLiteException
    //   682	692	1164	android/database/sqlite/SQLiteException
    //   700	718	1164	android/database/sqlite/SQLiteException
    //   726	733	1164	android/database/sqlite/SQLiteException
    //   741	750	1164	android/database/sqlite/SQLiteException
    //   772	795	1164	android/database/sqlite/SQLiteException
    //   819	834	1164	android/database/sqlite/SQLiteException
    //   846	894	1164	android/database/sqlite/SQLiteException
    //   1129	1149	1164	android/database/sqlite/SQLiteException
    //   244	253	1175	android/database/sqlite/SQLiteException
    //   280	290	1175	android/database/sqlite/SQLiteException
    //   435	444	1175	android/database/sqlite/SQLiteException
    //   471	481	1175	android/database/sqlite/SQLiteException
    //   488	495	1175	android/database/sqlite/SQLiteException
    //   59	72	1182	finally
    //   154	166	1182	finally
    //   180	237	1182	finally
    //   340	345	1182	finally
    //   349	357	1182	finally
    //   360	365	1182	finally
    //   372	428	1182	finally
    //   59	72	1189	android/database/sqlite/SQLiteException
    //   154	166	1189	android/database/sqlite/SQLiteException
    //   180	237	1189	android/database/sqlite/SQLiteException
    //   340	345	1189	android/database/sqlite/SQLiteException
    //   349	357	1189	android/database/sqlite/SQLiteException
    //   360	365	1189	android/database/sqlite/SQLiteException
    //   372	428	1189	android/database/sqlite/SQLiteException
    //   5124	5146	5149	android/database/sqlite/SQLiteException
    //   3264	3308	5187	finally
    //   3331	3344	5187	finally
    //   3533	3586	5187	finally
    //   3786	3802	5187	finally
    //   3909	3927	5187	finally
    //   3938	3945	5187	finally
    //   4035	4044	5187	finally
    //   4150	4179	5187	finally
    //   4196	4218	5187	finally
    //   4221	4247	5187	finally
    //   4255	4292	5187	finally
    //   4296	4313	5187	finally
    //   4324	4348	5187	finally
    //   4348	4372	5187	finally
    //   4372	4383	5187	finally
    //   4402	4432	5187	finally
    //   4442	4468	5187	finally
    //   4468	4481	5187	finally
    //   4488	4525	5187	finally
    //   4528	4548	5187	finally
    //   4551	4598	5187	finally
    //   4598	4626	5187	finally
    //   4629	4650	5187	finally
    //   501	545	5207	finally
    //   553	563	5207	finally
    //   571	589	5207	finally
    //   612	622	5207	finally
    //   630	641	5207	finally
    //   649	658	5207	finally
    //   666	674	5207	finally
    //   682	692	5207	finally
    //   700	718	5207	finally
    //   726	733	5207	finally
    //   741	750	5207	finally
    //   772	795	5207	finally
    //   819	834	5207	finally
    //   846	894	5207	finally
    //   1129	1149	5207	finally
    //   1200	1220	5207	finally
    //   4655	4682	5225	finally
    //   4685	4699	5225	finally
    //   4705	4711	5225	finally
    //   4714	4727	5225	finally
    //   4743	4749	5225	finally
    //   4752	4818	5225	finally
    //   4821	4855	5225	finally
    //   4860	4868	5225	finally
    //   4871	4880	5225	finally
    //   4883	4907	5225	finally
    //   4910	4938	5225	finally
    //   4938	4949	5225	finally
    //   4949	4987	5225	finally
    //   4990	5002	5225	finally
    //   5007	5016	5225	finally
    //   5016	5037	5225	finally
    //   5046	5113	5225	finally
    //   5113	5124	5225	finally
    //   5124	5146	5225	finally
    //   5151	5171	5225	finally
    //   5171	5178	5225	finally
    //   5191	5198	5225	finally
    //   5216	5223	5225	finally
    //   5223	5225	5225	finally
    //   18	59	5229	finally
    //   263	270	5229	finally
    //   454	461	5229	finally
    //   594	601	5229	finally
    //   927	934	5229	finally
    //   1035	1042	5229	finally
    //   1086	1093	5229	finally
    //   1154	1161	5229	finally
    //   1225	1232	5229	finally
    //   1232	1253	5229	finally
    //   1261	1304	5229	finally
    //   1319	1373	5229	finally
    //   1378	1458	5229	finally
    //   1466	1510	5229	finally
    //   1513	1535	5229	finally
    //   1540	1562	5229	finally
    //   1589	1599	5229	finally
    //   1605	1615	5229	finally
    //   1621	1631	5229	finally
    //   1637	1654	5229	finally
    //   1654	1664	5229	finally
    //   1686	1709	5229	finally
    //   1719	1742	5229	finally
    //   1762	1855	5229	finally
    //   1863	1956	5229	finally
    //   1956	2007	5229	finally
    //   2010	2053	5229	finally
    //   2058	2071	5229	finally
    //   2071	2098	5229	finally
    //   2098	2104	5229	finally
    //   2111	2122	5229	finally
    //   2135	2227	5229	finally
    //   2249	2263	5229	finally
    //   2274	2288	5229	finally
    //   2308	2333	5229	finally
    //   2345	2364	5229	finally
    //   2371	2399	5229	finally
    //   2410	2432	5229	finally
    //   2437	2444	5229	finally
    //   2453	2478	5229	finally
    //   2489	2506	5229	finally
    //   2526	2587	5229	finally
    //   2590	2599	5229	finally
    //   2603	2611	5229	finally
    //   2614	2639	5229	finally
    //   2642	2652	5229	finally
    //   2663	2702	5229	finally
    //   2702	2708	5229	finally
    //   2722	2753	5229	finally
    //   2756	2773	5229	finally
    //   2777	2805	5229	finally
    //   2811	2819	5229	finally
    //   2822	2850	5229	finally
    //   2853	2859	5229	finally
    //   2878	2911	5229	finally
    //   2916	2931	5229	finally
    //   2935	2942	5229	finally
    //   2945	2992	5229	finally
    //   2995	3031	5229	finally
    //   3031	3080	5229	finally
    //   3083	3123	5229	finally
    //   3134	3177	5229	finally
    //   3183	3213	5229	finally
    //   3213	3259	5229	finally
    //   3349	3380	5229	finally
    //   3389	3419	5229	finally
    //   3419	3466	5229	finally
    //   3466	3510	5229	finally
    //   3599	3611	5229	finally
    //   3628	3663	5229	finally
    //   3663	3684	5229	finally
    //   3684	3705	5229	finally
    //   3713	3735	5229	finally
    //   3743	3770	5229	finally
    //   3811	3833	5229	finally
    //   3842	3909	5229	finally
    //   3968	3992	5229	finally
    //   3996	4004	5229	finally
    //   4004	4028	5229	finally
    //   4049	4061	5229	finally
    //   4065	4082	5229	finally
    //   4093	4114	5229	finally
    //   4114	4141	5229	finally
    //   4184	4193	5229	finally
  }
  
  private final zzg zzg(zzh paramZzh)
  {
    zzaf();
    zzlr();
    Preconditions.checkNotNull(paramZzh);
    Preconditions.checkNotEmpty(packageName);
    zzg localZzg = zzjq().zzbl(packageName);
    String str = zzadj.zzgp().zzbz(packageName);
    if (localZzg == null)
    {
      localZzg = new zzg(zzadj, packageName);
      localZzg.zzam(zzadj.zzgm().zzmf());
      localZzg.zzap(str);
    }
    for (;;)
    {
      i = 1;
      break label139;
      if (str.equals(localZzg.zzgx())) {
        break;
      }
      localZzg.zzap(str);
      localZzg.zzam(zzadj.zzgm().zzmf());
    }
    int i = 0;
    label139:
    if (!TextUtils.equals(zzafx, localZzg.getGmpAppId()))
    {
      localZzg.zzan(zzafx);
      i = 1;
    }
    int j = i;
    if (!TextUtils.equals(zzagk, localZzg.zzgw()))
    {
      localZzg.zzao(zzagk);
      j = 1;
    }
    i = j;
    if (!TextUtils.isEmpty(zzafz))
    {
      i = j;
      if (!zzafz.equals(localZzg.getFirebaseInstanceId()))
      {
        localZzg.zzaq(zzafz);
        i = 1;
      }
    }
    j = i;
    if (zzadt != 0L)
    {
      j = i;
      if (zzadt != localZzg.zzhc())
      {
        localZzg.zzv(zzadt);
        j = 1;
      }
    }
    i = j;
    if (!TextUtils.isEmpty(zzts))
    {
      i = j;
      if (!zzts.equals(localZzg.zzak()))
      {
        localZzg.setAppVersion(zzts);
        i = 1;
      }
    }
    if (zzagd != localZzg.zzha())
    {
      localZzg.zzu(zzagd);
      i = 1;
    }
    j = i;
    if (zzage != null)
    {
      j = i;
      if (!zzage.equals(localZzg.zzhb()))
      {
        localZzg.zzar(zzage);
        j = 1;
      }
    }
    i = j;
    if (zzagf != localZzg.zzhd())
    {
      localZzg.zzw(zzagf);
      i = 1;
    }
    if (zzagg != localZzg.isMeasurementEnabled())
    {
      localZzg.setMeasurementEnabled(zzagg);
      i = 1;
    }
    j = i;
    if (!TextUtils.isEmpty(zzagv))
    {
      j = i;
      if (!zzagv.equals(localZzg.zzho()))
      {
        localZzg.zzas(zzagv);
        j = 1;
      }
    }
    if (zzagh != localZzg.zzhq())
    {
      localZzg.zzag(zzagh);
      j = 1;
    }
    if (zzagi != localZzg.zzhr())
    {
      localZzg.zze(zzagi);
      j = 1;
    }
    if (zzagj != localZzg.zzhs())
    {
      localZzg.zzf(zzagj);
      j = 1;
    }
    if (j != 0) {
      zzjq().zza(localZzg);
    }
    return localZzg;
  }
  
  private final zzbn zzln()
  {
    zza(zzatd);
    return zzatd;
  }
  
  private final zzay zzlp()
  {
    zzay localZzay = zzatg;
    if (localZzay != null) {
      return localZzay;
    }
    throw new IllegalStateException("Network broadcast receiver not created");
  }
  
  private final zzew zzlq()
  {
    zza(zzath);
    return zzath;
  }
  
  private final long zzls()
  {
    long l3 = zzadj.zzbx().currentTimeMillis();
    zzba localZzba = zzadj.zzgp();
    localZzba.zzcl();
    localZzba.zzaf();
    long l2 = zzani.get();
    long l1 = l2;
    if (l2 == 0L)
    {
      l1 = 1L + localZzba.zzgm().zzmd().nextInt(86400000);
      zzani.set(l1);
    }
    return (l3 + l1) / 1000L / 60L / 60L / 24L;
  }
  
  private final boolean zzlu()
  {
    zzaf();
    zzlr();
    return (zzjq().zzii()) || (!TextUtils.isEmpty(zzjq().zzid()));
  }
  
  private final void zzlv()
  {
    zzaf();
    zzlr();
    if (!zzlz()) {
      return;
    }
    long l1;
    if (zzatl > 0L)
    {
      l1 = 3600000L - Math.abs(zzadj.zzbx().elapsedRealtime() - zzatl);
      if (l1 > 0L)
      {
        zzadj.zzgo().zzjl().zzg("Upload has been suspended. Will update scheduling later in approximately ms", Long.valueOf(l1));
        zzlp().unregister();
        zzlq().cancel();
        return;
      }
      zzatl = 0L;
    }
    if ((zzadj.zzkr()) && (zzlu()))
    {
      long l3 = zzadj.zzbx().currentTimeMillis();
      long l2 = Math.max(0L, ((Long)zzaf.zzakd.get()).longValue());
      int i;
      if ((!zzjq().zzij()) && (!zzjq().zzie())) {
        i = 0;
      } else {
        i = 1;
      }
      if (i != 0)
      {
        String str = zzadj.zzgq().zzhy();
        if ((!TextUtils.isEmpty(str)) && (!".none.".equals(str))) {
          l1 = Math.max(0L, ((Long)zzaf.zzajy.get()).longValue());
        } else {
          l1 = Math.max(0L, ((Long)zzaf.zzajx.get()).longValue());
        }
      }
      else
      {
        l1 = Math.max(0L, ((Long)zzaf.zzajw.get()).longValue());
      }
      long l6 = zzadj.zzgp().zzane.get();
      long l5 = zzadj.zzgp().zzanf.get();
      long l4 = Math.max(zzjq().zzig(), zzjq().zzih());
      if (l4 == 0L) {}
      for (;;)
      {
        l1 = 0L;
        break;
        l4 = l3 - Math.abs(l4 - l3);
        l6 = Math.abs(l6 - l3);
        l5 = l3 - Math.abs(l5 - l3);
        l6 = Math.max(l3 - l6, l5);
        l3 = l4 + l2;
        l2 = l3;
        if (i != 0)
        {
          l2 = l3;
          if (l6 > 0L) {
            l2 = Math.min(l4, l6) + l1;
          }
        }
        if (!zzjo().zzb(l6, l1)) {
          l2 = l6 + l1;
        }
        l1 = l2;
        if (l5 == 0L) {
          break;
        }
        l1 = l2;
        if (l5 < l4) {
          break;
        }
        i = 0;
        while (i < Math.min(20, Math.max(0, ((Integer)zzaf.zzakf.get()).intValue())))
        {
          l1 = l2 + Math.max(0L, ((Long)zzaf.zzake.get()).longValue()) * (1L << i);
          if (l1 > l5) {
            break label530;
          }
          i += 1;
          l2 = l1;
        }
      }
      label530:
      if (l1 == 0L)
      {
        zzadj.zzgo().zzjl().zzbx("Next upload time is 0");
        zzlp().unregister();
        zzlq().cancel();
        return;
      }
      if (!zzlo().zzfb())
      {
        zzadj.zzgo().zzjl().zzbx("No network");
        zzlp().zzey();
        zzlq().cancel();
        return;
      }
      l3 = zzadj.zzgp().zzang.get();
      l4 = Math.max(0L, ((Long)zzaf.zzaju.get()).longValue());
      l2 = l1;
      if (!zzjo().zzb(l3, l4)) {
        l2 = Math.max(l1, l3 + l4);
      }
      zzlp().unregister();
      l2 -= zzadj.zzbx().currentTimeMillis();
      l1 = l2;
      if (l2 <= 0L)
      {
        l1 = Math.max(0L, ((Long)zzaf.zzajz.get()).longValue());
        zzadj.zzgp().zzane.set(zzadj.zzbx().currentTimeMillis());
      }
      zzadj.zzgo().zzjl().zzg("Upload scheduled in approximately ms", Long.valueOf(l1));
      zzlq().zzh(l1);
      return;
    }
    zzadj.zzgo().zzjl().zzbx("Nothing to upload or uploading impossible");
    zzlp().unregister();
    zzlq().cancel();
  }
  
  private final void zzlw()
  {
    zzaf();
    if ((!zzatp) && (!zzatq) && (!zzatr))
    {
      zzadj.zzgo().zzjl().zzbx("Stopping uploading service(s)");
      Object localObject = zzatm;
      if (localObject == null) {
        return;
      }
      localObject = ((List)localObject).iterator();
      while (((Iterator)localObject).hasNext()) {
        ((Runnable)((Iterator)localObject).next()).run();
      }
      zzatm.clear();
      return;
    }
    zzadj.zzgo().zzjl().zzd("Not stopping services. fetch, network, upload", Boolean.valueOf(zzatp), Boolean.valueOf(zzatq), Boolean.valueOf(zzatr));
  }
  
  private final boolean zzlx()
  {
    zzaf();
    File localFile = new File(zzadj.getContext().getFilesDir(), "google_app_measurement.db");
    try
    {
      zzatt = new RandomAccessFile(localFile, "rw").getChannel();
      zzats = zzatt.tryLock();
      if (zzats != null)
      {
        zzadj.zzgo().zzjl().zzbx("Storage concurrent access okay");
        return true;
      }
      zzadj.zzgo().zzjd().zzbx("Storage concurrent data access panic");
    }
    catch (IOException localIOException)
    {
      zzadj.zzgo().zzjd().zzg("Failed to access storage lock file", localIOException);
    }
    catch (FileNotFoundException localFileNotFoundException)
    {
      zzadj.zzgo().zzjd().zzg("Failed to acquire storage lock", localFileNotFoundException);
    }
    return false;
  }
  
  private final boolean zzlz()
  {
    zzaf();
    zzlr();
    return zzatk;
  }
  
  public static zzfa zzm(Context paramContext)
  {
    Preconditions.checkNotNull(paramContext);
    Preconditions.checkNotNull(paramContext.getApplicationContext());
    if (zzatc == null) {
      try
      {
        if (zzatc == null) {
          zzatc = new zzfa(new zzff(paramContext));
        }
      }
      finally {}
    }
    return zzatc;
  }
  
  public final Context getContext()
  {
    return zzadj.getContext();
  }
  
  protected final void start()
  {
    zzadj.zzgn().zzaf();
    zzjq().zzif();
    if (zzadj.zzgp().zzane.get() == 0L) {
      zzadj.zzgp().zzane.set(zzadj.zzbx().currentTimeMillis());
    }
    zzlv();
  }
  
  final void zza(int paramInt, Throwable paramThrowable, byte[] paramArrayOfByte, String paramString)
  {
    zzaf();
    zzlr();
    Object localObject = paramArrayOfByte;
    if (paramArrayOfByte == null) {}
    try
    {
      localObject = new byte[0];
      paramArrayOfByte = zzatu;
      zzatu = null;
      int j = 1;
      if (((paramInt == 200) || (paramInt == 204)) && (paramThrowable == null)) {
        try
        {
          zzadj.zzgp().zzane.set(zzadj.zzbx().currentTimeMillis());
          zzadj.zzgp().zzanf.set(0L);
          zzlv();
          zzadj.zzgo().zzjl().zze("Successful upload. Got network response. code, size", Integer.valueOf(paramInt), Integer.valueOf(localObject.length));
          zzjq().beginTransaction();
          try
          {
            paramThrowable = paramArrayOfByte.iterator();
            while (paramThrowable.hasNext())
            {
              paramArrayOfByte = (Long)paramThrowable.next();
              try
              {
                paramString = zzjq();
                long l = paramArrayOfByte.longValue();
                paramString.zzaf();
                paramString.zzcl();
                localObject = paramString.getWritableDatabase();
                try
                {
                  if (((SQLiteDatabase)localObject).delete("queue", "rowid=?", new String[] { String.valueOf(l) }) == 1) {
                    continue;
                  }
                  throw new SQLiteException("Deleted fewer rows from queue than expected");
                }
                catch (SQLiteException localSQLiteException)
                {
                  paramString.zzgo().zzjd().zzg("Failed to delete a bundle in a queue table", localSQLiteException);
                  throw localSQLiteException;
                }
                if (zzatv == null) {
                  break label269;
                }
              }
              catch (SQLiteException paramString) {}
              if (!zzatv.contains(paramArrayOfByte)) {
                label269:
                throw paramString;
              }
            }
            zzjq().setTransactionSuccessful();
            zzjq().endTransaction();
            zzatv = null;
            if ((zzlo().zzfb()) && (zzlu()))
            {
              zzlt();
            }
            else
            {
              zzatw = -1L;
              zzlv();
            }
            zzatl = 0L;
          }
          finally
          {
            zzjq().endTransaction();
          }
          zzadj.zzgo().zzjl().zze("Network upload failed. Will retry later. code, error", Integer.valueOf(paramInt), paramThrowable);
        }
        catch (SQLiteException paramThrowable)
        {
          zzadj.zzgo().zzjd().zzg("Database error while trying to delete uploaded bundles", paramThrowable);
          zzatl = zzadj.zzbx().elapsedRealtime();
          zzadj.zzgo().zzjl().zzg("Disable upload, time", Long.valueOf(zzatl));
        }
      }
      zzadj.zzgp().zzanf.set(zzadj.zzbx().currentTimeMillis());
      i = j;
      if (paramInt != 503)
      {
        if (paramInt != 429) {
          break label560;
        }
        i = j;
      }
    }
    finally
    {
      for (;;)
      {
        zzatq = false;
        zzlw();
        for (;;)
        {
          throw paramThrowable;
        }
        int i = 0;
      }
    }
    if (i != 0) {
      zzadj.zzgp().zzang.set(zzadj.zzbx().currentTimeMillis());
    }
    if (zzadj.zzgq().zzaz(paramString)) {
      zzjq().zzc(paramArrayOfByte);
    }
    zzlv();
    zzatq = false;
    zzlw();
  }
  
  public final byte[] zza(zzad paramZzad, String paramString)
  {
    zzlr();
    zzaf();
    zzadj.zzga();
    Preconditions.checkNotNull(paramZzad);
    Preconditions.checkNotEmpty(paramString);
    zzgh localZzgh = new zzgh();
    zzjq().beginTransaction();
    try
    {
      localZzg = zzjq().zzbl(paramString);
      if (localZzg == null)
      {
        zzadj.zzgo().zzjk().zzg("Log and bundle not available. package_name", paramString);
        zzjq().endTransaction();
        return new byte[0];
      }
      if (!localZzg.isMeasurementEnabled())
      {
        zzadj.zzgo().zzjk().zzg("Log and bundle disabled. package_name", paramString);
        zzjq().endTransaction();
        return new byte[0];
      }
      if ((("_iap".equals(name)) || ("ecommerce_purchase".equals(name))) && (!zza(paramString, paramZzad))) {
        zzadj.zzgo().zzjg().zzg("Failed to handle purchase event at single event bundle creation. appId", zzap.zzbv(paramString));
      }
      bool = zzadj.zzgq().zzax(paramString);
      localObject1 = Long.valueOf(0L);
      localObject2 = localObject1;
      if (bool)
      {
        localObject2 = localObject1;
        if ("_e".equals(name)) {
          if ((zzaid != null) && (zzaid.size() != 0))
          {
            if (zzaid.getLong("_et") == null)
            {
              zzadj.zzgo().zzjg().zzg("The engagement event does not include duration. appId", zzap.zzbv(paramString));
              localObject2 = localObject1;
            }
            else
            {
              localObject2 = zzaid.getLong("_et");
            }
          }
          else
          {
            zzadj.zzgo().zzjg().zzg("The engagement event does not contain any parameters. appId", zzap.zzbv(paramString));
            localObject2 = localObject1;
          }
        }
      }
      localZzgi = new zzgi();
      zzawy = new zzgi[] { localZzgi };
      zzaxa = Integer.valueOf(1);
      zzaxi = "android";
      zztt = localZzg.zzal();
      zzage = localZzg.zzhb();
      zzts = localZzg.zzak();
      l1 = localZzg.zzha();
      if (l1 == -2147483648L) {
        localObject1 = null;
      } else {
        localObject1 = Integer.valueOf((int)l1);
      }
      zzaxu = ((Integer)localObject1);
      zzaxm = Long.valueOf(localZzg.zzhc());
      zzafx = localZzg.getGmpAppId();
      if (TextUtils.isEmpty(zzafx)) {
        zzawj = localZzg.zzgw();
      }
      zzaxq = Long.valueOf(localZzg.zzhd());
      if ((zzadj.isEnabled()) && (zzn.zzhz()) && (zzadj.zzgq().zzav(zztt))) {
        zzaya = null;
      }
      localObject1 = zzadj.zzgp().zzby(localZzg.zzal());
      if ((localZzg.zzhr()) && (localObject1 != null) && (!TextUtils.isEmpty((CharSequence)first)))
      {
        zzaxo = ((String)first);
        zzaxp = ((Boolean)second);
      }
      zzadj.zzgk().zzcl();
      zzaxk = Build.MODEL;
      zzadj.zzgk().zzcl();
      zzaxj = Build.VERSION.RELEASE;
      zzaxl = Integer.valueOf((int)zzadj.zzgk().zzis());
      zzaia = zzadj.zzgk().zzit();
      zzafw = localZzg.getAppInstanceId();
      zzafz = localZzg.getFirebaseInstanceId();
      localList = zzjq().zzbk(localZzg.zzal());
      zzaxc = new zzgl[localList.size()];
      if (!bool) {
        break label1849;
      }
      localObject3 = zzjq().zzi(zztt, "_lte");
      if ((localObject3 != null) && (value != null))
      {
        localObject1 = localObject3;
        if (((Long)localObject2).longValue() > 0L) {
          localObject1 = new zzfj(zztt, "auto", "_lte", zzadj.zzbx().currentTimeMillis(), Long.valueOf(((Long)value).longValue() + ((Long)localObject2).longValue()));
        }
      }
      else
      {
        localObject1 = new zzfj(zztt, "auto", "_lte", zzadj.zzbx().currentTimeMillis(), localObject2);
      }
    }
    finally
    {
      for (;;)
      {
        zzg localZzg;
        boolean bool;
        Object localObject2;
        zzgi localZzgi;
        List localList;
        zzgl localZzgl;
        Object localObject4;
        long l2;
        zzjq().endTransaction();
        for (;;)
        {
          throw paramZzad;
        }
        Object localObject1 = null;
        int i = 0;
        Object localObject3 = null;
        continue;
        i += 1;
        localObject3 = localObject4;
        continue;
        continue;
        paramZzad = null;
        continue;
        long l1 = l2;
        continue;
        paramZzad = null;
      }
    }
    if (i < localList.size())
    {
      localZzgl = new zzgl();
      zzaxc[i] = localZzgl;
      name = getname;
      zzayl = Long.valueOf(getzzaue);
      zzjo().zza(localZzgl, getvalue);
      localObject4 = localObject3;
      if (bool)
      {
        localObject4 = localObject3;
        if ("_lte".equals(name))
        {
          zzawx = ((Long)value);
          zzayl = Long.valueOf(zzadj.zzbx().currentTimeMillis());
          localObject4 = localZzgl;
        }
      }
    }
    else
    {
      if ((!bool) || (localObject3 != null)) {
        break label1871;
      }
      localObject3 = new zzgl();
      name = "_lte";
      zzayl = Long.valueOf(zzadj.zzbx().currentTimeMillis());
      zzawx = ((Long)value);
      zzaxc = ((zzgl[])Arrays.copyOf(zzaxc, zzaxc.length + 1));
      zzaxc[(zzaxc.length - 1)] = localObject3;
      if (((Long)localObject2).longValue() > 0L) {
        zzjq().zza((zzfj)localObject1);
      }
      localObject1 = zzaid.zziv();
      bool = "_iap".equals(name);
      if (bool)
      {
        ((Bundle)localObject1).putLong("_c", 1L);
        zzadj.zzgo().zzjk().zzbx("Marking in-app purchase as real-time");
        ((Bundle)localObject1).putLong("_r", 1L);
      }
      ((Bundle)localObject1).putString("_o", origin);
      if (zzadj.zzgm().zzcw(zztt))
      {
        zzadj.zzgm().zza((Bundle)localObject1, "_dbg", Long.valueOf(1L));
        zzadj.zzgm().zza((Bundle)localObject1, "_r", Long.valueOf(1L));
      }
      localObject2 = zzjq().zzg(paramString, name);
      if (localObject2 == null)
      {
        localObject2 = new zzz(paramString, name, 1L, 0L, zzaip, 0L, null, null, null, null);
        zzjq().zza((zzz)localObject2);
        l1 = 0L;
      }
      else
      {
        l1 = zzaig;
        localObject2 = ((zzz)localObject2).zzai(zzaip).zziu();
        zzjq().zza((zzz)localObject2);
      }
      paramZzad = new zzy(zzadj, origin, paramString, name, zzaip, l1, (Bundle)localObject1);
      localObject1 = new zzgf();
      zzaxb = new zzgf[] { localObject1 };
      zzawu = Long.valueOf(timestamp);
      name = name;
      zzawv = Long.valueOf(zzaic);
      zzawt = new zzgg[zzaid.size()];
      localObject2 = zzaid.iterator();
      i = 0;
      while (((Iterator)localObject2).hasNext())
      {
        localObject4 = (String)((Iterator)localObject2).next();
        localObject3 = new zzgg();
        zzawt[i] = localObject3;
        name = ((String)localObject4);
        localObject4 = zzaid.get((String)localObject4);
        zzjo().zza((zzgg)localObject3, localObject4);
        i += 1;
      }
      zzaxt = zza(localZzg.zzal(), zzaxc, zzaxb);
      zzaxe = zzawu;
      zzaxf = zzawu;
      l1 = localZzg.zzgz();
      if (l1 == 0L) {
        break label1874;
      }
      paramZzad = Long.valueOf(l1);
      zzaxh = paramZzad;
      l2 = localZzg.zzgy();
      if (l2 != 0L) {
        break label1879;
      }
      if (l1 == 0L) {
        break label1886;
      }
      paramZzad = Long.valueOf(l1);
      zzaxg = paramZzad;
      localZzg.zzhh();
      zzaxr = Integer.valueOf((int)localZzg.zzhe());
      zzaxn = Long.valueOf(zzadj.zzgq().zzhc());
      zzaxd = Long.valueOf(zzadj.zzbx().currentTimeMillis());
      zzaxs = Boolean.TRUE;
      localZzg.zzs(zzaxe.longValue());
      localZzg.zzt(zzaxf.longValue());
      zzjq().zza(localZzg);
      zzjq().setTransactionSuccessful();
      zzjq().endTransaction();
      try
      {
        paramZzad = new byte[localZzgh.zzvu()];
        localObject1 = zzyy.zzk(paramZzad, 0, paramZzad.length);
        localZzgh.zza((zzyy)localObject1);
        ((zzyy)localObject1).zzyt();
        paramZzad = zzjo().zzb(paramZzad);
        return paramZzad;
      }
      catch (IOException paramZzad)
      {
        zzadj.zzgo().zzjd().zze("Data loss. Failed to bundle and serialize. appId", zzap.zzbv(paramString), paramZzad);
        return null;
      }
    }
  }
  
  final void zzb(zzez paramZzez)
  {
    zzatn += 1;
  }
  
  final void zzb(zzfh paramZzfh, zzh paramZzh)
  {
    zzaf();
    zzlr();
    if ((TextUtils.isEmpty(zzafx)) && (TextUtils.isEmpty(zzagk))) {
      return;
    }
    if (!zzagg)
    {
      zzg(paramZzh);
      return;
    }
    if ((zzadj.zzgq().zze(packageName, zzaf.zzalj)) && ("_ap".equals(name)))
    {
      localObject = zzjq().zzi(packageName, "_ap");
      if ((localObject != null) && ("auto".equals(origin)) && (!"auto".equals(origin)))
      {
        zzadj.zzgo().zzjk().zzbx("Not setting lower priority ad personalization property");
        return;
      }
    }
    int j = zzadj.zzgm().zzcs(name);
    int i;
    if (j != 0)
    {
      zzadj.zzgm();
      localObject = zzfk.zza(name, 24, true);
      if (name != null) {
        i = name.length();
      } else {
        i = 0;
      }
      zzadj.zzgm().zza(packageName, j, "_ev", (String)localObject, i);
      return;
    }
    j = zzadj.zzgm().zzi(name, paramZzfh.getValue());
    if (j != 0)
    {
      zzadj.zzgm();
      localObject = zzfk.zza(name, 24, true);
      paramZzfh = paramZzfh.getValue();
      if ((paramZzfh != null) && (((paramZzfh instanceof String)) || ((paramZzfh instanceof CharSequence)))) {
        i = String.valueOf(paramZzfh).length();
      } else {
        i = 0;
      }
      zzadj.zzgm().zza(packageName, j, "_ev", (String)localObject, i);
      return;
    }
    Object localObject = zzadj.zzgm().zzj(name, paramZzfh.getValue());
    if (localObject == null) {
      return;
    }
    paramZzfh = new zzfj(packageName, origin, name, zzaue, localObject);
    zzadj.zzgo().zzjk().zze("Setting user property", zzadj.zzgl().zzbu(name), localObject);
    zzjq().beginTransaction();
    try
    {
      zzg(paramZzh);
      boolean bool = zzjq().zza(paramZzfh);
      zzjq().setTransactionSuccessful();
      if (bool)
      {
        zzadj.zzgo().zzjk().zze("User property set", zzadj.zzgl().zzbu(name), value);
      }
      else
      {
        zzadj.zzgo().zzjd().zze("Too many unique user properties are set. Ignoring user property", zzadj.zzgl().zzbu(name), value);
        zzadj.zzgm().zza(packageName, 9, null, null, 0);
      }
      return;
    }
    finally
    {
      zzjq().endTransaction();
    }
  }
  
  final void zzb(zzl paramZzl, zzh paramZzh)
  {
    Preconditions.checkNotNull(paramZzl);
    Preconditions.checkNotEmpty(packageName);
    Preconditions.checkNotNull(origin);
    Preconditions.checkNotNull(zzahb);
    Preconditions.checkNotEmpty(zzahb.name);
    zzaf();
    zzlr();
    if ((TextUtils.isEmpty(zzafx)) && (TextUtils.isEmpty(zzagk))) {
      return;
    }
    if (!zzagg)
    {
      zzg(paramZzh);
      return;
    }
    paramZzl = new zzl(paramZzl);
    int i = 0;
    active = false;
    zzjq().beginTransaction();
    try
    {
      Object localObject = zzjq().zzj(packageName, zzahb.name);
      if ((localObject != null) && (!origin.equals(origin))) {
        zzadj.zzgo().zzjg().zzd("Updating a conditional user property with different origin. name, origin, origin (from DB)", zzadj.zzgl().zzbu(zzahb.name), origin, origin);
      }
      if ((localObject != null) && (active))
      {
        origin = origin;
        creationTimestamp = creationTimestamp;
        triggerTimeout = triggerTimeout;
        triggerEventName = triggerEventName;
        zzahd = zzahd;
        active = active;
        zzahb = new zzfh(zzahb.name, zzahb.zzaue, zzahb.getValue(), zzahb.origin);
      }
      else if (TextUtils.isEmpty(triggerEventName))
      {
        zzahb = new zzfh(zzahb.name, creationTimestamp, zzahb.getValue(), zzahb.origin);
        active = true;
        i = 1;
      }
      if (active)
      {
        localObject = zzahb;
        localObject = new zzfj(packageName, origin, name, zzaue, ((zzfh)localObject).getValue());
        if (zzjq().zza((zzfj)localObject)) {
          zzadj.zzgo().zzjk().zzd("User property updated immediately", packageName, zzadj.zzgl().zzbu(name), value);
        } else {
          zzadj.zzgo().zzjd().zzd("(2)Too many active user properties, ignoring", zzap.zzbv(packageName), zzadj.zzgl().zzbu(name), value);
        }
        if ((i != 0) && (zzahd != null)) {
          zzd(new zzad(zzahd, creationTimestamp), paramZzh);
        }
      }
      if (zzjq().zza(paramZzl)) {
        zzadj.zzgo().zzjk().zzd("Conditional property added", packageName, zzadj.zzgl().zzbu(zzahb.name), zzahb.getValue());
      } else {
        zzadj.zzgo().zzjd().zzd("Too many conditional properties, ignoring", zzap.zzbv(packageName), zzadj.zzgl().zzbu(zzahb.name), zzahb.getValue());
      }
      zzjq().setTransactionSuccessful();
      return;
    }
    finally
    {
      zzjq().endTransaction();
    }
  }
  
  final void zzb(String paramString, int paramInt, Throwable paramThrowable, byte[] paramArrayOfByte, Map<String, List<String>> paramMap)
  {
    zzaf();
    zzlr();
    Preconditions.checkNotEmpty(paramString);
    byte[] arrayOfByte = paramArrayOfByte;
    if (paramArrayOfByte == null) {}
    for (;;)
    {
      int i;
      try
      {
        arrayOfByte = new byte[0];
        zzadj.zzgo().zzjl().zzg("onConfigFetched. Response size", Integer.valueOf(arrayOfByte.length));
        zzjq().beginTransaction();
        try
        {
          paramArrayOfByte = zzjq().zzbl(paramString);
          j = 1;
          if ((paramInt == 200) || (paramInt == 204)) {
            break label545;
          }
          if (paramInt != 304) {
            break label555;
          }
        }
        finally
        {
          int j;
          boolean bool;
          zzjq().endTransaction();
        }
        if (paramArrayOfByte != null) {
          break label561;
        }
        zzadj.zzgo().zzjg().zzg("App does not exist in onConfigFetched. appId", zzap.zzbv(paramString));
        continue;
        paramArrayOfByte.zzz(zzadj.zzbx().currentTimeMillis());
        zzjq().zza(paramArrayOfByte);
        zzadj.zzgo().zzjl().zze("Fetching config failed. code, error", Integer.valueOf(paramInt), paramThrowable);
        zzln().zzch(paramString);
        zzadj.zzgp().zzanf.set(zzadj.zzbx().currentTimeMillis());
        i = j;
        if (paramInt != 503)
        {
          if (paramInt != 429) {
            break label576;
          }
          i = j;
        }
        if (i != 0) {
          zzadj.zzgp().zzang.set(zzadj.zzbx().currentTimeMillis());
        }
        zzlv();
        continue;
        if (paramMap == null) {
          break label582;
        }
        paramThrowable = (List)paramMap.get("Last-Modified");
        if ((paramThrowable == null) || (paramThrowable.size() <= 0)) {
          break label587;
        }
        paramThrowable = (String)paramThrowable.get(0);
        break label589;
        bool = zzln().zza(paramString, arrayOfByte, paramThrowable);
        if (!bool)
        {
          zzjq().endTransaction();
          return;
          if (zzln().zzcf(paramString) == null)
          {
            bool = zzln().zza(paramString, null, null);
            if (!bool)
            {
              zzjq().endTransaction();
              return;
            }
          }
        }
        paramArrayOfByte.zzy(zzadj.zzbx().currentTimeMillis());
        zzjq().zza(paramArrayOfByte);
        if (paramInt == 404) {
          zzadj.zzgo().zzji().zzg("Config not found. Using empty config. appId", paramString);
        } else {
          zzadj.zzgo().zzjl().zze("Successfully fetched config. Got network response. code, size", Integer.valueOf(paramInt), Integer.valueOf(arrayOfByte.length));
        }
        if ((zzlo().zzfb()) && (zzlu())) {
          zzlt();
        } else {
          zzlv();
        }
        zzjq().setTransactionSuccessful();
        zzjq().endTransaction();
        return;
      }
      finally
      {
        zzatp = false;
        zzlw();
      }
      label545:
      if (paramThrowable == null)
      {
        i = 1;
      }
      else
      {
        label555:
        i = 0;
        continue;
        label561:
        if (i == 0) {
          if (paramInt == 404)
          {
            continue;
            label576:
            i = 0;
            continue;
            label582:
            paramThrowable = null;
            continue;
            label587:
            paramThrowable = null;
            label589:
            if (paramInt != 404) {
              if (paramInt != 304) {}
            }
          }
        }
      }
    }
  }
  
  public final Clock zzbx()
  {
    return zzadj.zzbx();
  }
  
  final void zzc(zzad paramZzad, zzh paramZzh)
  {
    Preconditions.checkNotNull(paramZzh);
    Preconditions.checkNotEmpty(packageName);
    zzaf();
    zzlr();
    Object localObject2 = packageName;
    long l = zzaip;
    if (!zzjo().zze(paramZzad, paramZzh)) {
      return;
    }
    if (!zzagg)
    {
      zzg(paramZzh);
      return;
    }
    zzjq().beginTransaction();
    try
    {
      Object localObject1 = zzjq();
      Preconditions.checkNotEmpty((String)localObject2);
      ((zzco)localObject1).zzaf();
      ((zzez)localObject1).zzcl();
      if (l < 0L)
      {
        ((zzco)localObject1).zzgo().zzjg().zze("Invalid time querying timed out conditional properties", zzap.zzbv((String)localObject2), Long.valueOf(l));
        localObject1 = Collections.emptyList();
      }
      else
      {
        localObject1 = ((zzq)localObject1).zzb("active=0 and app_id=? and abs(? - creation_timestamp) > trigger_timeout", new String[] { localObject2, String.valueOf(l) });
      }
      localObject1 = ((List)localObject1).iterator();
      while (((Iterator)localObject1).hasNext())
      {
        localObject3 = (zzl)((Iterator)localObject1).next();
        if (localObject3 != null)
        {
          zzadj.zzgo().zzjk().zzd("User property timed out", packageName, zzadj.zzgl().zzbu(zzahb.name), zzahb.getValue());
          if (zzahc != null) {
            zzd(new zzad(zzahc, l), paramZzh);
          }
          zzjq().zzk((String)localObject2, zzahb.name);
        }
      }
      localObject1 = zzjq();
      Preconditions.checkNotEmpty((String)localObject2);
      ((zzco)localObject1).zzaf();
      ((zzez)localObject1).zzcl();
      if (l < 0L)
      {
        ((zzco)localObject1).zzgo().zzjg().zze("Invalid time querying expired conditional properties", zzap.zzbv((String)localObject2), Long.valueOf(l));
        localObject1 = Collections.emptyList();
      }
      else
      {
        localObject1 = ((zzq)localObject1).zzb("active<>0 and app_id=? and abs(? - triggered_timestamp) > time_to_live", new String[] { localObject2, String.valueOf(l) });
      }
      Object localObject3 = new ArrayList(((List)localObject1).size());
      localObject1 = ((List)localObject1).iterator();
      Object localObject4;
      while (((Iterator)localObject1).hasNext())
      {
        localObject4 = (zzl)((Iterator)localObject1).next();
        if (localObject4 != null)
        {
          zzadj.zzgo().zzjk().zzd("User property expired", packageName, zzadj.zzgl().zzbu(zzahb.name), zzahb.getValue());
          zzjq().zzh((String)localObject2, zzahb.name);
          if (zzahe != null) {
            ((List)localObject3).add(zzahe);
          }
          zzjq().zzk((String)localObject2, zzahb.name);
        }
      }
      localObject1 = (ArrayList)localObject3;
      int j = ((ArrayList)localObject1).size();
      int i = 0;
      while (i < j)
      {
        localObject3 = ((ArrayList)localObject1).get(i);
        i += 1;
        zzd(new zzad((zzad)localObject3, l), paramZzh);
      }
      localObject1 = zzjq();
      localObject3 = name;
      Preconditions.checkNotEmpty((String)localObject2);
      Preconditions.checkNotEmpty((String)localObject3);
      ((zzco)localObject1).zzaf();
      ((zzez)localObject1).zzcl();
      if (l < 0L)
      {
        ((zzco)localObject1).zzgo().zzjg().zzd("Invalid time querying triggered conditional properties", zzap.zzbv((String)localObject2), ((zzco)localObject1).zzgl().zzbs((String)localObject3), Long.valueOf(l));
        localObject1 = Collections.emptyList();
      }
      else
      {
        localObject1 = ((zzq)localObject1).zzb("active=0 and app_id=? and trigger_event_name=? and abs(? - creation_timestamp) <= trigger_timeout", new String[] { localObject2, localObject3, String.valueOf(l) });
      }
      localObject2 = new ArrayList(((List)localObject1).size());
      localObject1 = ((List)localObject1).iterator();
      while (((Iterator)localObject1).hasNext())
      {
        localObject3 = (zzl)((Iterator)localObject1).next();
        if (localObject3 != null)
        {
          localObject4 = zzahb;
          localObject4 = new zzfj(packageName, origin, name, l, ((zzfh)localObject4).getValue());
          if (zzjq().zza((zzfj)localObject4)) {
            zzadj.zzgo().zzjk().zzd("User property triggered", packageName, zzadj.zzgl().zzbu(name), value);
          } else {
            zzadj.zzgo().zzjd().zzd("Too many active user properties, ignoring", zzap.zzbv(packageName), zzadj.zzgl().zzbu(name), value);
          }
          if (zzahd != null) {
            ((List)localObject2).add(zzahd);
          }
          zzahb = new zzfh((zzfj)localObject4);
          active = true;
          zzjq().zza((zzl)localObject3);
        }
      }
      zzd(paramZzad, paramZzh);
      paramZzad = (ArrayList)localObject2;
      j = paramZzad.size();
      i = 0;
      while (i < j)
      {
        localObject1 = paramZzad.get(i);
        i += 1;
        zzd(new zzad((zzad)localObject1, l), paramZzh);
      }
      zzjq().setTransactionSuccessful();
      zzjq().endTransaction();
      return;
    }
    finally
    {
      zzjq().endTransaction();
    }
    for (;;)
    {
      throw paramZzad;
    }
  }
  
  final void zzc(zzad paramZzad, String paramString)
  {
    zzg localZzg = zzjq().zzbl(paramString);
    if ((localZzg != null) && (!TextUtils.isEmpty(localZzg.zzak())))
    {
      Boolean localBoolean = zzc(localZzg);
      if (localBoolean == null)
      {
        if (!"_ui".equals(name)) {
          zzadj.zzgo().zzjg().zzg("Could not find package. appId", zzap.zzbv(paramString));
        }
      }
      else if (!localBoolean.booleanValue())
      {
        zzadj.zzgo().zzjd().zzg("App version does not match; dropping event. appId", zzap.zzbv(paramString));
        return;
      }
      zzc(paramZzad, new zzh(paramString, localZzg.getGmpAppId(), localZzg.zzak(), localZzg.zzha(), localZzg.zzhb(), localZzg.zzhc(), localZzg.zzhd(), null, localZzg.isMeasurementEnabled(), false, localZzg.getFirebaseInstanceId(), localZzg.zzhq(), 0L, 0, localZzg.zzhr(), localZzg.zzhs(), false, localZzg.zzgw()));
      return;
    }
    zzadj.zzgo().zzjk().zzg("No app data available; dropping event", paramString);
  }
  
  final void zzc(zzfh paramZzfh, zzh paramZzh)
  {
    zzaf();
    zzlr();
    if ((TextUtils.isEmpty(zzafx)) && (TextUtils.isEmpty(zzagk))) {
      return;
    }
    if (!zzagg)
    {
      zzg(paramZzh);
      return;
    }
    if ((zzadj.zzgq().zze(packageName, zzaf.zzalj)) && ("_ap".equals(name)))
    {
      zzfj localZzfj = zzjq().zzi(packageName, "_ap");
      if ((localZzfj != null) && ("auto".equals(origin)) && (!"auto".equals(origin)))
      {
        zzadj.zzgo().zzjk().zzbx("Not removing higher priority ad personalization property");
        return;
      }
    }
    zzadj.zzgo().zzjk().zzg("Removing user property", zzadj.zzgl().zzbu(name));
    zzjq().beginTransaction();
    try
    {
      zzg(paramZzh);
      zzjq().zzh(packageName, name);
      zzjq().setTransactionSuccessful();
      zzadj.zzgo().zzjk().zzg("User property removed", zzadj.zzgl().zzbu(name));
      return;
    }
    finally
    {
      zzjq().endTransaction();
    }
  }
  
  final void zzc(zzl paramZzl, zzh paramZzh)
  {
    Preconditions.checkNotNull(paramZzl);
    Preconditions.checkNotEmpty(packageName);
    Preconditions.checkNotNull(zzahb);
    Preconditions.checkNotEmpty(zzahb.name);
    zzaf();
    zzlr();
    if ((TextUtils.isEmpty(zzafx)) && (TextUtils.isEmpty(zzagk))) {
      return;
    }
    if (!zzagg)
    {
      zzg(paramZzh);
      return;
    }
    zzjq().beginTransaction();
    try
    {
      zzg(paramZzh);
      zzl localZzl = zzjq().zzj(packageName, zzahb.name);
      if (localZzl != null)
      {
        zzadj.zzgo().zzjk().zze("Removing conditional user property", packageName, zzadj.zzgl().zzbu(zzahb.name));
        zzjq().zzk(packageName, zzahb.name);
        if (active) {
          zzjq().zzh(packageName, zzahb.name);
        }
        if (zzahe != null)
        {
          Bundle localBundle = null;
          if (zzahe.zzaid != null) {
            localBundle = zzahe.zzaid.zziv();
          }
          zzd(zzadj.zzgm().zza(packageName, zzahe.name, localBundle, origin, zzahe.zzaip, true, false), paramZzh);
        }
      }
      else
      {
        zzadj.zzgo().zzjg().zze("Conditional user property doesn't exist", zzap.zzbv(packageName), zzadj.zzgl().zzbu(zzahb.name));
      }
      zzjq().setTransactionSuccessful();
      return;
    }
    finally
    {
      zzjq().endTransaction();
    }
  }
  
  final void zzd(zzh paramZzh)
  {
    if (zzatu != null)
    {
      zzatv = new ArrayList();
      zzatv.addAll(zzatu);
    }
    Object localObject = zzjq();
    String str = packageName;
    Preconditions.checkNotEmpty(str);
    ((zzco)localObject).zzaf();
    ((zzez)localObject).zzcl();
    try
    {
      SQLiteDatabase localSQLiteDatabase = ((zzq)localObject).getWritableDatabase();
      String[] arrayOfString = new String[1];
      arrayOfString[0] = str;
      int i = localSQLiteDatabase.delete("apps", "app_id=?", arrayOfString) + 0 + localSQLiteDatabase.delete("events", "app_id=?", arrayOfString) + localSQLiteDatabase.delete("user_attributes", "app_id=?", arrayOfString) + localSQLiteDatabase.delete("conditional_properties", "app_id=?", arrayOfString) + localSQLiteDatabase.delete("raw_events", "app_id=?", arrayOfString) + localSQLiteDatabase.delete("raw_events_metadata", "app_id=?", arrayOfString) + localSQLiteDatabase.delete("queue", "app_id=?", arrayOfString) + localSQLiteDatabase.delete("audience_filter_values", "app_id=?", arrayOfString) + localSQLiteDatabase.delete("main_event_params", "app_id=?", arrayOfString);
      if (i > 0) {
        ((zzco)localObject).zzgo().zzjl().zze("Reset analytics data. app, records", str, Integer.valueOf(i));
      }
    }
    catch (SQLiteException localSQLiteException)
    {
      ((zzco)localObject).zzgo().zzjd().zze("Error resetting analytics data. appId, error", zzap.zzbv(str), localSQLiteException);
    }
    localObject = zza(zzadj.getContext(), packageName, zzafx, zzagg, zzagi, zzagj, zzagx, zzagk);
    if ((!zzadj.zzgq().zzbd(packageName)) || (zzagg)) {
      zzf((zzh)localObject);
    }
  }
  
  final void zze(zzh paramZzh)
  {
    zzaf();
    zzlr();
    Preconditions.checkNotEmpty(packageName);
    zzg(paramZzh);
  }
  
  final void zze(zzl paramZzl)
  {
    zzh localZzh = zzco(packageName);
    if (localZzh != null) {
      zzb(paramZzl, localZzh);
    }
  }
  
  final void zzf(zzh paramZzh)
  {
    zzaf();
    zzlr();
    Preconditions.checkNotNull(paramZzh);
    Preconditions.checkNotEmpty(packageName);
    if ((TextUtils.isEmpty(zzafx)) && (TextUtils.isEmpty(zzagk))) {
      return;
    }
    Object localObject1 = zzjq().zzbl(packageName);
    if ((localObject1 != null) && (TextUtils.isEmpty(((zzg)localObject1).getGmpAppId())) && (!TextUtils.isEmpty(zzafx)))
    {
      ((zzg)localObject1).zzy(0L);
      zzjq().zza((zzg)localObject1);
      zzln().zzci(packageName);
    }
    if (!zzagg)
    {
      zzg(paramZzh);
      return;
    }
    long l2 = zzagx;
    long l1 = l2;
    if (l2 == 0L) {
      l1 = zzadj.zzbx().currentTimeMillis();
    }
    int j = zzagy;
    int i = j;
    if (j != 0)
    {
      i = j;
      if (j != 1)
      {
        zzadj.zzgo().zzjg().zze("Incorrect app type, assuming installed app. appId, appType", zzap.zzbv(packageName), Integer.valueOf(j));
        i = 0;
      }
    }
    zzjq().beginTransaction();
    for (;;)
    {
      try
      {
        Object localObject3 = zzjq().zzbl(packageName);
        localObject1 = localObject3;
        if (localObject3 != null)
        {
          zzadj.zzgm();
          localObject1 = localObject3;
          if (zzfk.zza(zzafx, ((zzg)localObject3).getGmpAppId(), zzagk, ((zzg)localObject3).zzgw()))
          {
            zzadj.zzgo().zzjg().zzg("New GMP App Id passed in. Removing cached database data. appId", zzap.zzbv(((zzg)localObject3).zzal()));
            localObject1 = zzjq();
            localObject3 = ((zzg)localObject3).zzal();
            ((zzez)localObject1).zzcl();
            ((zzco)localObject1).zzaf();
            Preconditions.checkNotEmpty((String)localObject3);
            try
            {
              SQLiteDatabase localSQLiteDatabase = ((zzq)localObject1).getWritableDatabase();
              String[] arrayOfString = new String[1];
              arrayOfString[0] = localObject3;
              j = localSQLiteDatabase.delete("events", "app_id=?", arrayOfString) + 0 + localSQLiteDatabase.delete("user_attributes", "app_id=?", arrayOfString) + localSQLiteDatabase.delete("conditional_properties", "app_id=?", arrayOfString) + localSQLiteDatabase.delete("apps", "app_id=?", arrayOfString) + localSQLiteDatabase.delete("raw_events", "app_id=?", arrayOfString) + localSQLiteDatabase.delete("raw_events_metadata", "app_id=?", arrayOfString) + localSQLiteDatabase.delete("event_filters", "app_id=?", arrayOfString) + localSQLiteDatabase.delete("property_filters", "app_id=?", arrayOfString) + localSQLiteDatabase.delete("audience_filter_values", "app_id=?", arrayOfString);
              if (j <= 0) {
                break label1539;
              }
              ((zzco)localObject1).zzgo().zzjl().zze("Deleted application data. app, records", localObject3, Integer.valueOf(j));
            }
            catch (SQLiteException localSQLiteException)
            {
              ((zzco)localObject1).zzgo().zzjd().zze("Error deleting application data. appId, error", zzap.zzbv((String)localObject3), localSQLiteException);
            }
          }
        }
        if (localObject1 == null) {
          break label1545;
        }
        l2 = ((zzg)localObject1).zzha();
        if (l2 != -2147483648L)
        {
          if (((zzg)localObject1).zzha() == zzagd) {
            break label1545;
          }
          localObject3 = new Bundle();
          ((Bundle)localObject3).putString("_pv", ((zzg)localObject1).zzak());
          zzc(new zzad("_au", new zzaa((Bundle)localObject3), "auto", l1), paramZzh);
        }
        else if ((((zzg)localObject1).zzak() != null) && (!((zzg)localObject1).zzak().equals(zzts)))
        {
          localObject3 = new Bundle();
          ((Bundle)localObject3).putString("_pv", ((zzg)localObject1).zzak());
          zzc(new zzad("_au", new zzaa((Bundle)localObject3), "auto", l1), paramZzh);
        }
        zzg(paramZzh);
        if (i == 0)
        {
          localObject1 = zzjq().zzg(packageName, "_f");
        }
        else
        {
          if (i != 1) {
            break label1548;
          }
          localObject1 = zzjq().zzg(packageName, "_v");
        }
        if (localObject1 == null)
        {
          l2 = l1 / 3600000L;
          l2 = (l2 + 1L) * 3600000L;
          if (i == 0)
          {
            zzb(new zzfh("_fot", l1, Long.valueOf(l2), "auto"), paramZzh);
            if (zzadj.zzgq().zzbg(zzafx))
            {
              zzaf();
              zzadj.zzkg().zzcd(packageName);
            }
            zzaf();
            zzlr();
            localObject3 = new Bundle();
            ((Bundle)localObject3).putLong("_c", 1L);
            ((Bundle)localObject3).putLong("_r", 1L);
            ((Bundle)localObject3).putLong("_uwa", 0L);
            ((Bundle)localObject3).putLong("_pfo", 0L);
            ((Bundle)localObject3).putLong("_sys", 0L);
            ((Bundle)localObject3).putLong("_sysu", 0L);
            if ((zzadj.zzgq().zzbd(packageName)) && (zzagz)) {
              ((Bundle)localObject3).putLong("_dac", 1L);
            }
            if (zzadj.getContext().getPackageManager() == null)
            {
              zzadj.zzgo().zzjd().zzg("PackageManager is null, first open report might be inaccurate. appId", zzap.zzbv(packageName));
            }
            else
            {
              try
              {
                localObject1 = Wrappers.packageManager(zzadj.getContext());
                str = packageName;
                try
                {
                  localObject1 = ((PackageManagerWrapper)localObject1).getPackageInfo(str, 0);
                }
                catch (PackageManager.NameNotFoundException localNameNotFoundException1) {}
                zzadj.zzgo().zzjd().zze("Package info is null, first open report might be inaccurate. appId", zzap.zzbv(packageName), localNameNotFoundException2);
              }
              catch (PackageManager.NameNotFoundException localNameNotFoundException2) {}
              ApplicationInfo localApplicationInfo = null;
              if ((localApplicationInfo != null) && (firstInstallTime != 0L))
              {
                if (firstInstallTime == lastUpdateTime) {
                  break label1554;
                }
                ((Bundle)localObject3).putLong("_uwa", 1L);
                i = 0;
                if (i == 0) {
                  break label1559;
                }
                l2 = 1L;
                zzb(new zzfh("_fi", l1, Long.valueOf(l2), "auto"), paramZzh);
              }
              try
              {
                localApplicationInfo = Wrappers.packageManager(zzadj.getContext()).getApplicationInfo(packageName, 0);
              }
              catch (PackageManager.NameNotFoundException localNameNotFoundException3)
              {
                zzadj.zzgo().zzjd().zze("Application info is null, first open report might be inaccurate. appId", zzap.zzbv(packageName), localNameNotFoundException3);
                localObject2 = null;
              }
              if (localObject2 != null)
              {
                if ((flags & 0x1) != 0) {
                  ((Bundle)localObject3).putLong("_sys", 1L);
                }
                if ((flags & 0x80) != 0) {
                  ((Bundle)localObject3).putLong("_sysu", 1L);
                }
              }
            }
            localObject2 = zzjq();
            String str = packageName;
            Preconditions.checkNotEmpty(str);
            ((zzco)localObject2).zzaf();
            ((zzez)localObject2).zzcl();
            l2 = ((zzq)localObject2).zzn(str, "first_open_count");
            if (l2 >= 0L) {
              ((Bundle)localObject3).putLong("_pfo", l2);
            }
            zzc(new zzad("_f", new zzaa((Bundle)localObject3), "auto", l1), paramZzh);
          }
          else if (i == 1)
          {
            zzb(new zzfh("_fvt", l1, Long.valueOf(l2), "auto"), paramZzh);
            zzaf();
            zzlr();
            localObject2 = new Bundle();
            ((Bundle)localObject2).putLong("_c", 1L);
            ((Bundle)localObject2).putLong("_r", 1L);
            if ((zzadj.zzgq().zzbd(packageName)) && (zzagz)) {
              ((Bundle)localObject2).putLong("_dac", 1L);
            }
            zzc(new zzad("_v", new zzaa((Bundle)localObject2), "auto", l1), paramZzh);
          }
          localObject2 = new Bundle();
          ((Bundle)localObject2).putLong("_et", 1L);
          zzc(new zzad("_e", new zzaa((Bundle)localObject2), "auto", l1), paramZzh);
        }
        else if (zzagw)
        {
          zzc(new zzad("_cd", new zzaa(new Bundle()), "auto", l1), paramZzh);
        }
        zzjq().setTransactionSuccessful();
        return;
      }
      finally
      {
        zzjq().endTransaction();
      }
      label1539:
      Object localObject2 = null;
      continue;
      label1545:
      continue;
      label1548:
      localObject2 = null;
      continue;
      label1554:
      i = 1;
      continue;
      label1559:
      l2 = 0L;
    }
  }
  
  final void zzf(zzl paramZzl)
  {
    zzh localZzh = zzco(packageName);
    if (localZzh != null) {
      zzc(paramZzl, localZzh);
    }
  }
  
  final void zzg(Runnable paramRunnable)
  {
    zzaf();
    if (zzatm == null) {
      zzatm = new ArrayList();
    }
    zzatm.add(paramRunnable);
  }
  
  public final zzan zzgl()
  {
    return zzadj.zzgl();
  }
  
  public final zzfk zzgm()
  {
    return zzadj.zzgm();
  }
  
  public final zzbo zzgn()
  {
    return zzadj.zzgn();
  }
  
  public final zzap zzgo()
  {
    return zzadj.zzgo();
  }
  
  public final zzn zzgq()
  {
    return zzadj.zzgq();
  }
  
  public final zzk zzgr()
  {
    return zzadj.zzgr();
  }
  
  final String zzh(zzh paramZzh)
  {
    Object localObject = zzadj.zzgn().zzb(new zzfe(this, paramZzh));
    try
    {
      localObject = (String)((Future)localObject).get(30000L, TimeUnit.MILLISECONDS);
      return localObject;
    }
    catch (ExecutionException localExecutionException) {}catch (InterruptedException localInterruptedException) {}catch (TimeoutException localTimeoutException) {}
    zzadj.zzgo().zzjd().zze("Failed to get app instance id. appId", zzap.zzbv(packageName), localTimeoutException);
    return null;
  }
  
  public final zzfg zzjo()
  {
    zza(zzatj);
    return zzatj;
  }
  
  public final zzj zzjp()
  {
    zza(zzati);
    return zzati;
  }
  
  public final zzq zzjq()
  {
    zza(zzatf);
    return zzatf;
  }
  
  public final zzat zzlo()
  {
    zza(zzate);
    return zzate;
  }
  
  final void zzlr()
  {
    if (zzvz) {
      return;
    }
    throw new IllegalStateException("UploadController is not initialized");
  }
  
  final void zzlt()
  {
    zzaf();
    zzlr();
    zzatr = true;
    try
    {
      zzadj.zzgr();
      localObject1 = zzadj.zzgg().zzle();
      if (localObject1 == null)
      {
        zzadj.zzgo().zzjg().zzbx("Upload data called on the client side before use of service was decided");
        zzatr = false;
        zzlw();
        return;
      }
      if (((Boolean)localObject1).booleanValue())
      {
        zzadj.zzgo().zzjd().zzbx("Upload called in the client side when service should be used");
        zzatr = false;
        zzlw();
        return;
      }
      if (zzatl > 0L)
      {
        zzlv();
        zzatr = false;
        zzlw();
        return;
      }
      zzaf();
      if (zzatu == null) {
        break label1100;
      }
      i = 1;
    }
    finally
    {
      for (;;)
      {
        Object localObject1;
        long l1;
        long l2;
        String str1;
        String str2;
        int j;
        Object localObject5;
        Object localObject6;
        boolean bool;
        zzatr = false;
        zzlw();
        for (;;)
        {
          throw localObject2;
        }
        int i = 0;
        continue;
        Object localObject4 = null;
        Object localObject3 = localObject5;
        if (localObject4 != null)
        {
          i = 0;
          continue;
          i += 1;
          continue;
          i = 0;
          j = 0;
          continue;
          j += 1;
          continue;
          bool = false;
        }
      }
    }
    if (i != 0)
    {
      zzadj.zzgo().zzjl().zzbx("Uploading requested multiple times");
      zzatr = false;
      zzlw();
      return;
    }
    if (!zzlo().zzfb())
    {
      zzadj.zzgo().zzjl().zzbx("Network not connected, ignoring upload request");
      zzlv();
      zzatr = false;
      zzlw();
      return;
    }
    l1 = zzadj.zzbx().currentTimeMillis();
    l2 = zzn.zzhx();
    str1 = null;
    zzd(null, l1 - l2);
    l2 = zzadj.zzgp().zzane.get();
    if (l2 != 0L) {
      zzadj.zzgo().zzjk().zzg("Uploading events. Elapsed time since last upload attempt (ms)", Long.valueOf(Math.abs(l1 - l2)));
    }
    str2 = zzjq().zzid();
    if (!TextUtils.isEmpty(str2))
    {
      if (zzatw == -1L) {
        zzatw = zzjq().zzik();
      }
      i = zzadj.zzgq().zzb(str2, zzaf.zzajj);
      j = Math.max(0, zzadj.zzgq().zzb(str2, zzaf.zzajk));
      localObject5 = zzjq().zzb(str2, i, j);
      if (((List)localObject5).isEmpty()) {
        break label1065;
      }
      localObject1 = ((List)localObject5).iterator();
      do
      {
        if (!((Iterator)localObject1).hasNext()) {
          break;
        }
        localObject4 = (zzgi)nextfirst;
      } while (TextUtils.isEmpty(zzaxo));
      localObject4 = zzaxo;
      break label1108;
      localObject1 = localObject5;
      if (i < ((List)localObject5).size())
      {
        localObject1 = (zzgi)getfirst;
        if ((TextUtils.isEmpty(zzaxo)) || (zzaxo.equals(localObject4))) {
          break label1122;
        }
        localObject1 = ((List)localObject5).subList(0, i);
      }
      localObject5 = new zzgh();
      zzawy = new zzgi[((List)localObject1).size()];
      localObject4 = new ArrayList(((List)localObject1).size());
      if ((!zzn.zzhz()) || (!zzadj.zzgq().zzav(str2))) {
        break label1129;
      }
      i = 1;
      break label1131;
      if (j < zzawy.length)
      {
        zzawy[j] = ((zzgi)getfirst);
        ((List)localObject4).add((Long)getsecond);
        zzawy[j].zzaxn = Long.valueOf(zzadj.zzgq().zzhc());
        zzawy[j].zzaxd = Long.valueOf(l1);
        localObject6 = zzawy[j];
        zzadj.zzgr();
        zzaxs = Boolean.valueOf(false);
        if (i != 0) {
          break label1136;
        }
        zzawy[j].zzaya = null;
        break label1136;
      }
      localObject1 = str1;
      if (zzadj.zzgo().isLoggable(2)) {
        localObject1 = zzjo().zzb((zzgh)localObject5);
      }
      localObject6 = zzjo().zza((zzgh)localObject5);
      str1 = (String)zzaf.zzajt.get();
    }
    try
    {
      URL localURL = new URL(str1);
      if (((List)localObject4).isEmpty()) {
        break label1143;
      }
      bool = true;
      Preconditions.checkArgument(bool);
      if (zzatu != null) {
        zzadj.zzgo().zzjd().zzbx("Set uploading progress before finishing the previous upload");
      } else {
        zzatu = new ArrayList((Collection)localObject4);
      }
      zzadj.zzgp().zzanf.set(l1);
      localObject4 = "?";
      if (zzawy.length > 0) {
        localObject4 = zzawy[0].zztt;
      }
      zzadj.zzgo().zzjl().zzd("Uploading data. app, uncompressed size, data", localObject4, Integer.valueOf(localObject6.length), localObject1);
      zzatq = true;
      localObject1 = zzlo();
      localObject4 = new zzfc(this, str2);
      ((zzco)localObject1).zzaf();
      ((zzez)localObject1).zzcl();
      Preconditions.checkNotNull(localURL);
      Preconditions.checkNotNull(localObject6);
      Preconditions.checkNotNull(localObject4);
      ((zzco)localObject1).zzgn().zzd(new zzax((zzat)localObject1, str2, localURL, (byte[])localObject6, null, (zzav)localObject4));
    }
    catch (MalformedURLException localMalformedURLException)
    {
      for (;;) {}
    }
    zzadj.zzgo().zzjd().zze("Failed to parse upload URL. Not uploading. appId", zzap.zzbv(str2), str1);
    break label1065;
    zzatw = -1L;
    localObject1 = zzjq().zzah(l1 - zzn.zzhx());
    if (!TextUtils.isEmpty((CharSequence)localObject1))
    {
      localObject1 = zzjq().zzbl((String)localObject1);
      if (localObject1 != null) {
        zzb((zzg)localObject1);
      }
    }
    label1065:
    zzatr = false;
    zzlw();
  }
  
  final void zzly()
  {
    zzaf();
    zzlr();
    if (!zzatk)
    {
      zzadj.zzgo().zzjj().zzbx("This instance being marked as an uploader");
      zzaf();
      zzlr();
      if ((zzlz()) && (zzlx()))
      {
        int i = zza(zzatt);
        int j = zzadj.zzgf().zzja();
        zzaf();
        if (i > j) {
          zzadj.zzgo().zzjd().zze("Panic: can't downgrade version. Previous, current version", Integer.valueOf(i), Integer.valueOf(j));
        } else if (i < j) {
          if (zza(j, zzatt)) {
            zzadj.zzgo().zzjl().zze("Storage version upgraded. Previous, current version", Integer.valueOf(i), Integer.valueOf(j));
          } else {
            zzadj.zzgo().zzjd().zze("Storage version upgrade failed. Previous, current version", Integer.valueOf(i), Integer.valueOf(j));
          }
        }
      }
      zzatk = true;
      zzlv();
    }
  }
  
  final void zzma()
  {
    zzato += 1;
  }
  
  final zzbt zzmb()
  {
    return zzadj;
  }
  
  final void zzo(boolean paramBoolean)
  {
    zzlv();
  }
  
  final class zza
    implements zzs
  {
    zzgi zzaua;
    List<Long> zzaub;
    List<zzgf> zzauc;
    private long zzaud;
    
    private zza() {}
    
    private static long zza(zzgf paramZzgf)
    {
      return zzawu.longValue() / 1000L / 60L / 60L;
    }
    
    public final boolean zza(long paramLong, zzgf paramZzgf)
    {
      Preconditions.checkNotNull(paramZzgf);
      if (zzauc == null) {
        zzauc = new ArrayList();
      }
      if (zzaub == null) {
        zzaub = new ArrayList();
      }
      if ((zzauc.size() > 0) && (zza((zzgf)zzauc.get(0)) != zza(paramZzgf))) {
        return false;
      }
      long l = zzaud + paramZzgf.zzvu();
      if (l >= Math.max(0, ((Integer)zzaf.zzajl.get()).intValue())) {
        return false;
      }
      zzaud = l;
      zzauc.add(paramZzgf);
      zzaub.add(Long.valueOf(paramLong));
      return zzauc.size() < Math.max(1, ((Integer)zzaf.zzajm.get()).intValue());
    }
    
    public final void zzb(zzgi paramZzgi)
    {
      Preconditions.checkNotNull(paramZzgi);
      zzaua = paramZzgi;
    }
  }
}
